Workbook

Sheet Start
B2: MAANDBUDGET
B3: Klik op een tegel om te beginnen. Alle bedragen in dit sjabloon zijn voorbeelden.
B5: INVULLEN — wekelijks | C5: BEKIJKEN — vult zichzelf | D5: EENMALIG INSTELLEN
B6: TRANSACTIES | C6: DASHBOARD | D6: VASTE LASTEN
B7: noteer een uitgave of inkomst | C7: je maand in één oogopslag | D7: alles wat maandelijks terugkeert
B9: Dit is 90% van je gebruik: | C9: CATEGORIEËN | D9: VASTE INKOMSTEN
B10: uitgave erbij → Transacties, | C10: begroot tegenover werkelijk | D10: salaris en vaste inkomsten
B11: daarna kijken → Dashboard.
C12: JAAROVERZICHT | D12: SCHULDEN
C13: alle maanden naast elkaar | D13: saldo, rente en aflossing
D15: LIJSTEN
D16: keuzelijsten — zelden nodig
B18: ZO ZIT HET IN ELKAAR
B19: • Elk bedrag staat op precies één tabblad — nooit twee keer invullen.
B20: • Vaste lasten, inkomsten en schulden vul je één keer in; daarna draait alles vanzelf.
B21: • Kwartaal- of jaarrekening? Kies de frequentie en betaalmaand; het maandbedrag volgt automatisch.
B22: • Op elk tabblad staat rechtsboven een knop terug naar dit menu.
B24: KLEUREN
B25: Aa | C25: Geel = hier vul je iets in
B26: Aa | C26: Paars = berekend voor de gekozen maand
B27: Aa | C27: Grijs = categorie (nog) niet in gebruik
B29: Formules staan in alle niet-gekleurde cellen — laat die met rust. Kapotgemaakt? Download het origineel opnieuw.

Sheet Dashboard
N1: maandnr
B2: DASHBOARD | E2: ⌂ Menu | N2: =IFERROR(MATCH($C$5,Lijsten!$K$6:$K$17,0),1) -> 8
B3: Alleen cijfers en signalen. Invoeren doe je op de andere tabbladen; het detail per categorie staat op Categorieën. | N3: sleutel
B4: Weergave | C4: Gemiddeld per maand | D4: Jaar- en kwartaalposten uitsmeren, of tonen in de maand van afschrijving | N4: =$E$5*100+$N$2 -> 202608
B5: Maand | C5: augustus | D5: Jaar | E5: 2026
B7: INKOMSTEN | C7: UITGAVEN | E7: OVER
B9: =SUMIFS('Vaste inkomsten'!$J$8:$J$37,'Vaste inkomsten'!$H$8:$H$37,"Ja")+SUMIFS(Transacties!$D$8:$D$507,Transacties!$H$8:$H$507,$N$4,Transacties!$E$8:$E$507,"Inkomst") -> 2800 | C9: =SUMIFS('Vaste lasten'!$J$8:$J$207,'Vaste lasten'!$H$8:$H$207,"Ja")+SUMIFS(Schulden!$E$8:$E$37,Schulden!$G$8:$G$37,"Ja")+SUMIFS(Transacties!$D$8:$D$507,Transacties!$H$8:$H$507,$N$4)-SUMIFS(Transacties!$D$8:$D$507,Transacties!$H$8:$H$507,$N$4,Transacties!$E$8:$E$507,"Inkomst") -> 1202.3 | E9: =$B$9-$C$9 -> 1597.7
B11: KENGETALLEN DEZE MAAND
B12: Deel van je inkomen dat overblijft | C12: =IFERROR($E$9/$B$9,"") -> 0.57060714 | D12: Vuistregel: 10% of meer
B13: Vaste lasten | C13: =SUMIFS('Vaste lasten'!$J$8:$J$207,'Vaste lasten'!$H$8:$H$207,"Ja") -> 950 | D13: Huur, verzekeringen, abonnementen
B14: Schuldtermijnen | C14: =SUMIFS(Schulden!$E$8:$E$37,Schulden!$G$8:$G$37,"Ja") -> 190 | D14: Komt van tabblad Schulden
B15: Variabele uitgaven | C15: =SUMIFS(Transacties!$D$8:$D$507,Transacties!$H$8:$H$507,$N$4)-SUMIFS(Transacties!$D$8:$D$507,Transacties!$H$8:$H$507,$N$4,Transacties!$E$8:$E$507,"Inkomst") -> 62.3 | D15: Alles uit Transacties
B16: Vaste lasten als deel van inkomen | C16: =IFERROR((SUMIFS('Vaste lasten'!$J$8:$J$207,'Vaste lasten'!$H$8:$H$207,"Ja")+SUMIFS(Schulden!$E$8:$E$37,Schulden!$G$8:$G$37,"Ja"))/$B$9,"") -> 0.40714286 | D16: Onder 50% is comfortabel
B17: Opzij gezet | C17: =SUMIFS('Vaste lasten'!$J$8:$J$207,'Vaste lasten'!$G$8:$G$207,"Sparen & reserveringen",'Vaste lasten'!$H$8:$H$207,"Ja")+SUMIFS(Transacties!$D$8:$D$507,Transacties!$H$8:$H$507,$N$4,Transacties!$B$8:$B$507,"Sparen & reserveringen") -> 0 | D17: Categorie Sparen & reserveringen
B18: Actieve vaste lasten | C18: =COUNTIF('Vaste lasten'!$H$8:$H$207,"Ja")&" regels" -> 2 regels | D18: Op tabblad Vaste lasten
B20: GROOTSTE UITGAVEN DEZE MAAND
B21: =IFERROR(IF(LARGE(Categorieën!$I$26:$I$55,1)<=0,"",INDEX(Categorieën!$B$26:$B$55,MATCH(LARGE(Categorieën!$I$26:$I$55,1),Categorieën!$I$26:$I$55,0))),"") -> Wonen | C21: =IFERROR(IF(LARGE(Categorieën!$I$26:$I$55,1)<=0,"",INDEX(Categorieën!$E$26:$E$55,MATCH(LARGE(Categorieën!$I$26:$I$55,1),Categorieën!$I$26:$I$55,0))),"") -> 900 | D21: =IF($C21="","",IFERROR($C21/$C$9,"")) -> 0.74856525
B22: =IFERROR(IF(LARGE(Categorieën!$I$26:$I$55,2)<=0,"",INDEX(Categorieën!$B$26:$B$55,MATCH(LARGE(Categorieën!$I$26:$I$55,2),Categorieën!$I$26:$I$55,0))),"") -> Schulden & aflossingen | C22: =IFERROR(IF(LARGE(Categorieën!$I$26:$I$55,2)<=0,"",INDEX(Categorieën!$E$26:$E$55,MATCH(LARGE(Categorieën!$I$26:$I$55,2),Categorieën!$I$26:$I$55,0))),"") -> 190 | D22: =IF($C22="","",IFERROR($C22/$C$9,"")) -> 0.15803044
B23: =IFERROR(IF(LARGE(Categorieën!$I$26:$I$55,3)<=0,"",INDEX(Categorieën!$B$26:$B$55,MATCH(LARGE(Categorieën!$I$26:$I$55,3),Categorieën!$I$26:$I$55,0))),"") -> Boodschappen & eten | C23: =IFERROR(IF(LARGE(Categorieën!$I$26:$I$55,3)<=0,"",INDEX(Categorieën!$E$26:$E$55,MATCH(LARGE(Categorieën!$I$26:$I$55,3),Categorieën!$I$26:$I$55,0))),"") -> 62.3 | D23: =IF($C23="","",IFERROR($C23/$C$9,"")) -> 0.05181735
B24: =IFERROR(IF(LARGE(Categorieën!$I$26:$I$55,4)<=0,"",INDEX(Categorieën!$B$26:$B$55,MATCH(LARGE(Categorieën!$I$26:$I$55,4),Categorieën!$I$26:$I$55,0))),"") -> Auto & vervoer | C24: =IFERROR(IF(LARGE(Categorieën!$I$26:$I$55,4)<=0,"",INDEX(Categorieën!$E$26:$E$55,MATCH(LARGE(Categorieën!$I$26:$I$55,4),Categorieën!$I$26:$I$55,0))),"") -> 50 | D24: =IF($C24="","",IFERROR($C24/$C$9,"")) -> 0.041586958
B25: =IFERROR(IF(LARGE(Categorieën!$I$26:$I$55,5)<=0,"",INDEX(Categorieën!$B$26:$B$55,MATCH(LARGE(Categorieën!$I$26:$I$55,5),Categorieën!$I$26:$I$55,0))),"") -> Overig | C25: =IFERROR(IF(LARGE(Categorieën!$I$26:$I$55,5)<=0,"",INDEX(Categorieën!$E$26:$E$55,MATCH(LARGE(Categorieën!$I$26:$I$55,5),Categorieën!$I$26:$I$55,0))),"") -> 0 | D25: =IF($C25="","",IFERROR($C25/$C$9,"")) -> 0
B26: Percentage = aandeel in je totale uitgaven deze maand.
B28: SCHULDEN
B29: Totale schuld | C29: =Schulden!$C$5 -> 15000
B30: Maandlast | C30: =Schulden!$E$5 -> 190
B31: Schuldenvrij rond | C31: =IF(Schulden!$H$5="","nog invullen",Schulden!$H$5) -> 48907
B32: Aflosvolgorde en einddatums staan op tabblad Schulden.
B34: DIT JAAR
B35: Verwacht over aan het eind van het jaar | C35: =Jaaroverzicht!$F$19 -> 19857.7
B36: Duurste maand | C36: =IFERROR(INDEX(Jaaroverzicht!$B$8:$B$19,MATCH(MAX(Jaaroverzicht!$D$8:$D$19),Jaaroverzicht!$D$8:$D$19,0)),"") -> augustus
B37: Uitgaven in die maand | C37: =IFERROR(MAX(Jaaroverzicht!$D$8:$D$19),"") -> 1202.3
B39: SIGNALEN
B40: =IF($B$9=0,"Vul eerst je vaste inkomsten in.",IF($C$16>0.6,"Meer dan 60% van je inkomen gaat naar vaste lasten en schulden. Dat is veel — je grootste posten staan hierboven.",IF($C$16>0.4,"Je vaste lasten en schulden zitten tussen 40% en 60% van je inkomen. Dat is gangbaar.","Je vaste lasten en schulden blijven onder 40% van je inkomen. Comfortabel."))) -> Je vaste lasten en schulden zitten tussen 40% en 60% van je inkomen. Dat is gangbaar.
B41: =IF($B$9=0,"",IF($C$17/$B$9<0.1,"Je zet minder dan 10% van je inkomen opzij. Een vaste overboeking direct na je salaris werkt beter dan sparen wat overblijft.","Je spaardoel van 10% haal je deze maand.")) -> Je zet minder dan 10% van je inkomen opzij. Een vaste overboeking direct na je salaris werkt beter dan sparen wat overblijft.
B42: =IF($E$9<0,"Je geeft deze maand meer uit dan er binnenkomt. Kijk bij de grootste uitgaven hierboven.","")
B43: =IF(Schulden!$C$5=0,"Vul je openstaande schuldsaldo in op tabblad Schulden — dan zie je wanneer je schuldenvrij bent.","Extra aflossen? Begin bij prioriteit 1 op tabblad Schulden; dat is de hoogste rente.") -> Extra aflossen? Begin bij prioriteit 1 op tabblad Schulden; dat is de hoogste rente.
B44: =IF(COUNTIF(Transacties!$A$8:$A$507,"<>")=0,"Nog geen transacties ingevuld. Zonder die regels blijft je variabele budget een schatting.","")
B46: WAAR VUL IK WAT IN?
B47: Vaste lasten → alles wat terugkeert, met je eigen naam per regel. 200 regels beschikbaar.
B48: Vaste inkomsten → salaris en andere vaste inkomsten.
B49: Schulden → openstaande schulden; de maandtermijn telt automatisch mee als vaste last.
B50: Transacties → alleen wat wisselt: boodschappen, tanken, uit eten, losse inkomsten.
B51: Categorieën → begroot tegenover werkelijk per categorie, plus je variabele budgetten.
B52: Lijsten → alleen keuzelijsten: categorieën, bedrijven, schuldeisers, betaalmethoden.
B53: Weergave bovenaan: uitsmeren over het jaar, of tonen in de maand van afschrijving.

Sheet Categorieën
B2: CATEGORIEËN | E2: ⌂ Menu | F2: Dashboard ▸
B3: Begroot tegenover werkelijk, per categorie, voor de maand die op het Dashboard staat.
B4: ="Maand: "&Dashboard!$C$5&" "&Dashboard!$E$5&" · Weergave: "&Dashboard!$C$4 -> Maand: augustus 2026 · Weergave: Gemiddeld per maand
B12: Optelling van tabblad Vaste inkomsten + losse inkomsten uit Transacties. Hier vul je niets in.
B13: INKOMSTEN
B14: Categorie | C14: Budget variabel | D14: Begroot totaal | E14: Werkelijk | F14: Verschil | G14: % budget
B15: =IF(INDEX(Lijsten!$A$6:$A$12,1)="","",INDEX(Lijsten!$A$6:$A$12,1)) -> Salaris | D15: =IF($B15="","",SUMIFS('Vaste inkomsten'!$J$8:$J$37,'Vaste inkomsten'!$G$8:$G$37,$B15,'Vaste inkomsten'!$H$8:$H$37,"Ja")) -> 2800 | E15: =IF($B15="","",SUMIFS('Vaste inkomsten'!$J$8:$J$37,'Vaste inkomsten'!$G$8:$G$37,$B15,'Vaste inkomsten'!$H$8:$H$37,"Ja")+SUMIFS(Transacties!$D$8:$D$507,Transacties!$H$8:$H$507,Dashboard!$N$4,Transacties!$B$8:$B$507,$B15)) -> 2800 | F15: =IF($B15="","",$E15-$D15) -> 0 | G15: =IF(OR($B15="",$D15=0),"",$E15/$D15) -> 1 | I15: =IF($B15="",-1,$E15+ROW()/100000) -> 2800.0001
B16: =IF(INDEX(Lijsten!$A$6:$A$12,2)="","",INDEX(Lijsten!$A$6:$A$12,2)) -> Vakantiegeld | D16: =IF($B16="","",SUMIFS('Vaste inkomsten'!$J$8:$J$37,'Vaste inkomsten'!$G$8:$G$37,$B16,'Vaste inkomsten'!$H$8:$H$37,"Ja")) -> 0 | E16: =IF($B16="","",SUMIFS('Vaste inkomsten'!$J$8:$J$37,'Vaste inkomsten'!$G$8:$G$37,$B16,'Vaste inkomsten'!$H$8:$H$37,"Ja")+SUMIFS(Transacties!$D$8:$D$507,Transacties!$H$8:$H$507,Dashboard!$N$4,Transacties!$B$8:$B$507,$B16)) -> 0 | F16: =IF($B16="","",$E16-$D16) -> 0 | G16: =IF(OR($B16="",$D16=0),"",$E16/$D16) | I16: =IF($B16="",-1,$E16+ROW()/100000) -> 0.00016
B17: =IF(INDEX(Lijsten!$A$6:$A$12,3)="","",INDEX(Lijsten!$A$6:$A$12,3)) -> Bonus / extra werk | D17: =IF($B17="","",SUMIFS('Vaste inkomsten'!$J$8:$J$37,'Vaste inkomsten'!$G$8:$G$37,$B17,'Vaste inkomsten'!$H$8:$H$37,"Ja")) -> 0 | E17: =IF($B17="","",SUMIFS('Vaste inkomsten'!$J$8:$J$37,'Vaste inkomsten'!$G$8:$G$37,$B17,'Vaste inkomsten'!$H$8:$H$37,"Ja")+SUMIFS(Transacties!$D$8:$D$507,Transacties!$H$8:$H$507,Dashboard!$N$4,Transacties!$B$8:$B$507,$B17)) -> 0 | F17: =IF($B17="","",$E17-$D17) -> 0 | G17: =IF(OR($B17="",$D17=0),"",$E17/$D17) | I17: =IF($B17="",-1,$E17+ROW()/100000) -> 0.00017
B18: =IF(INDEX(Lijsten!$A$6:$A$12,4)="","",INDEX(Lijsten!$A$6:$A$12,4)) -> Toeslagen | D18: =IF($B18="","",SUMIFS('Vaste inkomsten'!$J$8:$J$37,'Vaste inkomsten'!$G$8:$G$37,$B18,'Vaste inkomsten'!$H$8:$H$37,"Ja")) -> 0 | E18: =IF($B18="","",SUMIFS('Vaste inkomsten'!$J$8:$J$37,'Vaste inkomsten'!$G$8:$G$37,$B18,'Vaste inkomsten'!$H$8:$H$37,"Ja")+SUMIFS(Transacties!$D$8:$D$507,Transacties!$H$8:$H$507,Dashboard!$N$4,Transacties!$B$8:$B$507,$B18)) -> 0 | F18: =IF($B18="","",$E18-$D18) -> 0 | G18: =IF(OR($B18="",$D18=0),"",$E18/$D18) | I18: =IF($B18="",-1,$E18+ROW()/100000) -> 0.00018
B19: =IF(INDEX(Lijsten!$A$6:$A$12,5)="","",INDEX(Lijsten!$A$6:$A$12,5)) -> Overig inkomen | D19: =IF($B19="","",SUMIFS('Vaste inkomsten'!$J$8:$J$37,'Vaste inkomsten'!$G$8:$G$37,$B19,'Vaste inkomsten'!$H$8:$H$37,"Ja")) -> 0 | E19: =IF($B19="","",SUMIFS('Vaste inkomsten'!$J$8:$J$37,'Vaste inkomsten'!$G$8:$G$37,$B19,'Vaste inkomsten'!$H$8:$H$37,"Ja")+SUMIFS(Transacties!$D$8:$D$507,Transacties!$H$8:$H$507,Dashboard!$N$4,Transacties!$B$8:$B$507,$B19)) -> 0 | F19: =IF($B19="","",$E19-$D19) -> 0 | G19: =IF(OR($B19="",$D19=0),"",$E19/$D19) | I19: =IF($B19="",-1,$E19+ROW()/100000) -> 0.00019
B20: =IF(INDEX(Lijsten!$A$6:$A$12,6)="","",INDEX(Lijsten!$A$6:$A$12,6)) | D20: =IF($B20="","",SUMIFS('Vaste inkomsten'!$J$8:$J$37,'Vaste inkomsten'!$G$8:$G$37,$B20,'Vaste inkomsten'!$H$8:$H$37,"Ja")) | E20: =IF($B20="","",SUMIFS('Vaste inkomsten'!$J$8:$J$37,'Vaste inkomsten'!$G$8:$G$37,$B20,'Vaste inkomsten'!$H$8:$H$37,"Ja")+SUMIFS(Transacties!$D$8:$D$507,Transacties!$H$8:$H$507,Dashboard!$N$4,Transacties!$B$8:$B$507,$B20)) | F20: =IF($B20="","",$E20-$D20) | G20: =IF(OR($B20="",$D20=0),"",$E20/$D20) | I20: =IF($B20="",-1,$E20+ROW()/100000) -> -1
B21: =IF(INDEX(Lijsten!$A$6:$A$12,7)="","",INDEX(Lijsten!$A$6:$A$12,7)) | D21: =IF($B21="","",SUMIFS('Vaste inkomsten'!$J$8:$J$37,'Vaste inkomsten'!$G$8:$G$37,$B21,'Vaste inkomsten'!$H$8:$H$37,"Ja")) | E21: =IF($B21="","",SUMIFS('Vaste inkomsten'!$J$8:$J$37,'Vaste inkomsten'!$G$8:$G$37,$B21,'Vaste inkomsten'!$H$8:$H$37,"Ja")+SUMIFS(Transacties!$D$8:$D$507,Transacties!$H$8:$H$507,Dashboard!$N$4,Transacties!$B$8:$B$507,$B21)) | F21: =IF($B21="","",$E21-$D21) | G21: =IF(OR($B21="",$D21=0),"",$E21/$D21) | I21: =IF($B21="",-1,$E21+ROW()/100000) -> -1
B22: Totaal inkomsten | C22: =SUM(C15:C21) -> 0 | D22: =SUM(D15:D21) -> 2800 | E22: =SUM(E15:E21) -> 2800 | F22: =SUM(F15:F21) -> 0
B23: Optelling van Vaste lasten + Schulden + Transacties. Alleen de gele kolom vul je zelf in.
B24: UITGAVEN
B25: Categorie | C25: Budget variabel | D25: Begroot totaal | E25: Werkelijk | F25: Verschil | G25: % budget
B26: =IF(INDEX(Lijsten!$C$6:$C$35,1)="","",INDEX(Lijsten!$C$6:$C$35,1)) -> Wonen | C26: 0 | D26: =IF($B26="","",SUMIFS('Vaste lasten'!$J$8:$J$207,'Vaste lasten'!$G$8:$G$207,$B26,'Vaste lasten'!$H$8:$H$207,"Ja")+SUMIFS(Schulden!$E$8:$E$37,Schulden!$F$8:$F$37,$B26,Schulden!$G$8:$G$37,"Ja")+IF($C26="",0,$C26)) -> 900 | E26: =IF($B26="","",SUMIFS('Vaste lasten'!$J$8:$J$207,'Vaste lasten'!$G$8:$G$207,$B26,'Vaste lasten'!$H$8:$H$207,"Ja")+SUMIFS(Schulden!$E$8:$E$37,Schulden!$F$8:$F$37,$B26,Schulden!$G$8:$G$37,"Ja")+SUMIFS(Transacties!$D$8:$D$507,Transacties!$H$8:$H$507,Dashboard!$N$4,Transacties!$B$8:$B$507,$B26)) -> 900 | F26: =IF($B26="","",$D26-$E26) -> 0 | G26: =IF(OR($B26="",$D26=0),"",$E26/$D26) -> 1 | I26: =IF($B26="",-1,$E26+ROW()/100000) -> 900.00026
B27: =IF(INDEX(Lijsten!$C$6:$C$35,2)="","",INDEX(Lijsten!$C$6:$C$35,2)) -> Nutsvoorzieningen | C27: 0 | D27: =IF($B27="","",SUMIFS('Vaste lasten'!$J$8:$J$207,'Vaste lasten'!$G$8:$G$207,$B27,'Vaste lasten'!$H$8:$H$207,"Ja")+SUMIFS(Schulden!$E$8:$E$37,Schulden!$F$8:$F$37,$B27,Schulden!$G$8:$G$37,"Ja")+IF($C27="",0,$C27)) -> 0 | E27: =IF($B27="","",SUMIFS('Vaste lasten'!$J$8:$J$207,'Vaste lasten'!$G$8:$G$207,$B27,'Vaste lasten'!$H$8:$H$207,"Ja")+SUMIFS(Schulden!$E$8:$E$37,Schulden!$F$8:$F$37,$B27,Schulden!$G$8:$G$37,"Ja")+SUMIFS(Transacties!$D$8:$D$507,Transacties!$H$8:$H$507,Dashboard!$N$4,Transacties!$B$8:$B$507,$B27)) -> 0 | F27: =IF($B27="","",$D27-$E27) -> 0 | G27: =IF(OR($B27="",$D27=0),"",$E27/$D27) | I27: =IF($B27="",-1,$E27+ROW()/100000) -> 0.00027
B28: =IF(INDEX(Lijsten!$C$6:$C$35,3)="","",INDEX(Lijsten!$C$6:$C$35,3)) -> Telefoon & internet | C28: 0 | D28: =IF($B28="","",SUMIFS('Vaste lasten'!$J$8:$J$207,'Vaste lasten'!$G$8:$G$207,$B28,'Vaste lasten'!$H$8:$H$207,"Ja")+SUMIFS(Schulden!$E$8:$E$37,Schulden!$F$8:$F$37,$B28,Schulden!$G$8:$G$37,"Ja")+IF($C28="",0,$C28)) -> 0 | E28: =IF($B28="","",SUMIFS('Vaste lasten'!$J$8:$J$207,'Vaste lasten'!$G$8:$G$207,$B28,'Vaste lasten'!$H$8:$H$207,"Ja")+SUMIFS(Schulden!$E$8:$E$37,Schulden!$F$8:$F$37,$B28,Schulden!$G$8:$G$37,"Ja")+SUMIFS(Transacties!$D$8:$D$507,Transacties!$H$8:$H$507,Dashboard!$N$4,Transacties!$B$8:$B$507,$B28)) -> 0 | F28: =IF($B28="","",$D28-$E28) -> 0 | G28: =IF(OR($B28="",$D28=0),"",$E28/$D28) | I28: =IF($B28="",-1,$E28+ROW()/100000) -> 0.00028
B29: =IF(INDEX(Lijsten!$C$6:$C$35,4)="","",INDEX(Lijsten!$C$6:$C$35,4)) -> Technologie & software | C29: 0 | D29: =IF($B29="","",SUMIFS('Vaste lasten'!$J$8:$J$207,'Vaste lasten'!$G$8:$G$207,$B29,'Vaste lasten'!$H$8:$H$207,"Ja")+SUMIFS(Schulden!$E$8:$E$37,Schulden!$F$8:$F$37,$B29,Schulden!$G$8:$G$37,"Ja")+IF($C29="",0,$C29)) -> 0 | E29: =IF($B29="","",SUMIFS('Vaste lasten'!$J$8:$J$207,'Vaste lasten'!$G$8:$G$207,$B29,'Vaste lasten'!$H$8:$H$207,"Ja")+SUMIFS(Schulden!$E$8:$E$37,Schulden!$F$8:$F$37,$B29,Schulden!$G$8:$G$37,"Ja")+SUMIFS(Transacties!$D$8:$D$507,Transacties!$H$8:$H$507,Dashboard!$N$4,Transacties!$B$8:$B$507,$B29)) -> 0 | F29: =IF($B29="","",$D29-$E29) -> 0 | G29: =IF(OR($B29="",$D29=0),"",$E29/$D29) | I29: =IF($B29="",-1,$E29+ROW()/100000) -> 0.00029
B30: =IF(INDEX(Lijsten!$C$6:$C$35,5)="","",INDEX(Lijsten!$C$6:$C$35,5)) -> Verzekeringen | C30: 0 | D30: =IF($B30="","",SUMIFS('Vaste lasten'!$J$8:$J$207,'Vaste lasten'!$G$8:$G$207,$B30,'Vaste lasten'!$H$8:$H$207,"Ja")+SUMIFS(Schulden!$E$8:$E$37,Schulden!$F$8:$F$37,$B30,Schulden!$G$8:$G$37,"Ja")+IF($C30="",0,$C30)) -> 0 | E30: =IF($B30="","",SUMIFS('Vaste lasten'!$J$8:$J$207,'Vaste lasten'!$G$8:$G$207,$B30,'Vaste lasten'!$H$8:$H$207,"Ja")+SUMIFS(Schulden!$E$8:$E$37,Schulden!$F$8:$F$37,$B30,Schulden!$G$8:$G$37,"Ja")+SUMIFS(Transacties!$D$8:$D$507,Transacties!$H$8:$H$507,Dashboard!$N$4,Transacties!$B$8:$B$507,$B30)) -> 0 | F30: =IF($B30="","",$D30-$E30) -> 0 | G30: =IF(OR($B30="",$D30=0),"",$E30/$D30) | I30: =IF($B30="",-1,$E30+ROW()/100000) -> 0.0003
B31: =IF(INDEX(Lijsten!$C$6:$C$35,6)="","",INDEX(Lijsten!$C$6:$C$35,6)) -> Auto & vervoer | C31: 150 | D31: =IF($B31="","",SUMIFS('Vaste lasten'!$J$8:$J$207,'Vaste lasten'!$G$8:$G$207,$B31,'Vaste lasten'!$H$8:$H$207,"Ja")+SUMIFS(Schulden!$E$8:$E$37,Schulden!$F$8:$F$37,$B31,Schulden!$G$8:$G$37,"Ja")+IF($C31="",0,$C31)) -> 200 | E31: =IF($B31="","",SUMIFS('Vaste lasten'!$J$8:$J$207,'Vaste lasten'!$G$8:$G$207,$B31,'Vaste lasten'!$H$8:$H$207,"Ja")+SUMIFS(Schulden!$E$8:$E$37,Schulden!$F$8:$F$37,$B31,Schulden!$G$8:$G$37,"Ja")+SUMIFS(Transacties!$D$8:$D$507,Transacties!$H$8:$H$507,Dashboard!$N$4,Transacties!$B$8:$B$507,$B31)) -> 50 | F31: =IF($B31="","",$D31-$E31) -> 150 | G31: =IF(OR($B31="",$D31=0),"",$E31/$D31) -> 0.25 | I31: =IF($B31="",-1,$E31+ROW()/100000) -> 50.00031
B32: =IF(INDEX(Lijsten!$C$6:$C$35,7)="","",INDEX(Lijsten!$C$6:$C$35,7)) -> Belastingen | C32: 0 | D32: =IF($B32="","",SUMIFS('Vaste lasten'!$J$8:$J$207,'Vaste lasten'!$G$8:$G$207,$B32,'Vaste lasten'!$H$8:$H$207,"Ja")+SUMIFS(Schulden!$E$8:$E$37,Schulden!$F$8:$F$37,$B32,Schulden!$G$8:$G$37,"Ja")+IF($C32="",0,$C32)) -> 0 | E32: =IF($B32="","",SUMIFS('Vaste lasten'!$J$8:$J$207,'Vaste lasten'!$G$8:$G$207,$B32,'Vaste lasten'!$H$8:$H$207,"Ja")+SUMIFS(Schulden!$E$8:$E$37,Schulden!$F$8:$F$37,$B32,Schulden!$G$8:$G$37,"Ja")+SUMIFS(Transacties!$D$8:$D$507,Transacties!$H$8:$H$507,Dashboard!$N$4,Transacties!$B$8:$B$507,$B32)) -> 0 | F32: =IF($B32="","",$D32-$E32) -> 0 | G32: =IF(OR($B32="",$D32=0),"",$E32/$D32) | I32: =IF($B32="",-1,$E32+ROW()/100000) -> 0.00032
B33: =IF(INDEX(Lijsten!$C$6:$C$35,8)="","",INDEX(Lijsten!$C$6:$C$35,8)) -> Boodschappen & eten | C33: 300 | D33: =IF($B33="","",SUMIFS('Vaste lasten'!$J$8:$J$207,'Vaste lasten'!$G$8:$G$207,$B33,'Vaste lasten'!$H$8:$H$207,"Ja")+SUMIFS(Schulden!$E$8:$E$37,Schulden!$F$8:$F$37,$B33,Schulden!$G$8:$G$37,"Ja")+IF($C33="",0,$C33)) -> 300 | E33: =IF($B33="","",SUMIFS('Vaste lasten'!$J$8:$J$207,'Vaste lasten'!$G$8:$G$207,$B33,'Vaste lasten'!$H$8:$H$207,"Ja")+SUMIFS(Schulden!$E$8:$E$37,Schulden!$F$8:$F$37,$B33,Schulden!$G$8:$G$37,"Ja")+SUMIFS(Transacties!$D$8:$D$507,Transacties!$H$8:$H$507,Dashboard!$N$4,Transacties!$B$8:$B$507,$B33)) -> 62.3 | F33: =IF($B33="","",$D33-$E33) -> 237.7 | G33: =IF(OR($B33="",$D33=0),"",$E33/$D33) -> 0.20766667 | I33: =IF($B33="",-1,$E33+ROW()/100000) -> 62.30033
B34: =IF(INDEX(Lijsten!$C$6:$C$35,9)="","",INDEX(Lijsten!$C$6:$C$35,9)) -> Uit eten & horeca | C34: 0 | D34: =IF($B34="","",SUMIFS('Vaste lasten'!$J$8:$J$207,'Vaste lasten'!$G$8:$G$207,$B34,'Vaste lasten'!$H$8:$H$207,"Ja")+SUMIFS(Schulden!$E$8:$E$37,Schulden!$F$8:$F$37,$B34,Schulden!$G$8:$G$37,"Ja")+IF($C34="",0,$C34)) -> 0 | E34: =IF($B34="","",SUMIFS('Vaste lasten'!$J$8:$J$207,'Vaste lasten'!$G$8:$G$207,$B34,'Vaste lasten'!$H$8:$H$207,"Ja")+SUMIFS(Schulden!$E$8:$E$37,Schulden!$F$8:$F$37,$B34,Schulden!$G$8:$G$37,"Ja")+SUMIFS(Transacties!$D$8:$D$507,Transacties!$H$8:$H$507,Dashboard!$N$4,Transacties!$B$8:$B$507,$B34)) -> 0 | F34: =IF($B34="","",$D34-$E34) -> 0 | G34: =IF(OR($B34="",$D34=0),"",$E34/$D34) | I34: =IF($B34="",-1,$E34+ROW()/100000) -> 0.00034
B35: =IF(INDEX(Lijsten!$C$6:$C$35,10)="","",INDEX(Lijsten!$C$6:$C$35,10)) -> Gezondheid & zorg | C35: 0 | D35: =IF($B35="","",SUMIFS('Vaste lasten'!$J$8:$J$207,'Vaste lasten'!$G$8:$G$207,$B35,'Vaste lasten'!$H$8:$H$207,"Ja")+SUMIFS(Schulden!$E$8:$E$37,Schulden!$F$8:$F$37,$B35,Schulden!$G$8:$G$37,"Ja")+IF($C35="",0,$C35)) -> 0 | E35: =IF($B35="","",SUMIFS('Vaste lasten'!$J$8:$J$207,'Vaste lasten'!$G$8:$G$207,$B35,'Vaste lasten'!$H$8:$H$207,"Ja")+SUMIFS(Schulden!$E$8:$E$37,Schulden!$F$8:$F$37,$B35,Schulden!$G$8:$G$37,"Ja")+SUMIFS(Transacties!$D$8:$D$507,Transacties!$H$8:$H$507,Dashboard!$N$4,Transacties!$B$8:$B$507,$B35)) -> 0 | F35: =IF($B35="","",$D35-$E35) -> 0 | G35: =IF(OR($B35="",$D35=0),"",$E35/$D35) | I35: =IF($B35="",-1,$E35+ROW()/100000) -> 0.00035
B36: =IF(INDEX(Lijsten!$C$6:$C$35,11)="","",INDEX(Lijsten!$C$6:$C$35,11)) -> Persoonlijke verzorging | C36: 0 | D36: =IF($B36="","",SUMIFS('Vaste lasten'!$J$8:$J$207,'Vaste lasten'!$G$8:$G$207,$B36,'Vaste lasten'!$H$8:$H$207,"Ja")+SUMIFS(Schulden!$E$8:$E$37,Schulden!$F$8:$F$37,$B36,Schulden!$G$8:$G$37,"Ja")+IF($C36="",0,$C36)) -> 0 | E36: =IF($B36="","",SUMIFS('Vaste lasten'!$J$8:$J$207,'Vaste lasten'!$G$8:$G$207,$B36,'Vaste lasten'!$H$8:$H$207,"Ja")+SUMIFS(Schulden!$E$8:$E$37,Schulden!$F$8:$F$37,$B36,Schulden!$G$8:$G$37,"Ja")+SUMIFS(Transacties!$D$8:$D$507,Transacties!$H$8:$H$507,Dashboard!$N$4,Transacties!$B$8:$B$507,$B36)) -> 0 | F36: =IF($B36="","",$D36-$E36) -> 0 | G36: =IF(OR($B36="",$D36=0),"",$E36/$D36) | I36: =IF($B36="",-1,$E36+ROW()/100000) -> 0.00036
B37: =IF(INDEX(Lijsten!$C$6:$C$35,12)="","",INDEX(Lijsten!$C$6:$C$35,12)) -> Kleding | C37: 0 | D37: =IF($B37="","",SUMIFS('Vaste lasten'!$J$8:$J$207,'Vaste lasten'!$G$8:$G$207,$B37,'Vaste lasten'!$H$8:$H$207,"Ja")+SUMIFS(Schulden!$E$8:$E$37,Schulden!$F$8:$F$37,$B37,Schulden!$G$8:$G$37,"Ja")+IF($C37="",0,$C37)) -> 0 | E37: =IF($B37="","",SUMIFS('Vaste lasten'!$J$8:$J$207,'Vaste lasten'!$G$8:$G$207,$B37,'Vaste lasten'!$H$8:$H$207,"Ja")+SUMIFS(Schulden!$E$8:$E$37,Schulden!$F$8:$F$37,$B37,Schulden!$G$8:$G$37,"Ja")+SUMIFS(Transacties!$D$8:$D$507,Transacties!$H$8:$H$507,Dashboard!$N$4,Transacties!$B$8:$B$507,$B37)) -> 0 | F37: =IF($B37="","",$D37-$E37) -> 0 | G37: =IF(OR($B37="",$D37=0),"",$E37/$D37) | I37: =IF($B37="",-1,$E37+ROW()/100000) -> 0.00037
B38: =IF(INDEX(Lijsten!$C$6:$C$35,13)="","",INDEX(Lijsten!$C$6:$C$35,13)) -> Huishouden | C38: 0 | D38: =IF($B38="","",SUMIFS('Vaste lasten'!$J$8:$J$207,'Vaste lasten'!$G$8:$G$207,$B38,'Vaste lasten'!$H$8:$H$207,"Ja")+SUMIFS(Schulden!$E$8:$E$37,Schulden!$F$8:$F$37,$B38,Schulden!$G$8:$G$37,"Ja")+IF($C38="",0,$C38)) -> 0 | E38: =IF($B38="","",SUMIFS('Vaste lasten'!$J$8:$J$207,'Vaste lasten'!$G$8:$G$207,$B38,'Vaste lasten'!$H$8:$H$207,"Ja")+SUMIFS(Schulden!$E$8:$E$37,Schulden!$F$8:$F$37,$B38,Schulden!$G$8:$G$37,"Ja")+SUMIFS(Transacties!$D$8:$D$507,Transacties!$H$8:$H$507,Dashboard!$N$4,Transacties!$B$8:$B$507,$B38)) -> 0 | F38: =IF($B38="","",$D38-$E38) -> 0 | G38: =IF(OR($B38="",$D38=0),"",$E38/$D38) | I38: =IF($B38="",-1,$E38+ROW()/100000) -> 0.00038
B39: =IF(INDEX(Lijsten!$C$6:$C$35,14)="","",INDEX(Lijsten!$C$6:$C$35,14)) -> Abonnementen & media | C39: 0 | D39: =IF($B39="","",SUMIFS('Vaste lasten'!$J$8:$J$207,'Vaste lasten'!$G$8:$G$207,$B39,'Vaste lasten'!$H$8:$H$207,"Ja")+SUMIFS(Schulden!$E$8:$E$37,Schulden!$F$8:$F$37,$B39,Schulden!$G$8:$G$37,"Ja")+IF($C39="",0,$C39)) -> 0 | E39: =IF($B39="","",SUMIFS('Vaste lasten'!$J$8:$J$207,'Vaste lasten'!$G$8:$G$207,$B39,'Vaste lasten'!$H$8:$H$207,"Ja")+SUMIFS(Schulden!$E$8:$E$37,Schulden!$F$8:$F$37,$B39,Schulden!$G$8:$G$37,"Ja")+SUMIFS(Transacties!$D$8:$D$507,Transacties!$H$8:$H$507,Dashboard!$N$4,Transacties!$B$8:$B$507,$B39)) -> 0 | F39: =IF($B39="","",$D39-$E39) -> 0 | G39: =IF(OR($B39="",$D39=0),"",$E39/$D39) | I39: =IF($B39="",-1,$E39+ROW()/100000) -> 0.00039
B40: =IF(INDEX(Lijsten!$C$6:$C$35,15)="","",INDEX(Lijsten!$C$6:$C$35,15)) -> Sport & fitness | C40: 0 | D40: =IF($B40="","",SUMIFS('Vaste lasten'!$J$8:$J$207,'Vaste lasten'!$G$8:$G$207,$B40,'Vaste lasten'!$H$8:$H$207,"Ja")+SUMIFS(Schulden!$E$8:$E$37,Schulden!$F$8:$F$37,$B40,Schulden!$G$8:$G$37,"Ja")+IF($C40="",0,$C40)) -> 0 | E40: =IF($B40="","",SUMIFS('Vaste lasten'!$J$8:$J$207,'Vaste lasten'!$G$8:$G$207,$B40,'Vaste lasten'!$H$8:$H$207,"Ja")+SUMIFS(Schulden!$E$8:$E$37,Schulden!$F$8:$F$37,$B40,Schulden!$G$8:$G$37,"Ja")+SUMIFS(Transacties!$D$8:$D$507,Transacties!$H$8:$H$507,Dashboard!$N$4,Transacties!$B$8:$B$507,$B40)) -> 0 | F40: =IF($B40="","",$D40-$E40) -> 0 | G40: =IF(OR($B40="",$D40=0),"",$E40/$D40) | I40: =IF($B40="",-1,$E40+ROW()/100000) -> 0.0004
B41: =IF(INDEX(Lijsten!$C$6:$C$35,16)="","",INDEX(Lijsten!$C$6:$C$35,16)) -> Vrije tijd & uitjes | C41: 0 | D41: =IF($B41="","",SUMIFS('Vaste lasten'!$J$8:$J$207,'Vaste lasten'!$G$8:$G$207,$B41,'Vaste lasten'!$H$8:$H$207,"Ja")+SUMIFS(Schulden!$E$8:$E$37,Schulden!$F$8:$F$37,$B41,Schulden!$G$8:$G$37,"Ja")+IF($C41="",0,$C41)) -> 0 | E41: =IF($B41="","",SUMIFS('Vaste lasten'!$J$8:$J$207,'Vaste lasten'!$G$8:$G$207,$B41,'Vaste lasten'!$H$8:$H$207,"Ja")+SUMIFS(Schulden!$E$8:$E$37,Schulden!$F$8:$F$37,$B41,Schulden!$G$8:$G$37,"Ja")+SUMIFS(Transacties!$D$8:$D$507,Transacties!$H$8:$H$507,Dashboard!$N$4,Transacties!$B$8:$B$507,$B41)) -> 0 | F41: =IF($B41="","",$D41-$E41) -> 0 | G41: =IF(OR($B41="",$D41=0),"",$E41/$D41) | I41: =IF($B41="",-1,$E41+ROW()/100000) -> 0.00041
B42: =IF(INDEX(Lijsten!$C$6:$C$35,17)="","",INDEX(Lijsten!$C$6:$C$35,17)) -> Vakantie & reizen | C42: 0 | D42: =IF($B42="","",SUMIFS('Vaste lasten'!$J$8:$J$207,'Vaste lasten'!$G$8:$G$207,$B42,'Vaste lasten'!$H$8:$H$207,"Ja")+SUMIFS(Schulden!$E$8:$E$37,Schulden!$F$8:$F$37,$B42,Schulden!$G$8:$G$37,"Ja")+IF($C42="",0,$C42)) -> 0 | E42: =IF($B42="","",SUMIFS('Vaste lasten'!$J$8:$J$207,'Vaste lasten'!$G$8:$G$207,$B42,'Vaste lasten'!$H$8:$H$207,"Ja")+SUMIFS(Schulden!$E$8:$E$37,Schulden!$F$8:$F$37,$B42,Schulden!$G$8:$G$37,"Ja")+SUMIFS(Transacties!$D$8:$D$507,Transacties!$H$8:$H$507,Dashboard!$N$4,Transacties!$B$8:$B$507,$B42)) -> 0 | F42: =IF($B42="","",$D42-$E42) -> 0 | G42: =IF(OR($B42="",$D42=0),"",$E42/$D42) | I42: =IF($B42="",-1,$E42+ROW()/100000) -> 0.00042
B43: =IF(INDEX(Lijsten!$C$6:$C$35,18)="","",INDEX(Lijsten!$C$6:$C$35,18)) -> Studie & ontwikkeling | C43: 0 | D43: =IF($B43="","",SUMIFS('Vaste lasten'!$J$8:$J$207,'Vaste lasten'!$G$8:$G$207,$B43,'Vaste lasten'!$H$8:$H$207,"Ja")+SUMIFS(Schulden!$E$8:$E$37,Schulden!$F$8:$F$37,$B43,Schulden!$G$8:$G$37,"Ja")+IF($C43="",0,$C43)) -> 0 | E43: =IF($B43="","",SUMIFS('Vaste lasten'!$J$8:$J$207,'Vaste lasten'!$G$8:$G$207,$B43,'Vaste lasten'!$H$8:$H$207,"Ja")+SUMIFS(Schulden!$E$8:$E$37,Schulden!$F$8:$F$37,$B43,Schulden!$G$8:$G$37,"Ja")+SUMIFS(Transacties!$D$8:$D$507,Transacties!$H$8:$H$507,Dashboard!$N$4,Transacties!$B$8:$B$507,$B43)) -> 0 | F43: =IF($B43="","",$D43-$E43) -> 0 | G43: =IF(OR($B43="",$D43=0),"",$E43/$D43) | I43: =IF($B43="",-1,$E43+ROW()/100000) -> 0.00043
B44: =IF(INDEX(Lijsten!$C$6:$C$35,19)="","",INDEX(Lijsten!$C$6:$C$35,19)) -> Kinderen & alimentatie | C44: 0 | D44: =IF($B44="","",SUMIFS('Vaste lasten'!$J$8:$J$207,'Vaste lasten'!$G$8:$G$207,$B44,'Vaste lasten'!$H$8:$H$207,"Ja")+SUMIFS(Schulden!$E$8:$E$37,Schulden!$F$8:$F$37,$B44,Schulden!$G$8:$G$37,"Ja")+IF($C44="",0,$C44)) -> 0 | E44: =IF($B44="","",SUMIFS('Vaste lasten'!$J$8:$J$207,'Vaste lasten'!$G$8:$G$207,$B44,'Vaste lasten'!$H$8:$H$207,"Ja")+SUMIFS(Schulden!$E$8:$E$37,Schulden!$F$8:$F$37,$B44,Schulden!$G$8:$G$37,"Ja")+SUMIFS(Transacties!$D$8:$D$507,Transacties!$H$8:$H$507,Dashboard!$N$4,Transacties!$B$8:$B$507,$B44)) -> 0 | F44: =IF($B44="","",$D44-$E44) -> 0 | G44: =IF(OR($B44="",$D44=0),"",$E44/$D44) | I44: =IF($B44="",-1,$E44+ROW()/100000) -> 0.00044
B45: =IF(INDEX(Lijsten!$C$6:$C$35,20)="","",INDEX(Lijsten!$C$6:$C$35,20)) -> Giften & goede doelen | C45: 0 | D45: =IF($B45="","",SUMIFS('Vaste lasten'!$J$8:$J$207,'Vaste lasten'!$G$8:$G$207,$B45,'Vaste lasten'!$H$8:$H$207,"Ja")+SUMIFS(Schulden!$E$8:$E$37,Schulden!$F$8:$F$37,$B45,Schulden!$G$8:$G$37,"Ja")+IF($C45="",0,$C45)) -> 0 | E45: =IF($B45="","",SUMIFS('Vaste lasten'!$J$8:$J$207,'Vaste lasten'!$G$8:$G$207,$B45,'Vaste lasten'!$H$8:$H$207,"Ja")+SUMIFS(Schulden!$E$8:$E$37,Schulden!$F$8:$F$37,$B45,Schulden!$G$8:$G$37,"Ja")+SUMIFS(Transacties!$D$8:$D$507,Transacties!$H$8:$H$507,Dashboard!$N$4,Transacties!$B$8:$B$507,$B45)) -> 0 | F45: =IF($B45="","",$D45-$E45) -> 0 | G45: =IF(OR($B45="",$D45=0),"",$E45/$D45) | I45: =IF($B45="",-1,$E45+ROW()/100000) -> 0.00045
B46: =IF(INDEX(Lijsten!$C$6:$C$35,21)="","",INDEX(Lijsten!$C$6:$C$35,21)) -> Huisdieren | C46: 0 | D46: =IF($B46="","",SUMIFS('Vaste lasten'!$J$8:$J$207,'Vaste lasten'!$G$8:$G$207,$B46,'Vaste lasten'!$H$8:$H$207,"Ja")+SUMIFS(Schulden!$E$8:$E$37,Schulden!$F$8:$F$37,$B46,Schulden!$G$8:$G$37,"Ja")+IF($C46="",0,$C46)) -> 0 | E46: =IF($B46="","",SUMIFS('Vaste lasten'!$J$8:$J$207,'Vaste lasten'!$G$8:$G$207,$B46,'Vaste lasten'!$H$8:$H$207,"Ja")+SUMIFS(Schulden!$E$8:$E$37,Schulden!$F$8:$F$37,$B46,Schulden!$G$8:$G$37,"Ja")+SUMIFS(Transacties!$D$8:$D$507,Transacties!$H$8:$H$507,Dashboard!$N$4,Transacties!$B$8:$B$507,$B46)) -> 0 | F46: =IF($B46="","",$D46-$E46) -> 0 | G46: =IF(OR($B46="",$D46=0),"",$E46/$D46) | I46: =IF($B46="",-1,$E46+ROW()/100000) -> 0.00046
B47: =IF(INDEX(Lijsten!$C$6:$C$35,22)="","",INDEX(Lijsten!$C$6:$C$35,22)) -> Schulden & aflossingen | C47: 0 | D47: =IF($B47="","",SUMIFS('Vaste lasten'!$J$8:$J$207,'Vaste lasten'!$G$8:$G$207,$B47,'Vaste lasten'!$H$8:$H$207,"Ja")+SUMIFS(Schulden!$E$8:$E$37,Schulden!$F$8:$F$37,$B47,Schulden!$G$8:$G$37,"Ja")+IF($C47="",0,$C47)) -> 190 | E47: =IF($B47="","",SUMIFS('Vaste lasten'!$J$8:$J$207,'Vaste lasten'!$G$8:$G$207,$B47,'Vaste lasten'!$H$8:$H$207,"Ja")+SUMIFS(Schulden!$E$8:$E$37,Schulden!$F$8:$F$37,$B47,Schulden!$G$8:$G$37,"Ja")+SUMIFS(Transacties!$D$8:$D$507,Transacties!$H$8:$H$507,Dashboard!$N$4,Transacties!$B$8:$B$507,$B47)) -> 190 | F47: =IF($B47="","",$D47-$E47) -> 0 | G47: =IF(OR($B47="",$D47=0),"",$E47/$D47) -> 1 | I47: =IF($B47="",-1,$E47+ROW()/100000) -> 190.00047
B48: =IF(INDEX(Lijsten!$C$6:$C$35,23)="","",INDEX(Lijsten!$C$6:$C$35,23)) -> Sparen & reserveringen | C48: 0 | D48: =IF($B48="","",SUMIFS('Vaste lasten'!$J$8:$J$207,'Vaste lasten'!$G$8:$G$207,$B48,'Vaste lasten'!$H$8:$H$207,"Ja")+SUMIFS(Schulden!$E$8:$E$37,Schulden!$F$8:$F$37,$B48,Schulden!$G$8:$G$37,"Ja")+IF($C48="",0,$C48)) -> 0 | E48: =IF($B48="","",SUMIFS('Vaste lasten'!$J$8:$J$207,'Vaste lasten'!$G$8:$G$207,$B48,'Vaste lasten'!$H$8:$H$207,"Ja")+SUMIFS(Schulden!$E$8:$E$37,Schulden!$F$8:$F$37,$B48,Schulden!$G$8:$G$37,"Ja")+SUMIFS(Transacties!$D$8:$D$507,Transacties!$H$8:$H$507,Dashboard!$N$4,Transacties!$B$8:$B$507,$B48)) -> 0 | F48: =IF($B48="","",$D48-$E48) -> 0 | G48: =IF(OR($B48="",$D48=0),"",$E48/$D48) | I48: =IF($B48="",-1,$E48+ROW()/100000) -> 0.00048
B49: =IF(INDEX(Lijsten!$C$6:$C$35,24)="","",INDEX(Lijsten!$C$6:$C$35,24)) -> Zakelijk | C49: 0 | D49: =IF($B49="","",SUMIFS('Vaste lasten'!$J$8:$J$207,'Vaste lasten'!$G$8:$G$207,$B49,'Vaste lasten'!$H$8:$H$207,"Ja")+SUMIFS(Schulden!$E$8:$E$37,Schulden!$F$8:$F$37,$B49,Schulden!$G$8:$G$37,"Ja")+IF($C49="",0,$C49)) -> 0 | E49: =IF($B49="","",SUMIFS('Vaste lasten'!$J$8:$J$207,'Vaste lasten'!$G$8:$G$207,$B49,'Vaste lasten'!$H$8:$H$207,"Ja")+SUMIFS(Schulden!$E$8:$E$37,Schulden!$F$8:$F$37,$B49,Schulden!$G$8:$G$37,"Ja")+SUMIFS(Transacties!$D$8:$D$507,Transacties!$H$8:$H$507,Dashboard!$N$4,Transacties!$B$8:$B$507,$B49)) -> 0 | F49: =IF($B49="","",$D49-$E49) -> 0 | G49: =IF(OR($B49="",$D49=0),"",$E49/$D49) | I49: =IF($B49="",-1,$E49+ROW()/100000) -> 0.00049
B50: =IF(INDEX(Lijsten!$C$6:$C$35,25)="","",INDEX(Lijsten!$C$6:$C$35,25)) -> Onvoorzien | C50: 0 | D50: =IF($B50="","",SUMIFS('Vaste lasten'!$J$8:$J$207,'Vaste lasten'!$G$8:$G$207,$B50,'Vaste lasten'!$H$8:$H$207,"Ja")+SUMIFS(Schulden!$E$8:$E$37,Schulden!$F$8:$F$37,$B50,Schulden!$G$8:$G$37,"Ja")+IF($C50="",0,$C50)) -> 0 | E50: =IF($B50="","",SUMIFS('Vaste lasten'!$J$8:$J$207,'Vaste lasten'!$G$8:$G$207,$B50,'Vaste lasten'!$H$8:$H$207,"Ja")+SUMIFS(Schulden!$E$8:$E$37,Schulden!$F$8:$F$37,$B50,Schulden!$G$8:$G$37,"Ja")+SUMIFS(Transacties!$D$8:$D$507,Transacties!$H$8:$H$507,Dashboard!$N$4,Transacties!$B$8:$B$507,$B50)) -> 0 | F50: =IF($B50="","",$D50-$E50) -> 0 | G50: =IF(OR($B50="",$D50=0),"",$E50/$D50) | I50: =IF($B50="",-1,$E50+ROW()/100000) -> 0.0005
B51: =IF(INDEX(Lijsten!$C$6:$C$35,26)="","",INDEX(Lijsten!$C$6:$C$35,26)) -> Overig | C51: 0 | D51: =IF($B51="","",SUMIFS('Vaste lasten'!$J$8:$J$207,'Vaste lasten'!$G$8:$G$207,$B51,'Vaste lasten'!$H$8:$H$207,"Ja")+SUMIFS(Schulden!$E$8:$E$37,Schulden!$F$8:$F$37,$B51,Schulden!$G$8:$G$37,"Ja")+IF($C51="",0,$C51)) -> 0 | E51: =IF($B51="","",SUMIFS('Vaste lasten'!$J$8:$J$207,'Vaste lasten'!$G$8:$G$207,$B51,'Vaste lasten'!$H$8:$H$207,"Ja")+SUMIFS(Schulden!$E$8:$E$37,Schulden!$F$8:$F$37,$B51,Schulden!$G$8:$G$37,"Ja")+SUMIFS(Transacties!$D$8:$D$507,Transacties!$H$8:$H$507,Dashboard!$N$4,Transacties!$B$8:$B$507,$B51)) -> 0 | F51: =IF($B51="","",$D51-$E51) -> 0 | G51: =IF(OR($B51="",$D51=0),"",$E51/$D51) | I51: =IF($B51="",-1,$E51+ROW()/100000) -> 0.00051
B52: =IF(INDEX(Lijsten!$C$6:$C$35,27)="","",INDEX(Lijsten!$C$6:$C$35,27)) | D52: =IF($B52="","",SUMIFS('Vaste lasten'!$J$8:$J$207,'Vaste lasten'!$G$8:$G$207,$B52,'Vaste lasten'!$H$8:$H$207,"Ja")+SUMIFS(Schulden!$E$8:$E$37,Schulden!$F$8:$F$37,$B52,Schulden!$G$8:$G$37,"Ja")+IF($C52="",0,$C52)) | E52: =IF($B52="","",SUMIFS('Vaste lasten'!$J$8:$J$207,'Vaste lasten'!$G$8:$G$207,$B52,'Vaste lasten'!$H$8:$H$207,"Ja")+SUMIFS(Schulden!$E$8:$E$37,Schulden!$F$8:$F$37,$B52,Schulden!$G$8:$G$37,"Ja")+SUMIFS(Transacties!$D$8:$D$507,Transacties!$H$8:$H$507,Dashboard!$N$4,Transacties!$B$8:$B$507,$B52)) | F52: =IF($B52="","",$D52-$E52) | G52: =IF(OR($B52="",$D52=0),"",$E52/$D52) | I52: =IF($B52="",-1,$E52+ROW()/100000) -> -1
B53: =IF(INDEX(Lijsten!$C$6:$C$35,28)="","",INDEX(Lijsten!$C$6:$C$35,28)) | D53: =IF($B53="","",SUMIFS('Vaste lasten'!$J$8:$J$207,'Vaste lasten'!$G$8:$G$207,$B53,'Vaste lasten'!$H$8:$H$207,"Ja")+SUMIFS(Schulden!$E$8:$E$37,Schulden!$F$8:$F$37,$B53,Schulden!$G$8:$G$37,"Ja")+IF($C53="",0,$C53)) | E53: =IF($B53="","",SUMIFS('Vaste lasten'!$J$8:$J$207,'Vaste lasten'!$G$8:$G$207,$B53,'Vaste lasten'!$H$8:$H$207,"Ja")+SUMIFS(Schulden!$E$8:$E$37,Schulden!$F$8:$F$37,$B53,Schulden!$G$8:$G$37,"Ja")+SUMIFS(Transacties!$D$8:$D$507,Transacties!$H$8:$H$507,Dashboard!$N$4,Transacties!$B$8:$B$507,$B53)) | F53: =IF($B53="","",$D53-$E53) | G53: =IF(OR($B53="",$D53=0),"",$E53/$D53) | I53: =IF($B53="",-1,$E53+ROW()/100000) -> -1
B54: =IF(INDEX(Lijsten!$C$6:$C$35,29)="","",INDEX(Lijsten!$C$6:$C$35,29)) | D54: =IF($B54="","",SUMIFS('Vaste lasten'!$J$8:$J$207,'Vaste lasten'!$G$8:$G$207,$B54,'Vaste lasten'!$H$8:$H$207,"Ja")+SUMIFS(Schulden!$E$8:$E$37,Schulden!$F$8:$F$37,$B54,Schulden!$G$8:$G$37,"Ja")+IF($C54="",0,$C54)) | E54: =IF($B54="","",SUMIFS('Vaste lasten'!$J$8:$J$207,'Vaste lasten'!$G$8:$G$207,$B54,'Vaste lasten'!$H$8:$H$207,"Ja")+SUMIFS(Schulden!$E$8:$E$37,Schulden!$F$8:$F$37,$B54,Schulden!$G$8:$G$37,"Ja")+SUMIFS(Transacties!$D$8:$D$507,Transacties!$H$8:$H$507,Dashboard!$N$4,Transacties!$B$8:$B$507,$B54)) | F54: =IF($B54="","",$D54-$E54) | G54: =IF(OR($B54="",$D54=0),"",$E54/$D54) | I54: =IF($B54="",-1,$E54+ROW()/100000) -> -1
B55: =IF(INDEX(Lijsten!$C$6:$C$35,30)="","",INDEX(Lijsten!$C$6:$C$35,30)) | D55: =IF($B55="","",SUMIFS('Vaste lasten'!$J$8:$J$207,'Vaste lasten'!$G$8:$G$207,$B55,'Vaste lasten'!$H$8:$H$207,"Ja")+SUMIFS(Schulden!$E$8:$E$37,Schulden!$F$8:$F$37,$B55,Schulden!$G$8:$G$37,"Ja")+IF($C55="",0,$C55)) | E55: =IF($B55="","",SUMIFS('Vaste lasten'!$J$8:$J$207,'Vaste lasten'!$G$8:$G$207,$B55,'Vaste lasten'!$H$8:$H$207,"Ja")+SUMIFS(Schulden!$E$8:$E$37,Schulden!$F$8:$F$37,$B55,Schulden!$G$8:$G$37,"Ja")+SUMIFS(Transacties!$D$8:$D$507,Transacties!$H$8:$H$507,Dashboard!$N$4,Transacties!$B$8:$B$507,$B55)) | F55: =IF($B55="","",$D55-$E55) | G55: =IF(OR($B55="",$D55=0),"",$E55/$D55) | I55: =IF($B55="",-1,$E55+ROW()/100000) -> -1
B56: Totaal uitgaven | C56: =SUM(C26:C55) -> 450 | D56: =SUM(D26:D55) -> 1590 | E56: =SUM(E26:E55) -> 1202.3 | F56: =SUM(F26:F55) -> 387.7
B58: Controle | D58: =ROUND(Dashboard!$B$9-$E$22,2) -> 0 | E58: =ROUND(Dashboard!$C$9-$E$56,2) -> 0 | F58: Beide € 0,00? Dan hangt alles aan een categorie.

Sheet Vaste lasten
A1: VASTE LASTEN | F1: ⌂ Menu | G1: Dashboard ▸
A2: Eén regel per post, met je eigen naam. Ruimte voor 200 regels — specificeer gerust alles apart.
A3: Betaal je iets per kwartaal of per jaar? Zet het factuurbedrag in 'Bedrag', kies de frequentie en vul de betaalmaand in.
A5: Totaal vaste lasten per maand | F5: =SUMIFS($F$8:$F$207,$H$8:$H$207,"Ja") -> 950 | G5: =COUNTIF($H$8:$H$207,"Ja")&" actieve regels" -> 2 actieve regels | J5: in gekozen maand:
J6: =SUMIFS($J$8:$J$207,$H$8:$H$207,"Ja") -> 950
A7: Omschrijving | B7: Leverancier | C7: Bedrag | D7: Frequentie | E7: Betaalmaand | F7: Bedrag p/m | G7: Categorie | H7: Actief | I7: Notitie | J7: Bedrag deze maand | K7: januari | L7: februari | M7: maart | N7: april | O7: mei | P7: juni | Q7: juli | R7: augustus | S7: september | T7: oktober | U7: november | V7: december | W7: mnr
A8: Huur | B8: Woningcorporatie | C8: 900 | D8: Per maand | F8: =IF($C8="","",IF($D8="Per jaar",$C8/12,IF($D8="Per kwartaal",$C8/3,IF($D8="Per half jaar",$C8/6,IF($D8="Per week",$C8*52/12,$C8))))) -> 900 | G8: Wonen | H8: Ja | I8: VOORBEELDREGEL — overschrijf of verwijder | J8: =IF($C8="","",IF(Dashboard!$C$4="Gemiddeld per maand",$F8,IF(OR($D8="Per maand",$D8="Per week",$D8=""),$F8,IF($D8="Per jaar",IF(Dashboard!$N$2=$W8,$C8,0),IF($D8="Per half jaar",IF(MOD(Dashboard!$N$2-$W8,6)=0,$C8,0),IF($D8="Per kwartaal",IF(MOD(Dashboard!$N$2-$W8,3)=0,$C8,0),$F8)))))) -> 900 | K8: =IF($C8="","",IF(Dashboard!$C$4="Gemiddeld per maand",$F8,IF(OR($D8="Per maand",$D8="Per week",$D8=""),$F8,IF($D8="Per jaar",IF(1=$W8,$C8,0),IF($D8="Per half jaar",IF(MOD(1-$W8,6)=0,$C8,0),IF($D8="Per kwartaal",IF(MOD(1-$W8,3)=0,$C8,0),$F8)))))) -> 900 | L8: =IF($C8="","",IF(Dashboard!$C$4="Gemiddeld per maand",$F8,IF(OR($D8="Per maand",$D8="Per week",$D8=""),$F8,IF($D8="Per jaar",IF(2=$W8,$C8,0),IF($D8="Per half jaar",IF(MOD(2-$W8,6)=0,$C8,0),IF($D8="Per kwartaal",IF(MOD(2-$W8,3)=0,$C8,0),$F8)))))) -> 900 | M8: =IF($C8="","",IF(Dashboard!$C$4="Gemiddeld per maand",$F8,IF(OR($D8="Per maand",$D8="Per week",$D8=""),$F8,IF($D8="Per jaar",IF(3=$W8,$C8,0),IF($D8="Per half jaar",IF(MOD(3-$W8,6)=0,$C8,0),IF($D8="Per kwartaal",IF(MOD(3-$W8,3)=0,$C8,0),$F8)))))) -> 900 | N8: =IF($C8="","",IF(Dashboard!$C$4="Gemiddeld per maand",$F8,IF(OR($D8="Per maand",$D8="Per week",$D8=""),$F8,IF($D8="Per jaar",IF(4=$W8,$C8,0),IF($D8="Per half jaar",IF(MOD(4-$W8,6)=0,$C8,0),IF($D8="Per kwartaal",IF(MOD(4-$W8,3)=0,$C8,0),$F8)))))) -> 900 | O8: =IF($C8="","",IF(Dashboard!$C$4="Gemiddeld per maand",$F8,IF(OR($D8="Per maand",$D8="Per week",$D8=""),$F8,IF($D8="Per jaar",IF(5=$W8,$C8,0),IF($D8="Per half jaar",IF(MOD(5-$W8,6)=0,$C8,0),IF($D8="Per kwartaal",IF(MOD(5-$W8,3)=0,$C8,0),$F8)))))) -> 900 | P8: =IF($C8="","",IF(Dashboard!$C$4="Gemiddeld per maand",$F8,IF(OR($D8="Per maand",$D8="Per week",$D8=""),$F8,IF($D8="Per jaar",IF(6=$W8,$C8,0),IF($D8="Per half jaar",IF(MOD(6-$W8,6)=0,$C8,0),IF($D8="Per kwartaal",IF(MOD(6-$W8,3)=0,$C8,0),$F8)))))) -> 900 | Q8: =IF($C8="","",IF(Dashboard!$C$4="Gemiddeld per maand",$F8,IF(OR($D8="Per maand",$D8="Per week",$D8=""),$F8,IF($D8="Per jaar",IF(7=$W8,$C8,0),IF($D8="Per half jaar",IF(MOD(7-$W8,6)=0,$C8,0),IF($D8="Per kwartaal",IF(MOD(7-$W8,3)=0,$C8,0),$F8)))))) -> 900 | R8: =IF($C8="","",IF(Dashboard!$C$4="Gemiddeld per maand",$F8,IF(OR($D8="Per maand",$D8="Per week",$D8=""),$F8,IF($D8="Per jaar",IF(8=$W8,$C8,0),IF($D8="Per half jaar",IF(MOD(8-$W8,6)=0,$C8,0),IF($D8="Per kwartaal",IF(MOD(8-$W8,3)=0,$C8,0),$F8)))))) -> 900 | S8: =IF($C8="","",IF(Dashboard!$C$4="Gemiddeld per maand",$F8,IF(OR($D8="Per maand",$D8="Per week",$D8=""),$F8,IF($D8="Per jaar",IF(9=$W8,$C8,0),IF($D8="Per half jaar",IF(MOD(9-$W8,6)=0,$C8,0),IF($D8="Per kwartaal",IF(MOD(9-$W8,3)=0,$C8,0),$F8)))))) -> 900 | T8: =IF($C8="","",IF(Dashboard!$C$4="Gemiddeld per maand",$F8,IF(OR($D8="Per maand",$D8="Per week",$D8=""),$F8,IF($D8="Per jaar",IF(10=$W8,$C8,0),IF($D8="Per half jaar",IF(MOD(10-$W8,6)=0,$C8,0),IF($D8="Per kwartaal",IF(MOD(10-$W8,3)=0,$C8,0),$F8)))))) -> 900 | U8: =IF($C8="","",IF(Dashboard!$C$4="Gemiddeld per maand",$F8,IF(OR($D8="Per maand",$D8="Per week",$D8=""),$F8,IF($D8="Per jaar",IF(11=$W8,$C8,0),IF($D8="Per half jaar",IF(MOD(11-$W8,6)=0,$C8,0),IF($D8="Per kwartaal",IF(MOD(11-$W8,3)=0,$C8,0),$F8)))))) -> 900 | V8: =IF($C8="","",IF(Dashboard!$C$4="Gemiddeld per maand",$F8,IF(OR($D8="Per maand",$D8="Per week",$D8=""),$F8,IF($D8="Per jaar",IF(12=$W8,$C8,0),IF($D8="Per half jaar",IF(MOD(12-$W8,6)=0,$C8,0),IF($D8="Per kwartaal",IF(MOD(12-$W8,3)=0,$C8,0),$F8)))))) -> 900 | W8: =IF($E8="",1,IFERROR(MATCH($E8,Lijsten!$K$6:$K$17,0),1)) -> 1
A9: Wegenbelasting | B9: Belastingdienst | C9: 150 | D9: Per kwartaal | E9: januari | F9: =IF($C9="","",IF($D9="Per jaar",$C9/12,IF($D9="Per kwartaal",$C9/3,IF($D9="Per half jaar",$C9/6,IF($D9="Per week",$C9*52/12,$C9))))) -> 50 | G9: Auto & vervoer | H9: Ja | I9: VOORBEELD van een kwartaalpost | J9: =IF($C9="","",IF(Dashboard!$C$4="Gemiddeld per maand",$F9,IF(OR($D9="Per maand",$D9="Per week",$D9=""),$F9,IF($D9="Per jaar",IF(Dashboard!$N$2=$W9,$C9,0),IF($D9="Per half jaar",IF(MOD(Dashboard!$N$2-$W9,6)=0,$C9,0),IF($D9="Per kwartaal",IF(MOD(Dashboard!$N$2-$W9,3)=0,$C9,0),$F9)))))) -> 50 | K9: =IF($C9="","",IF(Dashboard!$C$4="Gemiddeld per maand",$F9,IF(OR($D9="Per maand",$D9="Per week",$D9=""),$F9,IF($D9="Per jaar",IF(1=$W9,$C9,0),IF($D9="Per half jaar",IF(MOD(1-$W9,6)=0,$C9,0),IF($D9="Per kwartaal",IF(MOD(1-$W9,3)=0,$C9,0),$F9)))))) -> 50 | L9: =IF($C9="","",IF(Dashboard!$C$4="Gemiddeld per maand",$F9,IF(OR($D9="Per maand",$D9="Per week",$D9=""),$F9,IF($D9="Per jaar",IF(2=$W9,$C9,0),IF($D9="Per half jaar",IF(MOD(2-$W9,6)=0,$C9,0),IF($D9="Per kwartaal",IF(MOD(2-$W9,3)=0,$C9,0),$F9)))))) -> 50 | M9: =IF($C9="","",IF(Dashboard!$C$4="Gemiddeld per maand",$F9,IF(OR($D9="Per maand",$D9="Per week",$D9=""),$F9,IF($D9="Per jaar",IF(3=$W9,$C9,0),IF($D9="Per half jaar",IF(MOD(3-$W9,6)=0,$C9,0),IF($D9="Per kwartaal",IF(MOD(3-$W9,3)=0,$C9,0),$F9)))))) -> 50 | N9: =IF($C9="","",IF(Dashboard!$C$4="Gemiddeld per maand",$F9,IF(OR($D9="Per maand",$D9="Per week",$D9=""),$F9,IF($D9="Per jaar",IF(4=$W9,$C9,0),IF($D9="Per half jaar",IF(MOD(4-$W9,6)=0,$C9,0),IF($D9="Per kwartaal",IF(MOD(4-$W9,3)=0,$C9,0),$F9)))))) -> 50 | O9: =IF($C9="","",IF(Dashboard!$C$4="Gemiddeld per maand",$F9,IF(OR($D9="Per maand",$D9="Per week",$D9=""),$F9,IF($D9="Per jaar",IF(5=$W9,$C9,0),IF($D9="Per half jaar",IF(MOD(5-$W9,6)=0,$C9,0),IF($D9="Per kwartaal",IF(MOD(5-$W9,3)=0,$C9,0),$F9)))))) -> 50 | P9: =IF($C9="","",IF(Dashboard!$C$4="Gemiddeld per maand",$F9,IF(OR($D9="Per maand",$D9="Per week",$D9=""),$F9,IF($D9="Per jaar",IF(6=$W9,$C9,0),IF($D9="Per half jaar",IF(MOD(6-$W9,6)=0,$C9,0),IF($D9="Per kwartaal",IF(MOD(6-$W9,3)=0,$C9,0),$F9)))))) -> 50 | Q9: =IF($C9="","",IF(Dashboard!$C$4="Gemiddeld per maand",$F9,IF(OR($D9="Per maand",$D9="Per week",$D9=""),$F9,IF($D9="Per jaar",IF(7=$W9,$C9,0),IF($D9="Per half jaar",IF(MOD(7-$W9,6)=0,$C9,0),IF($D9="Per kwartaal",IF(MOD(7-$W9,3)=0,$C9,0),$F9)))))) -> 50 | R9: =IF($C9="","",IF(Dashboard!$C$4="Gemiddeld per maand",$F9,IF(OR($D9="Per maand",$D9="Per week",$D9=""),$F9,IF($D9="Per jaar",IF(8=$W9,$C9,0),IF($D9="Per half jaar",IF(MOD(8-$W9,6)=0,$C9,0),IF($D9="Per kwartaal",IF(MOD(8-$W9,3)=0,$C9,0),$F9)))))) -> 50 | S9: =IF($C9="","",IF(Dashboard!$C$4="Gemiddeld per maand",$F9,IF(OR($D9="Per maand",$D9="Per week",$D9=""),$F9,IF($D9="Per jaar",IF(9=$W9,$C9,0),IF($D9="Per half jaar",IF(MOD(9-$W9,6)=0,$C9,0),IF($D9="Per kwartaal",IF(MOD(9-$W9,3)=0,$C9,0),$F9)))))) -> 50 | T9: =IF($C9="","",IF(Dashboard!$C$4="Gemiddeld per maand",$F9,IF(OR($D9="Per maand",$D9="Per week",$D9=""),$F9,IF($D9="Per jaar",IF(10=$W9,$C9,0),IF($D9="Per half jaar",IF(MOD(10-$W9,6)=0,$C9,0),IF($D9="Per kwartaal",IF(MOD(10-$W9,3)=0,$C9,0),$F9)))))) -> 50 | U9: =IF($C9="","",IF(Dashboard!$C$4="Gemiddeld per maand",$F9,IF(OR($D9="Per maand",$D9="Per week",$D9=""),$F9,IF($D9="Per jaar",IF(11=$W9,$C9,0),IF($D9="Per half jaar",IF(MOD(11-$W9,6)=0,$C9,0),IF($D9="Per kwartaal",IF(MOD(11-$W9,3)=0,$C9,0),$F9)))))) -> 50 | V9: =IF($C9="","",IF(Dashboard!$C$4="Gemiddeld per maand",$F9,IF(OR($D9="Per maand",$D9="Per week",$D9=""),$F9,IF($D9="Per jaar",IF(12=$W9,$C9,0),IF($D9="Per half jaar",IF(MOD(12-$W9,6)=0,$C9,0),IF($D9="Per kwartaal",IF(MOD(12-$W9,3)=0,$C9,0),$F9)))))) -> 50 | W9: =IF($E9="",1,IFERROR(MATCH($E9,Lijsten!$K$6:$K$17,0),1)) -> 1
F10: =IF($C10="","",IF($D10="Per jaar",$C10/12,IF($D10="Per kwartaal",$C10/3,IF($D10="Per half jaar",$C10/6,IF($D10="Per week",$C10*52/12,$C10))))) | J10: =IF($C10="","",IF(Dashboard!$C$4="Gemiddeld per maand",$F10,IF(OR($D10="Per maand",$D10="Per week",$D10=""),$F10,IF($D10="Per jaar",IF(Dashboard!$N$2=$W10,$C10,0),IF($D10="Per half jaar",IF(MOD(Dashboard!$N$2-$W10,6)=0,$C10,0),IF($D10="Per kwartaal",IF(MOD(Dashboard!$N$2-$W10,3)=0,$C10,0),$F10)))))) | K10: =IF($C10="","",IF(Dashboard!$C$4="Gemiddeld per maand",$F10,IF(OR($D10="Per maand",$D10="Per week",$D10=""),$F10,IF($D10="Per jaar",IF(1=$W10,$C10,0),IF($D10="Per half jaar",IF(MOD(1-$W10,6)=0,$C10,0),IF($D10="Per kwartaal",IF(MOD(1-$W10,3)=0,$C10,0),$F10)))))) | L10: =IF($C10="","",IF(Dashboard!$C$4="Gemiddeld per maand",$F10,IF(OR($D10="Per maand",$D10="Per week",$D10=""),$F10,IF($D10="Per jaar",IF(2=$W10,$C10,0),IF($D10="Per half jaar",IF(MOD(2-$W10,6)=0,$C10,0),IF($D10="Per kwartaal",IF(MOD(2-$W10,3)=0,$C10,0),$F10)))))) | M10: =IF($C10="","",IF(Dashboard!$C$4="Gemiddeld per maand",$F10,IF(OR($D10="Per maand",$D10="Per week",$D10=""),$F10,IF($D10="Per jaar",IF(3=$W10,$C10,0),IF($D10="Per half jaar",IF(MOD(3-$W10,6)=0,$C10,0),IF($D10="Per kwartaal",IF(MOD(3-$W10,3)=0,$C10,0),$F10)))))) | N10: =IF($C10="","",IF(Dashboard!$C$4="Gemiddeld per maand",$F10,IF(OR($D10="Per maand",$D10="Per week",$D10=""),$F10,IF($D10="Per jaar",IF(4=$W10,$C10,0),IF($D10="Per half jaar",IF(MOD(4-$W10,6)=0,$C10,0),IF($D10="Per kwartaal",IF(MOD(4-$W10,3)=0,$C10,0),$F10)))))) | O10: =IF($C10="","",IF(Dashboard!$C$4="Gemiddeld per maand",$F10,IF(OR($D10="Per maand",$D10="Per week",$D10=""),$F10,IF($D10="Per jaar",IF(5=$W10,$C10,0),IF($D10="Per half jaar",IF(MOD(5-$W10,6)=0,$C10,0),IF($D10="Per kwartaal",IF(MOD(5-$W10,3)=0,$C10,0),$F10)))))) | P10: =IF($C10="","",IF(Dashboard!$C$4="Gemiddeld per maand",$F10,IF(OR($D10="Per maand",$D10="Per week",$D10=""),$F10,IF($D10="Per jaar",IF(6=$W10,$C10,0),IF($D10="Per half jaar",IF(MOD(6-$W10,6)=0,$C10,0),IF($D10="Per kwartaal",IF(MOD(6-$W10,3)=0,$C10,0),$F10)))))) | Q10: =IF($C10="","",IF(Dashboard!$C$4="Gemiddeld per maand",$F10,IF(OR($D10="Per maand",$D10="Per week",$D10=""),$F10,IF($D10="Per jaar",IF(7=$W10,$C10,0),IF($D10="Per half jaar",IF(MOD(7-$W10,6)=0,$C10,0),IF($D10="Per kwartaal",IF(MOD(7-$W10,3)=0,$C10,0),$F10)))))) | R10: =IF($C10="","",IF(Dashboard!$C$4="Gemiddeld per maand",$F10,IF(OR($D10="Per maand",$D10="Per week",$D10=""),$F10,IF($D10="Per jaar",IF(8=$W10,$C10,0),IF($D10="Per half jaar",IF(MOD(8-$W10,6)=0,$C10,0),IF($D10="Per kwartaal",IF(MOD(8-$W10,3)=0,$C10,0),$F10)))))) | S10: =IF($C10="","",IF(Dashboard!$C$4="Gemiddeld per maand",$F10,IF(OR($D10="Per maand",$D10="Per week",$D10=""),$F10,IF($D10="Per jaar",IF(9=$W10,$C10,0),IF($D10="Per half jaar",IF(MOD(9-$W10,6)=0,$C10,0),IF($D10="Per kwartaal",IF(MOD(9-$W10,3)=0,$C10,0),$F10)))))) | T10: =IF($C10="","",IF(Dashboard!$C$4="Gemiddeld per maand",$F10,IF(OR($D10="Per maand",$D10="Per week",$D10=""),$F10,IF($D10="Per jaar",IF(10=$W10,$C10,0),IF($D10="Per half jaar",IF(MOD(10-$W10,6)=0,$C10,0),IF($D10="Per kwartaal",IF(MOD(10-$W10,3)=0,$C10,0),$F10)))))) | U10: =IF($C10="","",IF(Dashboard!$C$4="Gemiddeld per maand",$F10,IF(OR($D10="Per maand",$D10="Per week",$D10=""),$F10,IF($D10="Per jaar",IF(11=$W10,$C10,0),IF($D10="Per half jaar",IF(MOD(11-$W10,6)=0,$C10,0),IF($D10="Per kwartaal",IF(MOD(11-$W10,3)=0,$C10,0),$F10)))))) | V10: =IF($C10="","",IF(Dashboard!$C$4="Gemiddeld per maand",$F10,IF(OR($D10="Per maand",$D10="Per week",$D10=""),$F10,IF($D10="Per jaar",IF(12=$W10,$C10,0),IF($D10="Per half jaar",IF(MOD(12-$W10,6)=0,$C10,0),IF($D10="Per kwartaal",IF(MOD(12-$W10,3)=0,$C10,0),$F10)))))) | W10: =IF($E10="",1,IFERROR(MATCH($E10,Lijsten!$K$6:$K$17,0),1)) -> 1
F11: =IF($C11="","",IF($D11="Per jaar",$C11/12,IF($D11="Per kwartaal",$C11/3,IF($D11="Per half jaar",$C11/6,IF($D11="Per week",$C11*52/12,$C11))))) | J11: =IF($C11="","",IF(Dashboard!$C$4="Gemiddeld per maand",$F11,IF(OR($D11="Per maand",$D11="Per week",$D11=""),$F11,IF($D11="Per jaar",IF(Dashboard!$N$2=$W11,$C11,0),IF($D11="Per half jaar",IF(MOD(Dashboard!$N$2-$W11,6)=0,$C11,0),IF($D11="Per kwartaal",IF(MOD(Dashboard!$N$2-$W11,3)=0,$C11,0),$F11)))))) | K11: =IF($C11="","",IF(Dashboard!$C$4="Gemiddeld per maand",$F11,IF(OR($D11="Per maand",$D11="Per week",$D11=""),$F11,IF($D11="Per jaar",IF(1=$W11,$C11,0),IF($D11="Per half jaar",IF(MOD(1-$W11,6)=0,$C11,0),IF($D11="Per kwartaal",IF(MOD(1-$W11,3)=0,$C11,0),$F11)))))) | L11: =IF($C11="","",IF(Dashboard!$C$4="Gemiddeld per maand",$F11,IF(OR($D11="Per maand",$D11="Per week",$D11=""),$F11,IF($D11="Per jaar",IF(2=$W11,$C11,0),IF($D11="Per half jaar",IF(MOD(2-$W11,6)=0,$C11,0),IF($D11="Per kwartaal",IF(MOD(2-$W11,3)=0,$C11,0),$F11)))))) | M11: =IF($C11="","",IF(Dashboard!$C$4="Gemiddeld per maand",$F11,IF(OR($D11="Per maand",$D11="Per week",$D11=""),$F11,IF($D11="Per jaar",IF(3=$W11,$C11,0),IF($D11="Per half jaar",IF(MOD(3-$W11,6)=0,$C11,0),IF($D11="Per kwartaal",IF(MOD(3-$W11,3)=0,$C11,0),$F11)))))) | N11: =IF($C11="","",IF(Dashboard!$C$4="Gemiddeld per maand",$F11,IF(OR($D11="Per maand",$D11="Per week",$D11=""),$F11,IF($D11="Per jaar",IF(4=$W11,$C11,0),IF($D11="Per half jaar",IF(MOD(4-$W11,6)=0,$C11,0),IF($D11="Per kwartaal",IF(MOD(4-$W11,3)=0,$C11,0),$F11)))))) | O11: =IF($C11="","",IF(Dashboard!$C$4="Gemiddeld per maand",$F11,IF(OR($D11="Per maand",$D11="Per week",$D11=""),$F11,IF($D11="Per jaar",IF(5=$W11,$C11,0),IF($D11="Per half jaar",IF(MOD(5-$W11,6)=0,$C11,0),IF($D11="Per kwartaal",IF(MOD(5-$W11,3)=0,$C11,0),$F11)))))) | P11: =IF($C11="","",IF(Dashboard!$C$4="Gemiddeld per maand",$F11,IF(OR($D11="Per maand",$D11="Per week",$D11=""),$F11,IF($D11="Per jaar",IF(6=$W11,$C11,0),IF($D11="Per half jaar",IF(MOD(6-$W11,6)=0,$C11,0),IF($D11="Per kwartaal",IF(MOD(6-$W11,3)=0,$C11,0),$F11)))))) | Q11: =IF($C11="","",IF(Dashboard!$C$4="Gemiddeld per maand",$F11,IF(OR($D11="Per maand",$D11="Per week",$D11=""),$F11,IF($D11="Per jaar",IF(7=$W11,$C11,0),IF($D11="Per half jaar",IF(MOD(7-$W11,6)=0,$C11,0),IF($D11="Per kwartaal",IF(MOD(7-$W11,3)=0,$C11,0),$F11)))))) | R11: =IF($C11="","",IF(Dashboard!$C$4="Gemiddeld per maand",$F11,IF(OR($D11="Per maand",$D11="Per week",$D11=""),$F11,IF($D11="Per jaar",IF(8=$W11,$C11,0),IF($D11="Per half jaar",IF(MOD(8-$W11,6)=0,$C11,0),IF($D11="Per kwartaal",IF(MOD(8-$W11,3)=0,$C11,0),$F11)))))) | S11: =IF($C11="","",IF(Dashboard!$C$4="Gemiddeld per maand",$F11,IF(OR($D11="Per maand",$D11="Per week",$D11=""),$F11,IF($D11="Per jaar",IF(9=$W11,$C11,0),IF($D11="Per half jaar",IF(MOD(9-$W11,6)=0,$C11,0),IF($D11="Per kwartaal",IF(MOD(9-$W11,3)=0,$C11,0),$F11)))))) | T11: =IF($C11="","",IF(Dashboard!$C$4="Gemiddeld per maand",$F11,IF(OR($D11="Per maand",$D11="Per week",$D11=""),$F11,IF($D11="Per jaar",IF(10=$W11,$C11,0),IF($D11="Per half jaar",IF(MOD(10-$W11,6)=0,$C11,0),IF($D11="Per kwartaal",IF(MOD(10-$W11,3)=0,$C11,0),$F11)))))) | U11: =IF($C11="","",IF(Dashboard!$C$4="Gemiddeld per maand",$F11,IF(OR($D11="Per maand",$D11="Per week",$D11=""),$F11,IF($D11="Per jaar",IF(11=$W11,$C11,0),IF($D11="Per half jaar",IF(MOD(11-$W11,6)=0,$C11,0),IF($D11="Per kwartaal",IF(MOD(11-$W11,3)=0,$C11,0),$F11)))))) | V11: =IF($C11="","",IF(Dashboard!$C$4="Gemiddeld per maand",$F11,IF(OR($D11="Per maand",$D11="Per week",$D11=""),$F11,IF($D11="Per jaar",IF(12=$W11,$C11,0),IF($D11="Per half jaar",IF(MOD(12-$W11,6)=0,$C11,0),IF($D11="Per kwartaal",IF(MOD(12-$W11,3)=0,$C11,0),$F11)))))) | W11: =IF($E11="",1,IFERROR(MATCH($E11,Lijsten!$K$6:$K$17,0),1)) -> 1
F12: =IF($C12="","",IF($D12="Per jaar",$C12/12,IF($D12="Per kwartaal",$C12/3,IF($D12="Per half jaar",$C12/6,IF($D12="Per week",$C12*52/12,$C12))))) | J12: =IF($C12="","",IF(Dashboard!$C$4="Gemiddeld per maand",$F12,IF(OR($D12="Per maand",$D12="Per week",$D12=""),$F12,IF($D12="Per jaar",IF(Dashboard!$N$2=$W12,$C12,0),IF($D12="Per half jaar",IF(MOD(Dashboard!$N$2-$W12,6)=0,$C12,0),IF($D12="Per kwartaal",IF(MOD(Dashboard!$N$2-$W12,3)=0,$C12,0),$F12)))))) | K12: =IF($C12="","",IF(Dashboard!$C$4="Gemiddeld per maand",$F12,IF(OR($D12="Per maand",$D12="Per week",$D12=""),$F12,IF($D12="Per jaar",IF(1=$W12,$C12,0),IF($D12="Per half jaar",IF(MOD(1-$W12,6)=0,$C12,0),IF($D12="Per kwartaal",IF(MOD(1-$W12,3)=0,$C12,0),$F12)))))) | L12: =IF($C12="","",IF(Dashboard!$C$4="Gemiddeld per maand",$F12,IF(OR($D12="Per maand",$D12="Per week",$D12=""),$F12,IF($D12="Per jaar",IF(2=$W12,$C12,0),IF($D12="Per half jaar",IF(MOD(2-$W12,6)=0,$C12,0),IF($D12="Per kwartaal",IF(MOD(2-$W12,3)=0,$C12,0),$F12)))))) | M12: =IF($C12="","",IF(Dashboard!$C$4="Gemiddeld per maand",$F12,IF(OR($D12="Per maand",$D12="Per week",$D12=""),$F12,IF($D12="Per jaar",IF(3=$W12,$C12,0),IF($D12="Per half jaar",IF(MOD(3-$W12,6)=0,$C12,0),IF($D12="Per kwartaal",IF(MOD(3-$W12,3)=0,$C12,0),$F12)))))) | N12: =IF($C12="","",IF(Dashboard!$C$4="Gemiddeld per maand",$F12,IF(OR($D12="Per maand",$D12="Per week",$D12=""),$F12,IF($D12="Per jaar",IF(4=$W12,$C12,0),IF($D12="Per half jaar",IF(MOD(4-$W12,6)=0,$C12,0),IF($D12="Per kwartaal",IF(MOD(4-$W12,3)=0,$C12,0),$F12)))))) | O12: =IF($C12="","",IF(Dashboard!$C$4="Gemiddeld per maand",$F12,IF(OR($D12="Per maand",$D12="Per week",$D12=""),$F12,IF($D12="Per jaar",IF(5=$W12,$C12,0),IF($D12="Per half jaar",IF(MOD(5-$W12,6)=0,$C12,0),IF($D12="Per kwartaal",IF(MOD(5-$W12,3)=0,$C12,0),$F12)))))) | P12: =IF($C12="","",IF(Dashboard!$C$4="Gemiddeld per maand",$F12,IF(OR($D12="Per maand",$D12="Per week",$D12=""),$F12,IF($D12="Per jaar",IF(6=$W12,$C12,0),IF($D12="Per half jaar",IF(MOD(6-$W12,6)=0,$C12,0),IF($D12="Per kwartaal",IF(MOD(6-$W12,3)=0,$C12,0),$F12)))))) | Q12: =IF($C12="","",IF(Dashboard!$C$4="Gemiddeld per maand",$F12,IF(OR($D12="Per maand",$D12="Per week",$D12=""),$F12,IF($D12="Per jaar",IF(7=$W12,$C12,0),IF($D12="Per half jaar",IF(MOD(7-$W12,6)=0,$C12,0),IF($D12="Per kwartaal",IF(MOD(7-$W12,3)=0,$C12,0),$F12)))))) | R12: =IF($C12="","",IF(Dashboard!$C$4="Gemiddeld per maand",$F12,IF(OR($D12="Per maand",$D12="Per week",$D12=""),$F12,IF($D12="Per jaar",IF(8=$W12,$C12,0),IF($D12="Per half jaar",IF(MOD(8-$W12,6)=0,$C12,0),IF($D12="Per kwartaal",IF(MOD(8-$W12,3)=0,$C12,0),$F12)))))) | S12: =IF($C12="","",IF(Dashboard!$C$4="Gemiddeld per maand",$F12,IF(OR($D12="Per maand",$D12="Per week",$D12=""),$F12,IF($D12="Per jaar",IF(9=$W12,$C12,0),IF($D12="Per half jaar",IF(MOD(9-$W12,6)=0,$C12,0),IF($D12="Per kwartaal",IF(MOD(9-$W12,3)=0,$C12,0),$F12)))))) | T12: =IF($C12="","",IF(Dashboard!$C$4="Gemiddeld per maand",$F12,IF(OR($D12="Per maand",$D12="Per week",$D12=""),$F12,IF($D12="Per jaar",IF(10=$W12,$C12,0),IF($D12="Per half jaar",IF(MOD(10-$W12,6)=0,$C12,0),IF($D12="Per kwartaal",IF(MOD(10-$W12,3)=0,$C12,0),$F12)))))) | U12: =IF($C12="","",IF(Dashboard!$C$4="Gemiddeld per maand",$F12,IF(OR($D12="Per maand",$D12="Per week",$D12=""),$F12,IF($D12="Per jaar",IF(11=$W12,$C12,0),IF($D12="Per half jaar",IF(MOD(11-$W12,6)=0,$C12,0),IF($D12="Per kwartaal",IF(MOD(11-$W12,3)=0,$C12,0),$F12)))))) | V12: =IF($C12="","",IF(Dashboard!$C$4="Gemiddeld per maand",$F12,IF(OR($D12="Per maand",$D12="Per week",$D12=""),$F12,IF($D12="Per jaar",IF(12=$W12,$C12,0),IF($D12="Per half jaar",IF(MOD(12-$W12,6)=0,$C12,0),IF($D12="Per kwartaal",IF(MOD(12-$W12,3)=0,$C12,0),$F12)))))) | W12: =IF($E12="",1,IFERROR(MATCH($E12,Lijsten!$K$6:$K$17,0),1)) -> 1
F13: =IF($C13="","",IF($D13="Per jaar",$C13/12,IF($D13="Per kwartaal",$C13/3,IF($D13="Per half jaar",$C13/6,IF($D13="Per week",$C13*52/12,$C13))))) | J13: =IF($C13="","",IF(Dashboard!$C$4="Gemiddeld per maand",$F13,IF(OR($D13="Per maand",$D13="Per week",$D13=""),$F13,IF($D13="Per jaar",IF(Dashboard!$N$2=$W13,$C13,0),IF($D13="Per half jaar",IF(MOD(Dashboard!$N$2-$W13,6)=0,$C13,0),IF($D13="Per kwartaal",IF(MOD(Dashboard!$N$2-$W13,3)=0,$C13,0),$F13)))))) | K13: =IF($C13="","",IF(Dashboard!$C$4="Gemiddeld per maand",$F13,IF(OR($D13="Per maand",$D13="Per week",$D13=""),$F13,IF($D13="Per jaar",IF(1=$W13,$C13,0),IF($D13="Per half jaar",IF(MOD(1-$W13,6)=0,$C13,0),IF($D13="Per kwartaal",IF(MOD(1-$W13,3)=0,$C13,0),$F13)))))) | L13: =IF($C13="","",IF(Dashboard!$C$4="Gemiddeld per maand",$F13,IF(OR($D13="Per maand",$D13="Per week",$D13=""),$F13,IF($D13="Per jaar",IF(2=$W13,$C13,0),IF($D13="Per half jaar",IF(MOD(2-$W13,6)=0,$C13,0),IF($D13="Per kwartaal",IF(MOD(2-$W13,3)=0,$C13,0),$F13)))))) | M13: =IF($C13="","",IF(Dashboard!$C$4="Gemiddeld per maand",$F13,IF(OR($D13="Per maand",$D13="Per week",$D13=""),$F13,IF($D13="Per jaar",IF(3=$W13,$C13,0),IF($D13="Per half jaar",IF(MOD(3-$W13,6)=0,$C13,0),IF($D13="Per kwartaal",IF(MOD(3-$W13,3)=0,$C13,0),$F13)))))) | N13: =IF($C13="","",IF(Dashboard!$C$4="Gemiddeld per maand",$F13,IF(OR($D13="Per maand",$D13="Per week",$D13=""),$F13,IF($D13="Per jaar",IF(4=$W13,$C13,0),IF($D13="Per half jaar",IF(MOD(4-$W13,6)=0,$C13,0),IF($D13="Per kwartaal",IF(MOD(4-$W13,3)=0,$C13,0),$F13)))))) | O13: =IF($C13="","",IF(Dashboard!$C$4="Gemiddeld per maand",$F13,IF(OR($D13="Per maand",$D13="Per week",$D13=""),$F13,IF($D13="Per jaar",IF(5=$W13,$C13,0),IF($D13="Per half jaar",IF(MOD(5-$W13,6)=0,$C13,0),IF($D13="Per kwartaal",IF(MOD(5-$W13,3)=0,$C13,0),$F13)))))) | P13: =IF($C13="","",IF(Dashboard!$C$4="Gemiddeld per maand",$F13,IF(OR($D13="Per maand",$D13="Per week",$D13=""),$F13,IF($D13="Per jaar",IF(6=$W13,$C13,0),IF($D13="Per half jaar",IF(MOD(6-$W13,6)=0,$C13,0),IF($D13="Per kwartaal",IF(MOD(6-$W13,3)=0,$C13,0),$F13)))))) | Q13: =IF($C13="","",IF(Dashboard!$C$4="Gemiddeld per maand",$F13,IF(OR($D13="Per maand",$D13="Per week",$D13=""),$F13,IF($D13="Per jaar",IF(7=$W13,$C13,0),IF($D13="Per half jaar",IF(MOD(7-$W13,6)=0,$C13,0),IF($D13="Per kwartaal",IF(MOD(7-$W13,3)=0,$C13,0),$F13)))))) | R13: =IF($C13="","",IF(Dashboard!$C$4="Gemiddeld per maand",$F13,IF(OR($D13="Per maand",$D13="Per week",$D13=""),$F13,IF($D13="Per jaar",IF(8=$W13,$C13,0),IF($D13="Per half jaar",IF(MOD(8-$W13,6)=0,$C13,0),IF($D13="Per kwartaal",IF(MOD(8-$W13,3)=0,$C13,0),$F13)))))) | S13: =IF($C13="","",IF(Dashboard!$C$4="Gemiddeld per maand",$F13,IF(OR($D13="Per maand",$D13="Per week",$D13=""),$F13,IF($D13="Per jaar",IF(9=$W13,$C13,0),IF($D13="Per half jaar",IF(MOD(9-$W13,6)=0,$C13,0),IF($D13="Per kwartaal",IF(MOD(9-$W13,3)=0,$C13,0),$F13)))))) | T13: =IF($C13="","",IF(Dashboard!$C$4="Gemiddeld per maand",$F13,IF(OR($D13="Per maand",$D13="Per week",$D13=""),$F13,IF($D13="Per jaar",IF(10=$W13,$C13,0),IF($D13="Per half jaar",IF(MOD(10-$W13,6)=0,$C13,0),IF($D13="Per kwartaal",IF(MOD(10-$W13,3)=0,$C13,0),$F13)))))) | U13: =IF($C13="","",IF(Dashboard!$C$4="Gemiddeld per maand",$F13,IF(OR($D13="Per maand",$D13="Per week",$D13=""),$F13,IF($D13="Per jaar",IF(11=$W13,$C13,0),IF($D13="Per half jaar",IF(MOD(11-$W13,6)=0,$C13,0),IF($D13="Per kwartaal",IF(MOD(11-$W13,3)=0,$C13,0),$F13)))))) | V13: =IF($C13="","",IF(Dashboard!$C$4="Gemiddeld per maand",$F13,IF(OR($D13="Per maand",$D13="Per week",$D13=""),$F13,IF($D13="Per jaar",IF(12=$W13,$C13,0),IF($D13="Per half jaar",IF(MOD(12-$W13,6)=0,$C13,0),IF($D13="Per kwartaal",IF(MOD(12-$W13,3)=0,$C13,0),$F13)))))) | W13: =IF($E13="",1,IFERROR(MATCH($E13,Lijsten!$K$6:$K$17,0),1)) -> 1
F14: =IF($C14="","",IF($D14="Per jaar",$C14/12,IF($D14="Per kwartaal",$C14/3,IF($D14="Per half jaar",$C14/6,IF($D14="Per week",$C14*52/12,$C14))))) | J14: =IF($C14="","",IF(Dashboard!$C$4="Gemiddeld per maand",$F14,IF(OR($D14="Per maand",$D14="Per week",$D14=""),$F14,IF($D14="Per jaar",IF(Dashboard!$N$2=$W14,$C14,0),IF($D14="Per half jaar",IF(MOD(Dashboard!$N$2-$W14,6)=0,$C14,0),IF($D14="Per kwartaal",IF(MOD(Dashboard!$N$2-$W14,3)=0,$C14,0),$F14)))))) | K14: =IF($C14="","",IF(Dashboard!$C$4="Gemiddeld per maand",$F14,IF(OR($D14="Per maand",$D14="Per week",$D14=""),$F14,IF($D14="Per jaar",IF(1=$W14,$C14,0),IF($D14="Per half jaar",IF(MOD(1-$W14,6)=0,$C14,0),IF($D14="Per kwartaal",IF(MOD(1-$W14,3)=0,$C14,0),$F14)))))) | L14: =IF($C14="","",IF(Dashboard!$C$4="Gemiddeld per maand",$F14,IF(OR($D14="Per maand",$D14="Per week",$D14=""),$F14,IF($D14="Per jaar",IF(2=$W14,$C14,0),IF($D14="Per half jaar",IF(MOD(2-$W14,6)=0,$C14,0),IF($D14="Per kwartaal",IF(MOD(2-$W14,3)=0,$C14,0),$F14)))))) | M14: =IF($C14="","",IF(Dashboard!$C$4="Gemiddeld per maand",$F14,IF(OR($D14="Per maand",$D14="Per week",$D14=""),$F14,IF($D14="Per jaar",IF(3=$W14,$C14,0),IF($D14="Per half jaar",IF(MOD(3-$W14,6)=0,$C14,0),IF($D14="Per kwartaal",IF(MOD(3-$W14,3)=0,$C14,0),$F14)))))) | N14: =IF($C14="","",IF(Dashboard!$C$4="Gemiddeld per maand",$F14,IF(OR($D14="Per maand",$D14="Per week",$D14=""),$F14,IF($D14="Per jaar",IF(4=$W14,$C14,0),IF($D14="Per half jaar",IF(MOD(4-$W14,6)=0,$C14,0),IF($D14="Per kwartaal",IF(MOD(4-$W14,3)=0,$C14,0),$F14)))))) | O14: =IF($C14="","",IF(Dashboard!$C$4="Gemiddeld per maand",$F14,IF(OR($D14="Per maand",$D14="Per week",$D14=""),$F14,IF($D14="Per jaar",IF(5=$W14,$C14,0),IF($D14="Per half jaar",IF(MOD(5-$W14,6)=0,$C14,0),IF($D14="Per kwartaal",IF(MOD(5-$W14,3)=0,$C14,0),$F14)))))) | P14: =IF($C14="","",IF(Dashboard!$C$4="Gemiddeld per maand",$F14,IF(OR($D14="Per maand",$D14="Per week",$D14=""),$F14,IF($D14="Per jaar",IF(6=$W14,$C14,0),IF($D14="Per half jaar",IF(MOD(6-$W14,6)=0,$C14,0),IF($D14="Per kwartaal",IF(MOD(6-$W14,3)=0,$C14,0),$F14)))))) | Q14: =IF($C14="","",IF(Dashboard!$C$4="Gemiddeld per maand",$F14,IF(OR($D14="Per maand",$D14="Per week",$D14=""),$F14,IF($D14="Per jaar",IF(7=$W14,$C14,0),IF($D14="Per half jaar",IF(MOD(7-$W14,6)=0,$C14,0),IF($D14="Per kwartaal",IF(MOD(7-$W14,3)=0,$C14,0),$F14)))))) | R14: =IF($C14="","",IF(Dashboard!$C$4="Gemiddeld per maand",$F14,IF(OR($D14="Per maand",$D14="Per week",$D14=""),$F14,IF($D14="Per jaar",IF(8=$W14,$C14,0),IF($D14="Per half jaar",IF(MOD(8-$W14,6)=0,$C14,0),IF($D14="Per kwartaal",IF(MOD(8-$W14,3)=0,$C14,0),$F14)))))) | S14: =IF($C14="","",IF(Dashboard!$C$4="Gemiddeld per maand",$F14,IF(OR($D14="Per maand",$D14="Per week",$D14=""),$F14,IF($D14="Per jaar",IF(9=$W14,$C14,0),IF($D14="Per half jaar",IF(MOD(9-$W14,6)=0,$C14,0),IF($D14="Per kwartaal",IF(MOD(9-$W14,3)=0,$C14,0),$F14)))))) | T14: =IF($C14="","",IF(Dashboard!$C$4="Gemiddeld per maand",$F14,IF(OR($D14="Per maand",$D14="Per week",$D14=""),$F14,IF($D14="Per jaar",IF(10=$W14,$C14,0),IF($D14="Per half jaar",IF(MOD(10-$W14,6)=0,$C14,0),IF($D14="Per kwartaal",IF(MOD(10-$W14,3)=0,$C14,0),$F14)))))) | U14: =IF($C14="","",IF(Dashboard!$C$4="Gemiddeld per maand",$F14,IF(OR($D14="Per maand",$D14="Per week",$D14=""),$F14,IF($D14="Per jaar",IF(11=$W14,$C14,0),IF($D14="Per half jaar",IF(MOD(11-$W14,6)=0,$C14,0),IF($D14="Per kwartaal",IF(MOD(11-$W14,3)=0,$C14,0),$F14)))))) | V14: =IF($C14="","",IF(Dashboard!$C$4="Gemiddeld per maand",$F14,IF(OR($D14="Per maand",$D14="Per week",$D14=""),$F14,IF($D14="Per jaar",IF(12=$W14,$C14,0),IF($D14="Per half jaar",IF(MOD(12-$W14,6)=0,$C14,0),IF($D14="Per kwartaal",IF(MOD(12-$W14,3)=0,$C14,0),$F14)))))) | W14: =IF($E14="",1,IFERROR(MATCH($E14,Lijsten!$K$6:$K$17,0),1)) -> 1
F15: =IF($C15="","",IF($D15="Per jaar",$C15/12,IF($D15="Per kwartaal",$C15/3,IF($D15="Per half jaar",$C15/6,IF($D15="Per week",$C15*52/12,$C15))))) | J15: =IF($C15="","",IF(Dashboard!$C$4="Gemiddeld per maand",$F15,IF(OR($D15="Per maand",$D15="Per week",$D15=""),$F15,IF($D15="Per jaar",IF(Dashboard!$N$2=$W15,$C15,0),IF($D15="Per half jaar",IF(MOD(Dashboard!$N$2-$W15,6)=0,$C15,0),IF($D15="Per kwartaal",IF(MOD(Dashboard!$N$2-$W15,3)=0,$C15,0),$F15)))))) | K15: =IF($C15="","",IF(Dashboard!$C$4="Gemiddeld per maand",$F15,IF(OR($D15="Per maand",$D15="Per week",$D15=""),$F15,IF($D15="Per jaar",IF(1=$W15,$C15,0),IF($D15="Per half jaar",IF(MOD(1-$W15,6)=0,$C15,0),IF($D15="Per kwartaal",IF(MOD(1-$W15,3)=0,$C15,0),$F15)))))) | L15: =IF($C15="","",IF(Dashboard!$C$4="Gemiddeld per maand",$F15,IF(OR($D15="Per maand",$D15="Per week",$D15=""),$F15,IF($D15="Per jaar",IF(2=$W15,$C15,0),IF($D15="Per half jaar",IF(MOD(2-$W15,6)=0,$C15,0),IF($D15="Per kwartaal",IF(MOD(2-$W15,3)=0,$C15,0),$F15)))))) | M15: =IF($C15="","",IF(Dashboard!$C$4="Gemiddeld per maand",$F15,IF(OR($D15="Per maand",$D15="Per week",$D15=""),$F15,IF($D15="Per jaar",IF(3=$W15,$C15,0),IF($D15="Per half jaar",IF(MOD(3-$W15,6)=0,$C15,0),IF($D15="Per kwartaal",IF(MOD(3-$W15,3)=0,$C15,0),$F15)))))) | N15: =IF($C15="","",IF(Dashboard!$C$4="Gemiddeld per maand",$F15,IF(OR($D15="Per maand",$D15="Per week",$D15=""),$F15,IF($D15="Per jaar",IF(4=$W15,$C15,0),IF($D15="Per half jaar",IF(MOD(4-$W15,6)=0,$C15,0),IF($D15="Per kwartaal",IF(MOD(4-$W15,3)=0,$C15,0),$F15)))))) | O15: =IF($C15="","",IF(Dashboard!$C$4="Gemiddeld per maand",$F15,IF(OR($D15="Per maand",$D15="Per week",$D15=""),$F15,IF($D15="Per jaar",IF(5=$W15,$C15,0),IF($D15="Per half jaar",IF(MOD(5-$W15,6)=0,$C15,0),IF($D15="Per kwartaal",IF(MOD(5-$W15,3)=0,$C15,0),$F15)))))) | P15: =IF($C15="","",IF(Dashboard!$C$4="Gemiddeld per maand",$F15,IF(OR($D15="Per maand",$D15="Per week",$D15=""),$F15,IF($D15="Per jaar",IF(6=$W15,$C15,0),IF($D15="Per half jaar",IF(MOD(6-$W15,6)=0,$C15,0),IF($D15="Per kwartaal",IF(MOD(6-$W15,3)=0,$C15,0),$F15)))))) | Q15: =IF($C15="","",IF(Dashboard!$C$4="Gemiddeld per maand",$F15,IF(OR($D15="Per maand",$D15="Per week",$D15=""),$F15,IF($D15="Per jaar",IF(7=$W15,$C15,0),IF($D15="Per half jaar",IF(MOD(7-$W15,6)=0,$C15,0),IF($D15="Per kwartaal",IF(MOD(7-$W15,3)=0,$C15,0),$F15)))))) | R15: =IF($C15="","",IF(Dashboard!$C$4="Gemiddeld per maand",$F15,IF(OR($D15="Per maand",$D15="Per week",$D15=""),$F15,IF($D15="Per jaar",IF(8=$W15,$C15,0),IF($D15="Per half jaar",IF(MOD(8-$W15,6)=0,$C15,0),IF($D15="Per kwartaal",IF(MOD(8-$W15,3)=0,$C15,0),$F15)))))) | S15: =IF($C15="","",IF(Dashboard!$C$4="Gemiddeld per maand",$F15,IF(OR($D15="Per maand",$D15="Per week",$D15=""),$F15,IF($D15="Per jaar",IF(9=$W15,$C15,0),IF($D15="Per half jaar",IF(MOD(9-$W15,6)=0,$C15,0),IF($D15="Per kwartaal",IF(MOD(9-$W15,3)=0,$C15,0),$F15)))))) | T15: =IF($C15="","",IF(Dashboard!$C$4="Gemiddeld per maand",$F15,IF(OR($D15="Per maand",$D15="Per week",$D15=""),$F15,IF($D15="Per jaar",IF(10=$W15,$C15,0),IF($D15="Per half jaar",IF(MOD(10-$W15,6)=0,$C15,0),IF($D15="Per kwartaal",IF(MOD(10-$W15,3)=0,$C15,0),$F15)))))) | U15: =IF($C15="","",IF(Dashboard!$C$4="Gemiddeld per maand",$F15,IF(OR($D15="Per maand",$D15="Per week",$D15=""),$F15,IF($D15="Per jaar",IF(11=$W15,$C15,0),IF($D15="Per half jaar",IF(MOD(11-$W15,6)=0,$C15,0),IF($D15="Per kwartaal",IF(MOD(11-$W15,3)=0,$C15,0),$F15)))))) | V15: =IF($C15="","",IF(Dashboard!$C$4="Gemiddeld per maand",$F15,IF(OR($D15="Per maand",$D15="Per week",$D15=""),$F15,IF($D15="Per jaar",IF(12=$W15,$C15,0),IF($D15="Per half jaar",IF(MOD(12-$W15,6)=0,$C15,0),IF($D15="Per kwartaal",IF(MOD(12-$W15,3)=0,$C15,0),$F15)))))) | W15: =IF($E15="",1,IFERROR(MATCH($E15,Lijsten!$K$6:$K$17,0),1)) -> 1
F16: =IF($C16="","",IF($D16="Per jaar",$C16/12,IF($D16="Per kwartaal",$C16/3,IF($D16="Per half jaar",$C16/6,IF($D16="Per week",$C16*52/12,$C16))))) | J16: =IF($C16="","",IF(Dashboard!$C$4="Gemiddeld per maand",$F16,IF(OR($D16="Per maand",$D16="Per week",$D16=""),$F16,IF($D16="Per jaar",IF(Dashboard!$N$2=$W16,$C16,0),IF($D16="Per half jaar",IF(MOD(Dashboard!$N$2-$W16,6)=0,$C16,0),IF($D16="Per kwartaal",IF(MOD(Dashboard!$N$2-$W16,3)=0,$C16,0),$F16)))))) | K16: =IF($C16="","",IF(Dashboard!$C$4="Gemiddeld per maand",$F16,IF(OR($D16="Per maand",$D16="Per week",$D16=""),$F16,IF($D16="Per jaar",IF(1=$W16,$C16,0),IF($D16="Per half jaar",IF(MOD(1-$W16,6)=0,$C16,0),IF($D16="Per kwartaal",IF(MOD(1-$W16,3)=0,$C16,0),$F16)))))) | L16: =IF($C16="","",IF(Dashboard!$C$4="Gemiddeld per maand",$F16,IF(OR($D16="Per maand",$D16="Per week",$D16=""),$F16,IF($D16="Per jaar",IF(2=$W16,$C16,0),IF($D16="Per half jaar",IF(MOD(2-$W16,6)=0,$C16,0),IF($D16="Per kwartaal",IF(MOD(2-$W16,3)=0,$C16,0),$F16)))))) | M16: =IF($C16="","",IF(Dashboard!$C$4="Gemiddeld per maand",$F16,IF(OR($D16="Per maand",$D16="Per week",$D16=""),$F16,IF($D16="Per jaar",IF(3=$W16,$C16,0),IF($D16="Per half jaar",IF(MOD(3-$W16,6)=0,$C16,0),IF($D16="Per kwartaal",IF(MOD(3-$W16,3)=0,$C16,0),$F16)))))) | N16: =IF($C16="","",IF(Dashboard!$C$4="Gemiddeld per maand",$F16,IF(OR($D16="Per maand",$D16="Per week",$D16=""),$F16,IF($D16="Per jaar",IF(4=$W16,$C16,0),IF($D16="Per half jaar",IF(MOD(4-$W16,6)=0,$C16,0),IF($D16="Per kwartaal",IF(MOD(4-$W16,3)=0,$C16,0),$F16)))))) | O16: =IF($C16="","",IF(Dashboard!$C$4="Gemiddeld per maand",$F16,IF(OR($D16="Per maand",$D16="Per week",$D16=""),$F16,IF($D16="Per jaar",IF(5=$W16,$C16,0),IF($D16="Per half jaar",IF(MOD(5-$W16,6)=0,$C16,0),IF($D16="Per kwartaal",IF(MOD(5-$W16,3)=0,$C16,0),$F16)))))) | P16: =IF($C16="","",IF(Dashboard!$C$4="Gemiddeld per maand",$F16,IF(OR($D16="Per maand",$D16="Per week",$D16=""),$F16,IF($D16="Per jaar",IF(6=$W16,$C16,0),IF($D16="Per half jaar",IF(MOD(6-$W16,6)=0,$C16,0),IF($D16="Per kwartaal",IF(MOD(6-$W16,3)=0,$C16,0),$F16)))))) | Q16: =IF($C16="","",IF(Dashboard!$C$4="Gemiddeld per maand",$F16,IF(OR($D16="Per maand",$D16="Per week",$D16=""),$F16,IF($D16="Per jaar",IF(7=$W16,$C16,0),IF($D16="Per half jaar",IF(MOD(7-$W16,6)=0,$C16,0),IF($D16="Per kwartaal",IF(MOD(7-$W16,3)=0,$C16,0),$F16)))))) | R16: =IF($C16="","",IF(Dashboard!$C$4="Gemiddeld per maand",$F16,IF(OR($D16="Per maand",$D16="Per week",$D16=""),$F16,IF($D16="Per jaar",IF(8=$W16,$C16,0),IF($D16="Per half jaar",IF(MOD(8-$W16,6)=0,$C16,0),IF($D16="Per kwartaal",IF(MOD(8-$W16,3)=0,$C16,0),$F16)))))) | S16: =IF($C16="","",IF(Dashboard!$C$4="Gemiddeld per maand",$F16,IF(OR($D16="Per maand",$D16="Per week",$D16=""),$F16,IF($D16="Per jaar",IF(9=$W16,$C16,0),IF($D16="Per half jaar",IF(MOD(9-$W16,6)=0,$C16,0),IF($D16="Per kwartaal",IF(MOD(9-$W16,3)=0,$C16,0),$F16)))))) | T16: =IF($C16="","",IF(Dashboard!$C$4="Gemiddeld per maand",$F16,IF(OR($D16="Per maand",$D16="Per week",$D16=""),$F16,IF($D16="Per jaar",IF(10=$W16,$C16,0),IF($D16="Per half jaar",IF(MOD(10-$W16,6)=0,$C16,0),IF($D16="Per kwartaal",IF(MOD(10-$W16,3)=0,$C16,0),$F16)))))) | U16: =IF($C16="","",IF(Dashboard!$C$4="Gemiddeld per maand",$F16,IF(OR($D16="Per maand",$D16="Per week",$D16=""),$F16,IF($D16="Per jaar",IF(11=$W16,$C16,0),IF($D16="Per half jaar",IF(MOD(11-$W16,6)=0,$C16,0),IF($D16="Per kwartaal",IF(MOD(11-$W16,3)=0,$C16,0),$F16)))))) | V16: =IF($C16="","",IF(Dashboard!$C$4="Gemiddeld per maand",$F16,IF(OR($D16="Per maand",$D16="Per week",$D16=""),$F16,IF($D16="Per jaar",IF(12=$W16,$C16,0),IF($D16="Per half jaar",IF(MOD(12-$W16,6)=0,$C16,0),IF($D16="Per kwartaal",IF(MOD(12-$W16,3)=0,$C16,0),$F16)))))) | W16: =IF($E16="",1,IFERROR(MATCH($E16,Lijsten!$K$6:$K$17,0),1)) -> 1
F17: =IF($C17="","",IF($D17="Per jaar",$C17/12,IF($D17="Per kwartaal",$C17/3,IF($D17="Per half jaar",$C17/6,IF($D17="Per week",$C17*52/12,$C17))))) | J17: =IF($C17="","",IF(Dashboard!$C$4="Gemiddeld per maand",$F17,IF(OR($D17="Per maand",$D17="Per week",$D17=""),$F17,IF($D17="Per jaar",IF(Dashboard!$N$2=$W17,$C17,0),IF($D17="Per half jaar",IF(MOD(Dashboard!$N$2-$W17,6)=0,$C17,0),IF($D17="Per kwartaal",IF(MOD(Dashboard!$N$2-$W17,3)=0,$C17,0),$F17)))))) | K17: =IF($C17="","",IF(Dashboard!$C$4="Gemiddeld per maand",$F17,IF(OR($D17="Per maand",$D17="Per week",$D17=""),$F17,IF($D17="Per jaar",IF(1=$W17,$C17,0),IF($D17="Per half jaar",IF(MOD(1-$W17,6)=0,$C17,0),IF($D17="Per kwartaal",IF(MOD(1-$W17,3)=0,$C17,0),$F17)))))) | L17: =IF($C17="","",IF(Dashboard!$C$4="Gemiddeld per maand",$F17,IF(OR($D17="Per maand",$D17="Per week",$D17=""),$F17,IF($D17="Per jaar",IF(2=$W17,$C17,0),IF($D17="Per half jaar",IF(MOD(2-$W17,6)=0,$C17,0),IF($D17="Per kwartaal",IF(MOD(2-$W17,3)=0,$C17,0),$F17)))))) | M17: =IF($C17="","",IF(Dashboard!$C$4="Gemiddeld per maand",$F17,IF(OR($D17="Per maand",$D17="Per week",$D17=""),$F17,IF($D17="Per jaar",IF(3=$W17,$C17,0),IF($D17="Per half jaar",IF(MOD(3-$W17,6)=0,$C17,0),IF($D17="Per kwartaal",IF(MOD(3-$W17,3)=0,$C17,0),$F17)))))) | N17: =IF($C17="","",IF(Dashboard!$C$4="Gemiddeld per maand",$F17,IF(OR($D17="Per maand",$D17="Per week",$D17=""),$F17,IF($D17="Per jaar",IF(4=$W17,$C17,0),IF($D17="Per half jaar",IF(MOD(4-$W17,6)=0,$C17,0),IF($D17="Per kwartaal",IF(MOD(4-$W17,3)=0,$C17,0),$F17)))))) | O17: =IF($C17="","",IF(Dashboard!$C$4="Gemiddeld per maand",$F17,IF(OR($D17="Per maand",$D17="Per week",$D17=""),$F17,IF($D17="Per jaar",IF(5=$W17,$C17,0),IF($D17="Per half jaar",IF(MOD(5-$W17,6)=0,$C17,0),IF($D17="Per kwartaal",IF(MOD(5-$W17,3)=0,$C17,0),$F17)))))) | P17: =IF($C17="","",IF(Dashboard!$C$4="Gemiddeld per maand",$F17,IF(OR($D17="Per maand",$D17="Per week",$D17=""),$F17,IF($D17="Per jaar",IF(6=$W17,$C17,0),IF($D17="Per half jaar",IF(MOD(6-$W17,6)=0,$C17,0),IF($D17="Per kwartaal",IF(MOD(6-$W17,3)=0,$C17,0),$F17)))))) | Q17: =IF($C17="","",IF(Dashboard!$C$4="Gemiddeld per maand",$F17,IF(OR($D17="Per maand",$D17="Per week",$D17=""),$F17,IF($D17="Per jaar",IF(7=$W17,$C17,0),IF($D17="Per half jaar",IF(MOD(7-$W17,6)=0,$C17,0),IF($D17="Per kwartaal",IF(MOD(7-$W17,3)=0,$C17,0),$F17)))))) | R17: =IF($C17="","",IF(Dashboard!$C$4="Gemiddeld per maand",$F17,IF(OR($D17="Per maand",$D17="Per week",$D17=""),$F17,IF($D17="Per jaar",IF(8=$W17,$C17,0),IF($D17="Per half jaar",IF(MOD(8-$W17,6)=0,$C17,0),IF($D17="Per kwartaal",IF(MOD(8-$W17,3)=0,$C17,0),$F17)))))) | S17: =IF($C17="","",IF(Dashboard!$C$4="Gemiddeld per maand",$F17,IF(OR($D17="Per maand",$D17="Per week",$D17=""),$F17,IF($D17="Per jaar",IF(9=$W17,$C17,0),IF($D17="Per half jaar",IF(MOD(9-$W17,6)=0,$C17,0),IF($D17="Per kwartaal",IF(MOD(9-$W17,3)=0,$C17,0),$F17)))))) | T17: =IF($C17="","",IF(Dashboard!$C$4="Gemiddeld per maand",$F17,IF(OR($D17="Per maand",$D17="Per week",$D17=""),$F17,IF($D17="Per jaar",IF(10=$W17,$C17,0),IF($D17="Per half jaar",IF(MOD(10-$W17,6)=0,$C17,0),IF($D17="Per kwartaal",IF(MOD(10-$W17,3)=0,$C17,0),$F17)))))) | U17: =IF($C17="","",IF(Dashboard!$C$4="Gemiddeld per maand",$F17,IF(OR($D17="Per maand",$D17="Per week",$D17=""),$F17,IF($D17="Per jaar",IF(11=$W17,$C17,0),IF($D17="Per half jaar",IF(MOD(11-$W17,6)=0,$C17,0),IF($D17="Per kwartaal",IF(MOD(11-$W17,3)=0,$C17,0),$F17)))))) | V17: =IF($C17="","",IF(Dashboard!$C$4="Gemiddeld per maand",$F17,IF(OR($D17="Per maand",$D17="Per week",$D17=""),$F17,IF($D17="Per jaar",IF(12=$W17,$C17,0),IF($D17="Per half jaar",IF(MOD(12-$W17,6)=0,$C17,0),IF($D17="Per kwartaal",IF(MOD(12-$W17,3)=0,$C17,0),$F17)))))) | W17: =IF($E17="",1,IFERROR(MATCH($E17,Lijsten!$K$6:$K$17,0),1)) -> 1
F18: =IF($C18="","",IF($D18="Per jaar",$C18/12,IF($D18="Per kwartaal",$C18/3,IF($D18="Per half jaar",$C18/6,IF($D18="Per week",$C18*52/12,$C18))))) | J18: =IF($C18="","",IF(Dashboard!$C$4="Gemiddeld per maand",$F18,IF(OR($D18="Per maand",$D18="Per week",$D18=""),$F18,IF($D18="Per jaar",IF(Dashboard!$N$2=$W18,$C18,0),IF($D18="Per half jaar",IF(MOD(Dashboard!$N$2-$W18,6)=0,$C18,0),IF($D18="Per kwartaal",IF(MOD(Dashboard!$N$2-$W18,3)=0,$C18,0),$F18)))))) | K18: =IF($C18="","",IF(Dashboard!$C$4="Gemiddeld per maand",$F18,IF(OR($D18="Per maand",$D18="Per week",$D18=""),$F18,IF($D18="Per jaar",IF(1=$W18,$C18,0),IF($D18="Per half jaar",IF(MOD(1-$W18,6)=0,$C18,0),IF($D18="Per kwartaal",IF(MOD(1-$W18,3)=0,$C18,0),$F18)))))) | L18: =IF($C18="","",IF(Dashboard!$C$4="Gemiddeld per maand",$F18,IF(OR($D18="Per maand",$D18="Per week",$D18=""),$F18,IF($D18="Per jaar",IF(2=$W18,$C18,0),IF($D18="Per half jaar",IF(MOD(2-$W18,6)=0,$C18,0),IF($D18="Per kwartaal",IF(MOD(2-$W18,3)=0,$C18,0),$F18)))))) | M18: =IF($C18="","",IF(Dashboard!$C$4="Gemiddeld per maand",$F18,IF(OR($D18="Per maand",$D18="Per week",$D18=""),$F18,IF($D18="Per jaar",IF(3=$W18,$C18,0),IF($D18="Per half jaar",IF(MOD(3-$W18,6)=0,$C18,0),IF($D18="Per kwartaal",IF(MOD(3-$W18,3)=0,$C18,0),$F18)))))) | N18: =IF($C18="","",IF(Dashboard!$C$4="Gemiddeld per maand",$F18,IF(OR($D18="Per maand",$D18="Per week",$D18=""),$F18,IF($D18="Per jaar",IF(4=$W18,$C18,0),IF($D18="Per half jaar",IF(MOD(4-$W18,6)=0,$C18,0),IF($D18="Per kwartaal",IF(MOD(4-$W18,3)=0,$C18,0),$F18)))))) | O18: =IF($C18="","",IF(Dashboard!$C$4="Gemiddeld per maand",$F18,IF(OR($D18="Per maand",$D18="Per week",$D18=""),$F18,IF($D18="Per jaar",IF(5=$W18,$C18,0),IF($D18="Per half jaar",IF(MOD(5-$W18,6)=0,$C18,0),IF($D18="Per kwartaal",IF(MOD(5-$W18,3)=0,$C18,0),$F18)))))) | P18: =IF($C18="","",IF(Dashboard!$C$4="Gemiddeld per maand",$F18,IF(OR($D18="Per maand",$D18="Per week",$D18=""),$F18,IF($D18="Per jaar",IF(6=$W18,$C18,0),IF($D18="Per half jaar",IF(MOD(6-$W18,6)=0,$C18,0),IF($D18="Per kwartaal",IF(MOD(6-$W18,3)=0,$C18,0),$F18)))))) | Q18: =IF($C18="","",IF(Dashboard!$C$4="Gemiddeld per maand",$F18,IF(OR($D18="Per maand",$D18="Per week",$D18=""),$F18,IF($D18="Per jaar",IF(7=$W18,$C18,0),IF($D18="Per half jaar",IF(MOD(7-$W18,6)=0,$C18,0),IF($D18="Per kwartaal",IF(MOD(7-$W18,3)=0,$C18,0),$F18)))))) | R18: =IF($C18="","",IF(Dashboard!$C$4="Gemiddeld per maand",$F18,IF(OR($D18="Per maand",$D18="Per week",$D18=""),$F18,IF($D18="Per jaar",IF(8=$W18,$C18,0),IF($D18="Per half jaar",IF(MOD(8-$W18,6)=0,$C18,0),IF($D18="Per kwartaal",IF(MOD(8-$W18,3)=0,$C18,0),$F18)))))) | S18: =IF($C18="","",IF(Dashboard!$C$4="Gemiddeld per maand",$F18,IF(OR($D18="Per maand",$D18="Per week",$D18=""),$F18,IF($D18="Per jaar",IF(9=$W18,$C18,0),IF($D18="Per half jaar",IF(MOD(9-$W18,6)=0,$C18,0),IF($D18="Per kwartaal",IF(MOD(9-$W18,3)=0,$C18,0),$F18)))))) | T18: =IF($C18="","",IF(Dashboard!$C$4="Gemiddeld per maand",$F18,IF(OR($D18="Per maand",$D18="Per week",$D18=""),$F18,IF($D18="Per jaar",IF(10=$W18,$C18,0),IF($D18="Per half jaar",IF(MOD(10-$W18,6)=0,$C18,0),IF($D18="Per kwartaal",IF(MOD(10-$W18,3)=0,$C18,0),$F18)))))) | U18: =IF($C18="","",IF(Dashboard!$C$4="Gemiddeld per maand",$F18,IF(OR($D18="Per maand",$D18="Per week",$D18=""),$F18,IF($D18="Per jaar",IF(11=$W18,$C18,0),IF($D18="Per half jaar",IF(MOD(11-$W18,6)=0,$C18,0),IF($D18="Per kwartaal",IF(MOD(11-$W18,3)=0,$C18,0),$F18)))))) | V18: =IF($C18="","",IF(Dashboard!$C$4="Gemiddeld per maand",$F18,IF(OR($D18="Per maand",$D18="Per week",$D18=""),$F18,IF($D18="Per jaar",IF(12=$W18,$C18,0),IF($D18="Per half jaar",IF(MOD(12-$W18,6)=0,$C18,0),IF($D18="Per kwartaal",IF(MOD(12-$W18,3)=0,$C18,0),$F18)))))) | W18: =IF($E18="",1,IFERROR(MATCH($E18,Lijsten!$K$6:$K$17,0),1)) -> 1
F19: =IF($C19="","",IF($D19="Per jaar",$C19/12,IF($D19="Per kwartaal",$C19/3,IF($D19="Per half jaar",$C19/6,IF($D19="Per week",$C19*52/12,$C19))))) | J19: =IF($C19="","",IF(Dashboard!$C$4="Gemiddeld per maand",$F19,IF(OR($D19="Per maand",$D19="Per week",$D19=""),$F19,IF($D19="Per jaar",IF(Dashboard!$N$2=$W19,$C19,0),IF($D19="Per half jaar",IF(MOD(Dashboard!$N$2-$W19,6)=0,$C19,0),IF($D19="Per kwartaal",IF(MOD(Dashboard!$N$2-$W19,3)=0,$C19,0),$F19)))))) | K19: =IF($C19="","",IF(Dashboard!$C$4="Gemiddeld per maand",$F19,IF(OR($D19="Per maand",$D19="Per week",$D19=""),$F19,IF($D19="Per jaar",IF(1=$W19,$C19,0),IF($D19="Per half jaar",IF(MOD(1-$W19,6)=0,$C19,0),IF($D19="Per kwartaal",IF(MOD(1-$W19,3)=0,$C19,0),$F19)))))) | L19: =IF($C19="","",IF(Dashboard!$C$4="Gemiddeld per maand",$F19,IF(OR($D19="Per maand",$D19="Per week",$D19=""),$F19,IF($D19="Per jaar",IF(2=$W19,$C19,0),IF($D19="Per half jaar",IF(MOD(2-$W19,6)=0,$C19,0),IF($D19="Per kwartaal",IF(MOD(2-$W19,3)=0,$C19,0),$F19)))))) | M19: =IF($C19="","",IF(Dashboard!$C$4="Gemiddeld per maand",$F19,IF(OR($D19="Per maand",$D19="Per week",$D19=""),$F19,IF($D19="Per jaar",IF(3=$W19,$C19,0),IF($D19="Per half jaar",IF(MOD(3-$W19,6)=0,$C19,0),IF($D19="Per kwartaal",IF(MOD(3-$W19,3)=0,$C19,0),$F19)))))) | N19: =IF($C19="","",IF(Dashboard!$C$4="Gemiddeld per maand",$F19,IF(OR($D19="Per maand",$D19="Per week",$D19=""),$F19,IF($D19="Per jaar",IF(4=$W19,$C19,0),IF($D19="Per half jaar",IF(MOD(4-$W19,6)=0,$C19,0),IF($D19="Per kwartaal",IF(MOD(4-$W19,3)=0,$C19,0),$F19)))))) | O19: =IF($C19="","",IF(Dashboard!$C$4="Gemiddeld per maand",$F19,IF(OR($D19="Per maand",$D19="Per week",$D19=""),$F19,IF($D19="Per jaar",IF(5=$W19,$C19,0),IF($D19="Per half jaar",IF(MOD(5-$W19,6)=0,$C19,0),IF($D19="Per kwartaal",IF(MOD(5-$W19,3)=0,$C19,0),$F19)))))) | P19: =IF($C19="","",IF(Dashboard!$C$4="Gemiddeld per maand",$F19,IF(OR($D19="Per maand",$D19="Per week",$D19=""),$F19,IF($D19="Per jaar",IF(6=$W19,$C19,0),IF($D19="Per half jaar",IF(MOD(6-$W19,6)=0,$C19,0),IF($D19="Per kwartaal",IF(MOD(6-$W19,3)=0,$C19,0),$F19)))))) | Q19: =IF($C19="","",IF(Dashboard!$C$4="Gemiddeld per maand",$F19,IF(OR($D19="Per maand",$D19="Per week",$D19=""),$F19,IF($D19="Per jaar",IF(7=$W19,$C19,0),IF($D19="Per half jaar",IF(MOD(7-$W19,6)=0,$C19,0),IF($D19="Per kwartaal",IF(MOD(7-$W19,3)=0,$C19,0),$F19)))))) | R19: =IF($C19="","",IF(Dashboard!$C$4="Gemiddeld per maand",$F19,IF(OR($D19="Per maand",$D19="Per week",$D19=""),$F19,IF($D19="Per jaar",IF(8=$W19,$C19,0),IF($D19="Per half jaar",IF(MOD(8-$W19,6)=0,$C19,0),IF($D19="Per kwartaal",IF(MOD(8-$W19,3)=0,$C19,0),$F19)))))) | S19: =IF($C19="","",IF(Dashboard!$C$4="Gemiddeld per maand",$F19,IF(OR($D19="Per maand",$D19="Per week",$D19=""),$F19,IF($D19="Per jaar",IF(9=$W19,$C19,0),IF($D19="Per half jaar",IF(MOD(9-$W19,6)=0,$C19,0),IF($D19="Per kwartaal",IF(MOD(9-$W19,3)=0,$C19,0),$F19)))))) | T19: =IF($C19="","",IF(Dashboard!$C$4="Gemiddeld per maand",$F19,IF(OR($D19="Per maand",$D19="Per week",$D19=""),$F19,IF($D19="Per jaar",IF(10=$W19,$C19,0),IF($D19="Per half jaar",IF(MOD(10-$W19,6)=0,$C19,0),IF($D19="Per kwartaal",IF(MOD(10-$W19,3)=0,$C19,0),$F19)))))) | U19: =IF($C19="","",IF(Dashboard!$C$4="Gemiddeld per maand",$F19,IF(OR($D19="Per maand",$D19="Per week",$D19=""),$F19,IF($D19="Per jaar",IF(11=$W19,$C19,0),IF($D19="Per half jaar",IF(MOD(11-$W19,6)=0,$C19,0),IF($D19="Per kwartaal",IF(MOD(11-$W19,3)=0,$C19,0),$F19)))))) | V19: =IF($C19="","",IF(Dashboard!$C$4="Gemiddeld per maand",$F19,IF(OR($D19="Per maand",$D19="Per week",$D19=""),$F19,IF($D19="Per jaar",IF(12=$W19,$C19,0),IF($D19="Per half jaar",IF(MOD(12-$W19,6)=0,$C19,0),IF($D19="Per kwartaal",IF(MOD(12-$W19,3)=0,$C19,0),$F19)))))) | W19: =IF($E19="",1,IFERROR(MATCH($E19,Lijsten!$K$6:$K$17,0),1)) -> 1
F20: =IF($C20="","",IF($D20="Per jaar",$C20/12,IF($D20="Per kwartaal",$C20/3,IF($D20="Per half jaar",$C20/6,IF($D20="Per week",$C20*52/12,$C20))))) | J20: =IF($C20="","",IF(Dashboard!$C$4="Gemiddeld per maand",$F20,IF(OR($D20="Per maand",$D20="Per week",$D20=""),$F20,IF($D20="Per jaar",IF(Dashboard!$N$2=$W20,$C20,0),IF($D20="Per half jaar",IF(MOD(Dashboard!$N$2-$W20,6)=0,$C20,0),IF($D20="Per kwartaal",IF(MOD(Dashboard!$N$2-$W20,3)=0,$C20,0),$F20)))))) | K20: =IF($C20="","",IF(Dashboard!$C$4="Gemiddeld per maand",$F20,IF(OR($D20="Per maand",$D20="Per week",$D20=""),$F20,IF($D20="Per jaar",IF(1=$W20,$C20,0),IF($D20="Per half jaar",IF(MOD(1-$W20,6)=0,$C20,0),IF($D20="Per kwartaal",IF(MOD(1-$W20,3)=0,$C20,0),$F20)))))) | L20: =IF($C20="","",IF(Dashboard!$C$4="Gemiddeld per maand",$F20,IF(OR($D20="Per maand",$D20="Per week",$D20=""),$F20,IF($D20="Per jaar",IF(2=$W20,$C20,0),IF($D20="Per half jaar",IF(MOD(2-$W20,6)=0,$C20,0),IF($D20="Per kwartaal",IF(MOD(2-$W20,3)=0,$C20,0),$F20)))))) | M20: =IF($C20="","",IF(Dashboard!$C$4="Gemiddeld per maand",$F20,IF(OR($D20="Per maand",$D20="Per week",$D20=""),$F20,IF($D20="Per jaar",IF(3=$W20,$C20,0),IF($D20="Per half jaar",IF(MOD(3-$W20,6)=0,$C20,0),IF($D20="Per kwartaal",IF(MOD(3-$W20,3)=0,$C20,0),$F20)))))) | N20: =IF($C20="","",IF(Dashboard!$C$4="Gemiddeld per maand",$F20,IF(OR($D20="Per maand",$D20="Per week",$D20=""),$F20,IF($D20="Per jaar",IF(4=$W20,$C20,0),IF($D20="Per half jaar",IF(MOD(4-$W20,6)=0,$C20,0),IF($D20="Per kwartaal",IF(MOD(4-$W20,3)=0,$C20,0),$F20)))))) | O20: =IF($C20="","",IF(Dashboard!$C$4="Gemiddeld per maand",$F20,IF(OR($D20="Per maand",$D20="Per week",$D20=""),$F20,IF($D20="Per jaar",IF(5=$W20,$C20,0),IF($D20="Per half jaar",IF(MOD(5-$W20,6)=0,$C20,0),IF($D20="Per kwartaal",IF(MOD(5-$W20,3)=0,$C20,0),$F20)))))) | P20: =IF($C20="","",IF(Dashboard!$C$4="Gemiddeld per maand",$F20,IF(OR($D20="Per maand",$D20="Per week",$D20=""),$F20,IF($D20="Per jaar",IF(6=$W20,$C20,0),IF($D20="Per half jaar",IF(MOD(6-$W20,6)=0,$C20,0),IF($D20="Per kwartaal",IF(MOD(6-$W20,3)=0,$C20,0),$F20)))))) | Q20: =IF($C20="","",IF(Dashboard!$C$4="Gemiddeld per maand",$F20,IF(OR($D20="Per maand",$D20="Per week",$D20=""),$F20,IF($D20="Per jaar",IF(7=$W20,$C20,0),IF($D20="Per half jaar",IF(MOD(7-$W20,6)=0,$C20,0),IF($D20="Per kwartaal",IF(MOD(7-$W20,3)=0,$C20,0),$F20)))))) | R20: =IF($C20="","",IF(Dashboard!$C$4="Gemiddeld per maand",$F20,IF(OR($D20="Per maand",$D20="Per week",$D20=""),$F20,IF($D20="Per jaar",IF(8=$W20,$C20,0),IF($D20="Per half jaar",IF(MOD(8-$W20,6)=0,$C20,0),IF($D20="Per kwartaal",IF(MOD(8-$W20,3)=0,$C20,0),$F20)))))) | S20: =IF($C20="","",IF(Dashboard!$C$4="Gemiddeld per maand",$F20,IF(OR($D20="Per maand",$D20="Per week",$D20=""),$F20,IF($D20="Per jaar",IF(9=$W20,$C20,0),IF($D20="Per half jaar",IF(MOD(9-$W20,6)=0,$C20,0),IF($D20="Per kwartaal",IF(MOD(9-$W20,3)=0,$C20,0),$F20)))))) | T20: =IF($C20="","",IF(Dashboard!$C$4="Gemiddeld per maand",$F20,IF(OR($D20="Per maand",$D20="Per week",$D20=""),$F20,IF($D20="Per jaar",IF(10=$W20,$C20,0),IF($D20="Per half jaar",IF(MOD(10-$W20,6)=0,$C20,0),IF($D20="Per kwartaal",IF(MOD(10-$W20,3)=0,$C20,0),$F20)))))) | U20: =IF($C20="","",IF(Dashboard!$C$4="Gemiddeld per maand",$F20,IF(OR($D20="Per maand",$D20="Per week",$D20=""),$F20,IF($D20="Per jaar",IF(11=$W20,$C20,0),IF($D20="Per half jaar",IF(MOD(11-$W20,6)=0,$C20,0),IF($D20="Per kwartaal",IF(MOD(11-$W20,3)=0,$C20,0),$F20)))))) | V20: =IF($C20="","",IF(Dashboard!$C$4="Gemiddeld per maand",$F20,IF(OR($D20="Per maand",$D20="Per week",$D20=""),$F20,IF($D20="Per jaar",IF(12=$W20,$C20,0),IF($D20="Per half jaar",IF(MOD(12-$W20,6)=0,$C20,0),IF($D20="Per kwartaal",IF(MOD(12-$W20,3)=0,$C20,0),$F20)))))) | W20: =IF($E20="",1,IFERROR(MATCH($E20,Lijsten!$K$6:$K$17,0),1)) -> 1
F21: =IF($C21="","",IF($D21="Per jaar",$C21/12,IF($D21="Per kwartaal",$C21/3,IF($D21="Per half jaar",$C21/6,IF($D21="Per week",$C21*52/12,$C21))))) | J21: =IF($C21="","",IF(Dashboard!$C$4="Gemiddeld per maand",$F21,IF(OR($D21="Per maand",$D21="Per week",$D21=""),$F21,IF($D21="Per jaar",IF(Dashboard!$N$2=$W21,$C21,0),IF($D21="Per half jaar",IF(MOD(Dashboard!$N$2-$W21,6)=0,$C21,0),IF($D21="Per kwartaal",IF(MOD(Dashboard!$N$2-$W21,3)=0,$C21,0),$F21)))))) | K21: =IF($C21="","",IF(Dashboard!$C$4="Gemiddeld per maand",$F21,IF(OR($D21="Per maand",$D21="Per week",$D21=""),$F21,IF($D21="Per jaar",IF(1=$W21,$C21,0),IF($D21="Per half jaar",IF(MOD(1-$W21,6)=0,$C21,0),IF($D21="Per kwartaal",IF(MOD(1-$W21,3)=0,$C21,0),$F21)))))) | L21: =IF($C21="","",IF(Dashboard!$C$4="Gemiddeld per maand",$F21,IF(OR($D21="Per maand",$D21="Per week",$D21=""),$F21,IF($D21="Per jaar",IF(2=$W21,$C21,0),IF($D21="Per half jaar",IF(MOD(2-$W21,6)=0,$C21,0),IF($D21="Per kwartaal",IF(MOD(2-$W21,3)=0,$C21,0),$F21)))))) | M21: =IF($C21="","",IF(Dashboard!$C$4="Gemiddeld per maand",$F21,IF(OR($D21="Per maand",$D21="Per week",$D21=""),$F21,IF($D21="Per jaar",IF(3=$W21,$C21,0),IF($D21="Per half jaar",IF(MOD(3-$W21,6)=0,$C21,0),IF($D21="Per kwartaal",IF(MOD(3-$W21,3)=0,$C21,0),$F21)))))) | N21: =IF($C21="","",IF(Dashboard!$C$4="Gemiddeld per maand",$F21,IF(OR($D21="Per maand",$D21="Per week",$D21=""),$F21,IF($D21="Per jaar",IF(4=$W21,$C21,0),IF($D21="Per half jaar",IF(MOD(4-$W21,6)=0,$C21,0),IF($D21="Per kwartaal",IF(MOD(4-$W21,3)=0,$C21,0),$F21)))))) | O21: =IF($C21="","",IF(Dashboard!$C$4="Gemiddeld per maand",$F21,IF(OR($D21="Per maand",$D21="Per week",$D21=""),$F21,IF($D21="Per jaar",IF(5=$W21,$C21,0),IF($D21="Per half jaar",IF(MOD(5-$W21,6)=0,$C21,0),IF($D21="Per kwartaal",IF(MOD(5-$W21,3)=0,$C21,0),$F21)))))) | P21: =IF($C21="","",IF(Dashboard!$C$4="Gemiddeld per maand",$F21,IF(OR($D21="Per maand",$D21="Per week",$D21=""),$F21,IF($D21="Per jaar",IF(6=$W21,$C21,0),IF($D21="Per half jaar",IF(MOD(6-$W21,6)=0,$C21,0),IF($D21="Per kwartaal",IF(MOD(6-$W21,3)=0,$C21,0),$F21)))))) | Q21: =IF($C21="","",IF(Dashboard!$C$4="Gemiddeld per maand",$F21,IF(OR($D21="Per maand",$D21="Per week",$D21=""),$F21,IF($D21="Per jaar",IF(7=$W21,$C21,0),IF($D21="Per half jaar",IF(MOD(7-$W21,6)=0,$C21,0),IF($D21="Per kwartaal",IF(MOD(7-$W21,3)=0,$C21,0),$F21)))))) | R21: =IF($C21="","",IF(Dashboard!$C$4="Gemiddeld per maand",$F21,IF(OR($D21="Per maand",$D21="Per week",$D21=""),$F21,IF($D21="Per jaar",IF(8=$W21,$C21,0),IF($D21="Per half jaar",IF(MOD(8-$W21,6)=0,$C21,0),IF($D21="Per kwartaal",IF(MOD(8-$W21,3)=0,$C21,0),$F21)))))) | S21: =IF($C21="","",IF(Dashboard!$C$4="Gemiddeld per maand",$F21,IF(OR($D21="Per maand",$D21="Per week",$D21=""),$F21,IF($D21="Per jaar",IF(9=$W21,$C21,0),IF($D21="Per half jaar",IF(MOD(9-$W21,6)=0,$C21,0),IF($D21="Per kwartaal",IF(MOD(9-$W21,3)=0,$C21,0),$F21)))))) | T21: =IF($C21="","",IF(Dashboard!$C$4="Gemiddeld per maand",$F21,IF(OR($D21="Per maand",$D21="Per week",$D21=""),$F21,IF($D21="Per jaar",IF(10=$W21,$C21,0),IF($D21="Per half jaar",IF(MOD(10-$W21,6)=0,$C21,0),IF($D21="Per kwartaal",IF(MOD(10-$W21,3)=0,$C21,0),$F21)))))) | U21: =IF($C21="","",IF(Dashboard!$C$4="Gemiddeld per maand",$F21,IF(OR($D21="Per maand",$D21="Per week",$D21=""),$F21,IF($D21="Per jaar",IF(11=$W21,$C21,0),IF($D21="Per half jaar",IF(MOD(11-$W21,6)=0,$C21,0),IF($D21="Per kwartaal",IF(MOD(11-$W21,3)=0,$C21,0),$F21)))))) | V21: =IF($C21="","",IF(Dashboard!$C$4="Gemiddeld per maand",$F21,IF(OR($D21="Per maand",$D21="Per week",$D21=""),$F21,IF($D21="Per jaar",IF(12=$W21,$C21,0),IF($D21="Per half jaar",IF(MOD(12-$W21,6)=0,$C21,0),IF($D21="Per kwartaal",IF(MOD(12-$W21,3)=0,$C21,0),$F21)))))) | W21: =IF($E21="",1,IFERROR(MATCH($E21,Lijsten!$K$6:$K$17,0),1)) -> 1
... F207: =IF($C207="","",IF($D207="Per jaar",$C207/12,IF($D207="Per kwartaal",$C207/3,IF($D207="Per half jaar",$C207/6,IF($D207="Per week",$C207*52/12,$C207))))) | J207: =IF($C207="","",IF(Dashboard!$C$4="Gemiddeld per maand",$F207,IF(OR($D207="Per maand",$D207="Per week",$D207=""),$F207,IF($D207="Per jaar",IF(Dashboard!$N$2=$W207,$C207,0),IF($D207="Per half jaar",IF(MOD(Dashboard!$N$2-$W207,6)=0,$C207,0),IF($D207="Per kwartaal",IF(MOD(Dashboard!$N$2-$W207,3)=0,$C207,0),$F207)))))) | K207: =IF($C207="","",IF(Dashboard!$C$4="Gemiddeld per maand",$F207,IF(OR($D207="Per maand",$D207="Per week",$D207=""),$F207,IF($D207="Per jaar",IF(1=$W207,$C207,0),IF($D207="Per half jaar",IF(MOD(1-$W207,6)=0,$C207,0),IF($D207="Per kwartaal",IF(MOD(1-$W207,3)=0,$C207,0),$F207)))))) | L207: =IF($C207="","",IF(Dashboard!$C$4="Gemiddeld per maand",$F207,IF(OR($D207="Per maand",$D207="Per week",$D207=""),$F207,IF($D207="Per jaar",IF(2=$W207,$C207,0),IF($D207="Per half jaar",IF(MOD(2-$W207,6)=0,$C207,0),IF($D207="Per kwartaal",IF(MOD(2-$W207,3)=0,$C207,0),$F207)))))) | M207: =IF($C207="","",IF(Dashboard!$C$4="Gemiddeld per maand",$F207,IF(OR($D207="Per maand",$D207="Per week",$D207=""),$F207,IF($D207="Per jaar",IF(3=$W207,$C207,0),IF($D207="Per half jaar",IF(MOD(3-$W207,6)=0,$C207,0),IF($D207="Per kwartaal",IF(MOD(3-$W207,3)=0,$C207,0),$F207)))))) | N207: =IF($C207="","",IF(Dashboard!$C$4="Gemiddeld per maand",$F207,IF(OR($D207="Per maand",$D207="Per week",$D207=""),$F207,IF($D207="Per jaar",IF(4=$W207,$C207,0),IF($D207="Per half jaar",IF(MOD(4-$W207,6)=0,$C207,0),IF($D207="Per kwartaal",IF(MOD(4-$W207,3)=0,$C207,0),$F207)))))) | O207: =IF($C207="","",IF(Dashboard!$C$4="Gemiddeld per maand",$F207,IF(OR($D207="Per maand",$D207="Per week",$D207=""),$F207,IF($D207="Per jaar",IF(5=$W207,$C207,0),IF($D207="Per half jaar",IF(MOD(5-$W207,6)=0,$C207,0),IF($D207="Per kwartaal",IF(MOD(5-$W207,3)=0,$C207,0),$F207)))))) | P207: =IF($C207="","",IF(Dashboard!$C$4="Gemiddeld per maand",$F207,IF(OR($D207="Per maand",$D207="Per week",$D207=""),$F207,IF($D207="Per jaar",IF(6=$W207,$C207,0),IF($D207="Per half jaar",IF(MOD(6-$W207,6)=0,$C207,0),IF($D207="Per kwartaal",IF(MOD(6-$W207,3)=0,$C207,0),$F207)))))) | Q207: =IF($C207="","",IF(Dashboard!$C$4="Gemiddeld per maand",$F207,IF(OR($D207="Per maand",$D207="Per week",$D207=""),$F207,IF($D207="Per jaar",IF(7=$W207,$C207,0),IF($D207="Per half jaar",IF(MOD(7-$W207,6)=0,$C207,0),IF($D207="Per kwartaal",IF(MOD(7-$W207,3)=0,$C207,0),$F207)))))) | R207: =IF($C207="","",IF(Dashboard!$C$4="Gemiddeld per maand",$F207,IF(OR($D207="Per maand",$D207="Per week",$D207=""),$F207,IF($D207="Per jaar",IF(8=$W207,$C207,0),IF($D207="Per half jaar",IF(MOD(8-$W207,6)=0,$C207,0),IF($D207="Per kwartaal",IF(MOD(8-$W207,3)=0,$C207,0),$F207)))))) | S207: =IF($C207="","",IF(Dashboard!$C$4="Gemiddeld per maand",$F207,IF(OR($D207="Per maand",$D207="Per week",$D207=""),$F207,IF($D207="Per jaar",IF(9=$W207,$C207,0),IF($D207="Per half jaar",IF(MOD(9-$W207,6)=0,$C207,0),IF($D207="Per kwartaal",IF(MOD(9-$W207,3)=0,$C207,0),$F207)))))) | T207: =IF($C207="","",IF(Dashboard!$C$4="Gemiddeld per maand",$F207,IF(OR($D207="Per maand",$D207="Per week",$D207=""),$F207,IF($D207="Per jaar",IF(10=$W207,$C207,0),IF($D207="Per half jaar",IF(MOD(10-$W207,6)=0,$C207,0),IF($D207="Per kwartaal",IF(MOD(10-$W207,3)=0,$C207,0),$F207)))))) | U207: =IF($C207="","",IF(Dashboard!$C$4="Gemiddeld per maand",$F207,IF(OR($D207="Per maand",$D207="Per week",$D207=""),$F207,IF($D207="Per jaar",IF(11=$W207,$C207,0),IF($D207="Per half jaar",IF(MOD(11-$W207,6)=0,$C207,0),IF($D207="Per kwartaal",IF(MOD(11-$W207,3)=0,$C207,0),$F207)))))) | V207: =IF($C207="","",IF(Dashboard!$C$4="Gemiddeld per maand",$F207,IF(OR($D207="Per maand",$D207="Per week",$D207=""),$F207,IF($D207="Per jaar",IF(12=$W207,$C207,0),IF($D207="Per half jaar",IF(MOD(12-$W207,6)=0,$C207,0),IF($D207="Per kwartaal",IF(MOD(12-$W207,3)=0,$C207,0),$F207)))))) | W207: =IF($E207="",1,IFERROR(MATCH($E207,Lijsten!$K$6:$K$17,0),1)) -> 1

Sheet Vaste inkomsten
A1: VASTE INKOMSTEN | F1: ⌂ Menu | G1: Dashboard ▸
A2: Alles wat regelmatig binnenkomt. Losse inkomsten (verkoop, teruggave) horen op Transacties.
A3: Betaal je iets per kwartaal of per jaar? Zet het factuurbedrag in 'Bedrag', kies de frequentie en vul de betaalmaand in.
A5: Totaal vaste inkomsten per maand | F5: =SUMIFS($F$8:$F$37,$H$8:$H$37,"Ja") -> 2800 | G5: =COUNTIF($H$8:$H$37,"Ja")&" actieve regels" -> 1 actieve regels | J5: in gekozen maand:
J6: =SUMIFS($J$8:$J$37,$H$8:$H$37,"Ja") -> 2800
A7: Omschrijving | B7: Bron | C7: Bedrag | D7: Frequentie | E7: Betaalmaand | F7: Bedrag p/m | G7: Categorie | H7: Actief | I7: Notitie | J7: Bedrag deze maand | K7: januari | L7: februari | M7: maart | N7: april | O7: mei | P7: juni | Q7: juli | R7: augustus | S7: september | T7: oktober | U7: november | V7: december | W7: mnr
A8: Salaris | B8: Werkgever | C8: 2800 | D8: Per maand | F8: =IF($C8="","",IF($D8="Per jaar",$C8/12,IF($D8="Per kwartaal",$C8/3,IF($D8="Per half jaar",$C8/6,IF($D8="Per week",$C8*52/12,$C8))))) -> 2800 | G8: Salaris | H8: Ja | I8: VOORBEELDREGEL — vervang door je eigen netto salaris | J8: =IF($C8="","",IF(Dashboard!$C$4="Gemiddeld per maand",$F8,IF(OR($D8="Per maand",$D8="Per week",$D8=""),$F8,IF($D8="Per jaar",IF(Dashboard!$N$2=$W8,$C8,0),IF($D8="Per half jaar",IF(MOD(Dashboard!$N$2-$W8,6)=0,$C8,0),IF($D8="Per kwartaal",IF(MOD(Dashboard!$N$2-$W8,3)=0,$C8,0),$F8)))))) -> 2800 | K8: =IF($C8="","",IF(Dashboard!$C$4="Gemiddeld per maand",$F8,IF(OR($D8="Per maand",$D8="Per week",$D8=""),$F8,IF($D8="Per jaar",IF(1=$W8,$C8,0),IF($D8="Per half jaar",IF(MOD(1-$W8,6)=0,$C8,0),IF($D8="Per kwartaal",IF(MOD(1-$W8,3)=0,$C8,0),$F8)))))) -> 2800 | L8: =IF($C8="","",IF(Dashboard!$C$4="Gemiddeld per maand",$F8,IF(OR($D8="Per maand",$D8="Per week",$D8=""),$F8,IF($D8="Per jaar",IF(2=$W8,$C8,0),IF($D8="Per half jaar",IF(MOD(2-$W8,6)=0,$C8,0),IF($D8="Per kwartaal",IF(MOD(2-$W8,3)=0,$C8,0),$F8)))))) -> 2800 | M8: =IF($C8="","",IF(Dashboard!$C$4="Gemiddeld per maand",$F8,IF(OR($D8="Per maand",$D8="Per week",$D8=""),$F8,IF($D8="Per jaar",IF(3=$W8,$C8,0),IF($D8="Per half jaar",IF(MOD(3-$W8,6)=0,$C8,0),IF($D8="Per kwartaal",IF(MOD(3-$W8,3)=0,$C8,0),$F8)))))) -> 2800 | N8: =IF($C8="","",IF(Dashboard!$C$4="Gemiddeld per maand",$F8,IF(OR($D8="Per maand",$D8="Per week",$D8=""),$F8,IF($D8="Per jaar",IF(4=$W8,$C8,0),IF($D8="Per half jaar",IF(MOD(4-$W8,6)=0,$C8,0),IF($D8="Per kwartaal",IF(MOD(4-$W8,3)=0,$C8,0),$F8)))))) -> 2800 | O8: =IF($C8="","",IF(Dashboard!$C$4="Gemiddeld per maand",$F8,IF(OR($D8="Per maand",$D8="Per week",$D8=""),$F8,IF($D8="Per jaar",IF(5=$W8,$C8,0),IF($D8="Per half jaar",IF(MOD(5-$W8,6)=0,$C8,0),IF($D8="Per kwartaal",IF(MOD(5-$W8,3)=0,$C8,0),$F8)))))) -> 2800 | P8: =IF($C8="","",IF(Dashboard!$C$4="Gemiddeld per maand",$F8,IF(OR($D8="Per maand",$D8="Per week",$D8=""),$F8,IF($D8="Per jaar",IF(6=$W8,$C8,0),IF($D8="Per half jaar",IF(MOD(6-$W8,6)=0,$C8,0),IF($D8="Per kwartaal",IF(MOD(6-$W8,3)=0,$C8,0),$F8)))))) -> 2800 | Q8: =IF($C8="","",IF(Dashboard!$C$4="Gemiddeld per maand",$F8,IF(OR($D8="Per maand",$D8="Per week",$D8=""),$F8,IF($D8="Per jaar",IF(7=$W8,$C8,0),IF($D8="Per half jaar",IF(MOD(7-$W8,6)=0,$C8,0),IF($D8="Per kwartaal",IF(MOD(7-$W8,3)=0,$C8,0),$F8)))))) -> 2800 | R8: =IF($C8="","",IF(Dashboard!$C$4="Gemiddeld per maand",$F8,IF(OR($D8="Per maand",$D8="Per week",$D8=""),$F8,IF($D8="Per jaar",IF(8=$W8,$C8,0),IF($D8="Per half jaar",IF(MOD(8-$W8,6)=0,$C8,0),IF($D8="Per kwartaal",IF(MOD(8-$W8,3)=0,$C8,0),$F8)))))) -> 2800 | S8: =IF($C8="","",IF(Dashboard!$C$4="Gemiddeld per maand",$F8,IF(OR($D8="Per maand",$D8="Per week",$D8=""),$F8,IF($D8="Per jaar",IF(9=$W8,$C8,0),IF($D8="Per half jaar",IF(MOD(9-$W8,6)=0,$C8,0),IF($D8="Per kwartaal",IF(MOD(9-$W8,3)=0,$C8,0),$F8)))))) -> 2800 | T8: =IF($C8="","",IF(Dashboard!$C$4="Gemiddeld per maand",$F8,IF(OR($D8="Per maand",$D8="Per week",$D8=""),$F8,IF($D8="Per jaar",IF(10=$W8,$C8,0),IF($D8="Per half jaar",IF(MOD(10-$W8,6)=0,$C8,0),IF($D8="Per kwartaal",IF(MOD(10-$W8,3)=0,$C8,0),$F8)))))) -> 2800 | U8: =IF($C8="","",IF(Dashboard!$C$4="Gemiddeld per maand",$F8,IF(OR($D8="Per maand",$D8="Per week",$D8=""),$F8,IF($D8="Per jaar",IF(11=$W8,$C8,0),IF($D8="Per half jaar",IF(MOD(11-$W8,6)=0,$C8,0),IF($D8="Per kwartaal",IF(MOD(11-$W8,3)=0,$C8,0),$F8)))))) -> 2800 | V8: =IF($C8="","",IF(Dashboard!$C$4="Gemiddeld per maand",$F8,IF(OR($D8="Per maand",$D8="Per week",$D8=""),$F8,IF($D8="Per jaar",IF(12=$W8,$C8,0),IF($D8="Per half jaar",IF(MOD(12-$W8,6)=0,$C8,0),IF($D8="Per kwartaal",IF(MOD(12-$W8,3)=0,$C8,0),$F8)))))) -> 2800 | W8: =IF($E8="",1,IFERROR(MATCH($E8,Lijsten!$K$6:$K$17,0),1)) -> 1
F9: =IF($C9="","",IF($D9="Per jaar",$C9/12,IF($D9="Per kwartaal",$C9/3,IF($D9="Per half jaar",$C9/6,IF($D9="Per week",$C9*52/12,$C9))))) | J9: =IF($C9="","",IF(Dashboard!$C$4="Gemiddeld per maand",$F9,IF(OR($D9="Per maand",$D9="Per week",$D9=""),$F9,IF($D9="Per jaar",IF(Dashboard!$N$2=$W9,$C9,0),IF($D9="Per half jaar",IF(MOD(Dashboard!$N$2-$W9,6)=0,$C9,0),IF($D9="Per kwartaal",IF(MOD(Dashboard!$N$2-$W9,3)=0,$C9,0),$F9)))))) | K9: =IF($C9="","",IF(Dashboard!$C$4="Gemiddeld per maand",$F9,IF(OR($D9="Per maand",$D9="Per week",$D9=""),$F9,IF($D9="Per jaar",IF(1=$W9,$C9,0),IF($D9="Per half jaar",IF(MOD(1-$W9,6)=0,$C9,0),IF($D9="Per kwartaal",IF(MOD(1-$W9,3)=0,$C9,0),$F9)))))) | L9: =IF($C9="","",IF(Dashboard!$C$4="Gemiddeld per maand",$F9,IF(OR($D9="Per maand",$D9="Per week",$D9=""),$F9,IF($D9="Per jaar",IF(2=$W9,$C9,0),IF($D9="Per half jaar",IF(MOD(2-$W9,6)=0,$C9,0),IF($D9="Per kwartaal",IF(MOD(2-$W9,3)=0,$C9,0),$F9)))))) | M9: =IF($C9="","",IF(Dashboard!$C$4="Gemiddeld per maand",$F9,IF(OR($D9="Per maand",$D9="Per week",$D9=""),$F9,IF($D9="Per jaar",IF(3=$W9,$C9,0),IF($D9="Per half jaar",IF(MOD(3-$W9,6)=0,$C9,0),IF($D9="Per kwartaal",IF(MOD(3-$W9,3)=0,$C9,0),$F9)))))) | N9: =IF($C9="","",IF(Dashboard!$C$4="Gemiddeld per maand",$F9,IF(OR($D9="Per maand",$D9="Per week",$D9=""),$F9,IF($D9="Per jaar",IF(4=$W9,$C9,0),IF($D9="Per half jaar",IF(MOD(4-$W9,6)=0,$C9,0),IF($D9="Per kwartaal",IF(MOD(4-$W9,3)=0,$C9,0),$F9)))))) | O9: =IF($C9="","",IF(Dashboard!$C$4="Gemiddeld per maand",$F9,IF(OR($D9="Per maand",$D9="Per week",$D9=""),$F9,IF($D9="Per jaar",IF(5=$W9,$C9,0),IF($D9="Per half jaar",IF(MOD(5-$W9,6)=0,$C9,0),IF($D9="Per kwartaal",IF(MOD(5-$W9,3)=0,$C9,0),$F9)))))) | P9: =IF($C9="","",IF(Dashboard!$C$4="Gemiddeld per maand",$F9,IF(OR($D9="Per maand",$D9="Per week",$D9=""),$F9,IF($D9="Per jaar",IF(6=$W9,$C9,0),IF($D9="Per half jaar",IF(MOD(6-$W9,6)=0,$C9,0),IF($D9="Per kwartaal",IF(MOD(6-$W9,3)=0,$C9,0),$F9)))))) | Q9: =IF($C9="","",IF(Dashboard!$C$4="Gemiddeld per maand",$F9,IF(OR($D9="Per maand",$D9="Per week",$D9=""),$F9,IF($D9="Per jaar",IF(7=$W9,$C9,0),IF($D9="Per half jaar",IF(MOD(7-$W9,6)=0,$C9,0),IF($D9="Per kwartaal",IF(MOD(7-$W9,3)=0,$C9,0),$F9)))))) | R9: =IF($C9="","",IF(Dashboard!$C$4="Gemiddeld per maand",$F9,IF(OR($D9="Per maand",$D9="Per week",$D9=""),$F9,IF($D9="Per jaar",IF(8=$W9,$C9,0),IF($D9="Per half jaar",IF(MOD(8-$W9,6)=0,$C9,0),IF($D9="Per kwartaal",IF(MOD(8-$W9,3)=0,$C9,0),$F9)))))) | S9: =IF($C9="","",IF(Dashboard!$C$4="Gemiddeld per maand",$F9,IF(OR($D9="Per maand",$D9="Per week",$D9=""),$F9,IF($D9="Per jaar",IF(9=$W9,$C9,0),IF($D9="Per half jaar",IF(MOD(9-$W9,6)=0,$C9,0),IF($D9="Per kwartaal",IF(MOD(9-$W9,3)=0,$C9,0),$F9)))))) | T9: =IF($C9="","",IF(Dashboard!$C$4="Gemiddeld per maand",$F9,IF(OR($D9="Per maand",$D9="Per week",$D9=""),$F9,IF($D9="Per jaar",IF(10=$W9,$C9,0),IF($D9="Per half jaar",IF(MOD(10-$W9,6)=0,$C9,0),IF($D9="Per kwartaal",IF(MOD(10-$W9,3)=0,$C9,0),$F9)))))) | U9: =IF($C9="","",IF(Dashboard!$C$4="Gemiddeld per maand",$F9,IF(OR($D9="Per maand",$D9="Per week",$D9=""),$F9,IF($D9="Per jaar",IF(11=$W9,$C9,0),IF($D9="Per half jaar",IF(MOD(11-$W9,6)=0,$C9,0),IF($D9="Per kwartaal",IF(MOD(11-$W9,3)=0,$C9,0),$F9)))))) | V9: =IF($C9="","",IF(Dashboard!$C$4="Gemiddeld per maand",$F9,IF(OR($D9="Per maand",$D9="Per week",$D9=""),$F9,IF($D9="Per jaar",IF(12=$W9,$C9,0),IF($D9="Per half jaar",IF(MOD(12-$W9,6)=0,$C9,0),IF($D9="Per kwartaal",IF(MOD(12-$W9,3)=0,$C9,0),$F9)))))) | W9: =IF($E9="",1,IFERROR(MATCH($E9,Lijsten!$K$6:$K$17,0),1)) -> 1
F10: =IF($C10="","",IF($D10="Per jaar",$C10/12,IF($D10="Per kwartaal",$C10/3,IF($D10="Per half jaar",$C10/6,IF($D10="Per week",$C10*52/12,$C10))))) | J10: =IF($C10="","",IF(Dashboard!$C$4="Gemiddeld per maand",$F10,IF(OR($D10="Per maand",$D10="Per week",$D10=""),$F10,IF($D10="Per jaar",IF(Dashboard!$N$2=$W10,$C10,0),IF($D10="Per half jaar",IF(MOD(Dashboard!$N$2-$W10,6)=0,$C10,0),IF($D10="Per kwartaal",IF(MOD(Dashboard!$N$2-$W10,3)=0,$C10,0),$F10)))))) | K10: =IF($C10="","",IF(Dashboard!$C$4="Gemiddeld per maand",$F10,IF(OR($D10="Per maand",$D10="Per week",$D10=""),$F10,IF($D10="Per jaar",IF(1=$W10,$C10,0),IF($D10="Per half jaar",IF(MOD(1-$W10,6)=0,$C10,0),IF($D10="Per kwartaal",IF(MOD(1-$W10,3)=0,$C10,0),$F10)))))) | L10: =IF($C10="","",IF(Dashboard!$C$4="Gemiddeld per maand",$F10,IF(OR($D10="Per maand",$D10="Per week",$D10=""),$F10,IF($D10="Per jaar",IF(2=$W10,$C10,0),IF($D10="Per half jaar",IF(MOD(2-$W10,6)=0,$C10,0),IF($D10="Per kwartaal",IF(MOD(2-$W10,3)=0,$C10,0),$F10)))))) | M10: =IF($C10="","",IF(Dashboard!$C$4="Gemiddeld per maand",$F10,IF(OR($D10="Per maand",$D10="Per week",$D10=""),$F10,IF($D10="Per jaar",IF(3=$W10,$C10,0),IF($D10="Per half jaar",IF(MOD(3-$W10,6)=0,$C10,0),IF($D10="Per kwartaal",IF(MOD(3-$W10,3)=0,$C10,0),$F10)))))) | N10: =IF($C10="","",IF(Dashboard!$C$4="Gemiddeld per maand",$F10,IF(OR($D10="Per maand",$D10="Per week",$D10=""),$F10,IF($D10="Per jaar",IF(4=$W10,$C10,0),IF($D10="Per half jaar",IF(MOD(4-$W10,6)=0,$C10,0),IF($D10="Per kwartaal",IF(MOD(4-$W10,3)=0,$C10,0),$F10)))))) | O10: =IF($C10="","",IF(Dashboard!$C$4="Gemiddeld per maand",$F10,IF(OR($D10="Per maand",$D10="Per week",$D10=""),$F10,IF($D10="Per jaar",IF(5=$W10,$C10,0),IF($D10="Per half jaar",IF(MOD(5-$W10,6)=0,$C10,0),IF($D10="Per kwartaal",IF(MOD(5-$W10,3)=0,$C10,0),$F10)))))) | P10: =IF($C10="","",IF(Dashboard!$C$4="Gemiddeld per maand",$F10,IF(OR($D10="Per maand",$D10="Per week",$D10=""),$F10,IF($D10="Per jaar",IF(6=$W10,$C10,0),IF($D10="Per half jaar",IF(MOD(6-$W10,6)=0,$C10,0),IF($D10="Per kwartaal",IF(MOD(6-$W10,3)=0,$C10,0),$F10)))))) | Q10: =IF($C10="","",IF(Dashboard!$C$4="Gemiddeld per maand",$F10,IF(OR($D10="Per maand",$D10="Per week",$D10=""),$F10,IF($D10="Per jaar",IF(7=$W10,$C10,0),IF($D10="Per half jaar",IF(MOD(7-$W10,6)=0,$C10,0),IF($D10="Per kwartaal",IF(MOD(7-$W10,3)=0,$C10,0),$F10)))))) | R10: =IF($C10="","",IF(Dashboard!$C$4="Gemiddeld per maand",$F10,IF(OR($D10="Per maand",$D10="Per week",$D10=""),$F10,IF($D10="Per jaar",IF(8=$W10,$C10,0),IF($D10="Per half jaar",IF(MOD(8-$W10,6)=0,$C10,0),IF($D10="Per kwartaal",IF(MOD(8-$W10,3)=0,$C10,0),$F10)))))) | S10: =IF($C10="","",IF(Dashboard!$C$4="Gemiddeld per maand",$F10,IF(OR($D10="Per maand",$D10="Per week",$D10=""),$F10,IF($D10="Per jaar",IF(9=$W10,$C10,0),IF($D10="Per half jaar",IF(MOD(9-$W10,6)=0,$C10,0),IF($D10="Per kwartaal",IF(MOD(9-$W10,3)=0,$C10,0),$F10)))))) | T10: =IF($C10="","",IF(Dashboard!$C$4="Gemiddeld per maand",$F10,IF(OR($D10="Per maand",$D10="Per week",$D10=""),$F10,IF($D10="Per jaar",IF(10=$W10,$C10,0),IF($D10="Per half jaar",IF(MOD(10-$W10,6)=0,$C10,0),IF($D10="Per kwartaal",IF(MOD(10-$W10,3)=0,$C10,0),$F10)))))) | U10: =IF($C10="","",IF(Dashboard!$C$4="Gemiddeld per maand",$F10,IF(OR($D10="Per maand",$D10="Per week",$D10=""),$F10,IF($D10="Per jaar",IF(11=$W10,$C10,0),IF($D10="Per half jaar",IF(MOD(11-$W10,6)=0,$C10,0),IF($D10="Per kwartaal",IF(MOD(11-$W10,3)=0,$C10,0),$F10)))))) | V10: =IF($C10="","",IF(Dashboard!$C$4="Gemiddeld per maand",$F10,IF(OR($D10="Per maand",$D10="Per week",$D10=""),$F10,IF($D10="Per jaar",IF(12=$W10,$C10,0),IF($D10="Per half jaar",IF(MOD(12-$W10,6)=0,$C10,0),IF($D10="Per kwartaal",IF(MOD(12-$W10,3)=0,$C10,0),$F10)))))) | W10: =IF($E10="",1,IFERROR(MATCH($E10,Lijsten!$K$6:$K$17,0),1)) -> 1
F11: =IF($C11="","",IF($D11="Per jaar",$C11/12,IF($D11="Per kwartaal",$C11/3,IF($D11="Per half jaar",$C11/6,IF($D11="Per week",$C11*52/12,$C11))))) | J11: =IF($C11="","",IF(Dashboard!$C$4="Gemiddeld per maand",$F11,IF(OR($D11="Per maand",$D11="Per week",$D11=""),$F11,IF($D11="Per jaar",IF(Dashboard!$N$2=$W11,$C11,0),IF($D11="Per half jaar",IF(MOD(Dashboard!$N$2-$W11,6)=0,$C11,0),IF($D11="Per kwartaal",IF(MOD(Dashboard!$N$2-$W11,3)=0,$C11,0),$F11)))))) | K11: =IF($C11="","",IF(Dashboard!$C$4="Gemiddeld per maand",$F11,IF(OR($D11="Per maand",$D11="Per week",$D11=""),$F11,IF($D11="Per jaar",IF(1=$W11,$C11,0),IF($D11="Per half jaar",IF(MOD(1-$W11,6)=0,$C11,0),IF($D11="Per kwartaal",IF(MOD(1-$W11,3)=0,$C11,0),$F11)))))) | L11: =IF($C11="","",IF(Dashboard!$C$4="Gemiddeld per maand",$F11,IF(OR($D11="Per maand",$D11="Per week",$D11=""),$F11,IF($D11="Per jaar",IF(2=$W11,$C11,0),IF($D11="Per half jaar",IF(MOD(2-$W11,6)=0,$C11,0),IF($D11="Per kwartaal",IF(MOD(2-$W11,3)=0,$C11,0),$F11)))))) | M11: =IF($C11="","",IF(Dashboard!$C$4="Gemiddeld per maand",$F11,IF(OR($D11="Per maand",$D11="Per week",$D11=""),$F11,IF($D11="Per jaar",IF(3=$W11,$C11,0),IF($D11="Per half jaar",IF(MOD(3-$W11,6)=0,$C11,0),IF($D11="Per kwartaal",IF(MOD(3-$W11,3)=0,$C11,0),$F11)))))) | N11: =IF($C11="","",IF(Dashboard!$C$4="Gemiddeld per maand",$F11,IF(OR($D11="Per maand",$D11="Per week",$D11=""),$F11,IF($D11="Per jaar",IF(4=$W11,$C11,0),IF($D11="Per half jaar",IF(MOD(4-$W11,6)=0,$C11,0),IF($D11="Per kwartaal",IF(MOD(4-$W11,3)=0,$C11,0),$F11)))))) | O11: =IF($C11="","",IF(Dashboard!$C$4="Gemiddeld per maand",$F11,IF(OR($D11="Per maand",$D11="Per week",$D11=""),$F11,IF($D11="Per jaar",IF(5=$W11,$C11,0),IF($D11="Per half jaar",IF(MOD(5-$W11,6)=0,$C11,0),IF($D11="Per kwartaal",IF(MOD(5-$W11,3)=0,$C11,0),$F11)))))) | P11: =IF($C11="","",IF(Dashboard!$C$4="Gemiddeld per maand",$F11,IF(OR($D11="Per maand",$D11="Per week",$D11=""),$F11,IF($D11="Per jaar",IF(6=$W11,$C11,0),IF($D11="Per half jaar",IF(MOD(6-$W11,6)=0,$C11,0),IF($D11="Per kwartaal",IF(MOD(6-$W11,3)=0,$C11,0),$F11)))))) | Q11: =IF($C11="","",IF(Dashboard!$C$4="Gemiddeld per maand",$F11,IF(OR($D11="Per maand",$D11="Per week",$D11=""),$F11,IF($D11="Per jaar",IF(7=$W11,$C11,0),IF($D11="Per half jaar",IF(MOD(7-$W11,6)=0,$C11,0),IF($D11="Per kwartaal",IF(MOD(7-$W11,3)=0,$C11,0),$F11)))))) | R11: =IF($C11="","",IF(Dashboard!$C$4="Gemiddeld per maand",$F11,IF(OR($D11="Per maand",$D11="Per week",$D11=""),$F11,IF($D11="Per jaar",IF(8=$W11,$C11,0),IF($D11="Per half jaar",IF(MOD(8-$W11,6)=0,$C11,0),IF($D11="Per kwartaal",IF(MOD(8-$W11,3)=0,$C11,0),$F11)))))) | S11: =IF($C11="","",IF(Dashboard!$C$4="Gemiddeld per maand",$F11,IF(OR($D11="Per maand",$D11="Per week",$D11=""),$F11,IF($D11="Per jaar",IF(9=$W11,$C11,0),IF($D11="Per half jaar",IF(MOD(9-$W11,6)=0,$C11,0),IF($D11="Per kwartaal",IF(MOD(9-$W11,3)=0,$C11,0),$F11)))))) | T11: =IF($C11="","",IF(Dashboard!$C$4="Gemiddeld per maand",$F11,IF(OR($D11="Per maand",$D11="Per week",$D11=""),$F11,IF($D11="Per jaar",IF(10=$W11,$C11,0),IF($D11="Per half jaar",IF(MOD(10-$W11,6)=0,$C11,0),IF($D11="Per kwartaal",IF(MOD(10-$W11,3)=0,$C11,0),$F11)))))) | U11: =IF($C11="","",IF(Dashboard!$C$4="Gemiddeld per maand",$F11,IF(OR($D11="Per maand",$D11="Per week",$D11=""),$F11,IF($D11="Per jaar",IF(11=$W11,$C11,0),IF($D11="Per half jaar",IF(MOD(11-$W11,6)=0,$C11,0),IF($D11="Per kwartaal",IF(MOD(11-$W11,3)=0,$C11,0),$F11)))))) | V11: =IF($C11="","",IF(Dashboard!$C$4="Gemiddeld per maand",$F11,IF(OR($D11="Per maand",$D11="Per week",$D11=""),$F11,IF($D11="Per jaar",IF(12=$W11,$C11,0),IF($D11="Per half jaar",IF(MOD(12-$W11,6)=0,$C11,0),IF($D11="Per kwartaal",IF(MOD(12-$W11,3)=0,$C11,0),$F11)))))) | W11: =IF($E11="",1,IFERROR(MATCH($E11,Lijsten!$K$6:$K$17,0),1)) -> 1
F12: =IF($C12="","",IF($D12="Per jaar",$C12/12,IF($D12="Per kwartaal",$C12/3,IF($D12="Per half jaar",$C12/6,IF($D12="Per week",$C12*52/12,$C12))))) | J12: =IF($C12="","",IF(Dashboard!$C$4="Gemiddeld per maand",$F12,IF(OR($D12="Per maand",$D12="Per week",$D12=""),$F12,IF($D12="Per jaar",IF(Dashboard!$N$2=$W12,$C12,0),IF($D12="Per half jaar",IF(MOD(Dashboard!$N$2-$W12,6)=0,$C12,0),IF($D12="Per kwartaal",IF(MOD(Dashboard!$N$2-$W12,3)=0,$C12,0),$F12)))))) | K12: =IF($C12="","",IF(Dashboard!$C$4="Gemiddeld per maand",$F12,IF(OR($D12="Per maand",$D12="Per week",$D12=""),$F12,IF($D12="Per jaar",IF(1=$W12,$C12,0),IF($D12="Per half jaar",IF(MOD(1-$W12,6)=0,$C12,0),IF($D12="Per kwartaal",IF(MOD(1-$W12,3)=0,$C12,0),$F12)))))) | L12: =IF($C12="","",IF(Dashboard!$C$4="Gemiddeld per maand",$F12,IF(OR($D12="Per maand",$D12="Per week",$D12=""),$F12,IF($D12="Per jaar",IF(2=$W12,$C12,0),IF($D12="Per half jaar",IF(MOD(2-$W12,6)=0,$C12,0),IF($D12="Per kwartaal",IF(MOD(2-$W12,3)=0,$C12,0),$F12)))))) | M12: =IF($C12="","",IF(Dashboard!$C$4="Gemiddeld per maand",$F12,IF(OR($D12="Per maand",$D12="Per week",$D12=""),$F12,IF($D12="Per jaar",IF(3=$W12,$C12,0),IF($D12="Per half jaar",IF(MOD(3-$W12,6)=0,$C12,0),IF($D12="Per kwartaal",IF(MOD(3-$W12,3)=0,$C12,0),$F12)))))) | N12: =IF($C12="","",IF(Dashboard!$C$4="Gemiddeld per maand",$F12,IF(OR($D12="Per maand",$D12="Per week",$D12=""),$F12,IF($D12="Per jaar",IF(4=$W12,$C12,0),IF($D12="Per half jaar",IF(MOD(4-$W12,6)=0,$C12,0),IF($D12="Per kwartaal",IF(MOD(4-$W12,3)=0,$C12,0),$F12)))))) | O12: =IF($C12="","",IF(Dashboard!$C$4="Gemiddeld per maand",$F12,IF(OR($D12="Per maand",$D12="Per week",$D12=""),$F12,IF($D12="Per jaar",IF(5=$W12,$C12,0),IF($D12="Per half jaar",IF(MOD(5-$W12,6)=0,$C12,0),IF($D12="Per kwartaal",IF(MOD(5-$W12,3)=0,$C12,0),$F12)))))) | P12: =IF($C12="","",IF(Dashboard!$C$4="Gemiddeld per maand",$F12,IF(OR($D12="Per maand",$D12="Per week",$D12=""),$F12,IF($D12="Per jaar",IF(6=$W12,$C12,0),IF($D12="Per half jaar",IF(MOD(6-$W12,6)=0,$C12,0),IF($D12="Per kwartaal",IF(MOD(6-$W12,3)=0,$C12,0),$F12)))))) | Q12: =IF($C12="","",IF(Dashboard!$C$4="Gemiddeld per maand",$F12,IF(OR($D12="Per maand",$D12="Per week",$D12=""),$F12,IF($D12="Per jaar",IF(7=$W12,$C12,0),IF($D12="Per half jaar",IF(MOD(7-$W12,6)=0,$C12,0),IF($D12="Per kwartaal",IF(MOD(7-$W12,3)=0,$C12,0),$F12)))))) | R12: =IF($C12="","",IF(Dashboard!$C$4="Gemiddeld per maand",$F12,IF(OR($D12="Per maand",$D12="Per week",$D12=""),$F12,IF($D12="Per jaar",IF(8=$W12,$C12,0),IF($D12="Per half jaar",IF(MOD(8-$W12,6)=0,$C12,0),IF($D12="Per kwartaal",IF(MOD(8-$W12,3)=0,$C12,0),$F12)))))) | S12: =IF($C12="","",IF(Dashboard!$C$4="Gemiddeld per maand",$F12,IF(OR($D12="Per maand",$D12="Per week",$D12=""),$F12,IF($D12="Per jaar",IF(9=$W12,$C12,0),IF($D12="Per half jaar",IF(MOD(9-$W12,6)=0,$C12,0),IF($D12="Per kwartaal",IF(MOD(9-$W12,3)=0,$C12,0),$F12)))))) | T12: =IF($C12="","",IF(Dashboard!$C$4="Gemiddeld per maand",$F12,IF(OR($D12="Per maand",$D12="Per week",$D12=""),$F12,IF($D12="Per jaar",IF(10=$W12,$C12,0),IF($D12="Per half jaar",IF(MOD(10-$W12,6)=0,$C12,0),IF($D12="Per kwartaal",IF(MOD(10-$W12,3)=0,$C12,0),$F12)))))) | U12: =IF($C12="","",IF(Dashboard!$C$4="Gemiddeld per maand",$F12,IF(OR($D12="Per maand",$D12="Per week",$D12=""),$F12,IF($D12="Per jaar",IF(11=$W12,$C12,0),IF($D12="Per half jaar",IF(MOD(11-$W12,6)=0,$C12,0),IF($D12="Per kwartaal",IF(MOD(11-$W12,3)=0,$C12,0),$F12)))))) | V12: =IF($C12="","",IF(Dashboard!$C$4="Gemiddeld per maand",$F12,IF(OR($D12="Per maand",$D12="Per week",$D12=""),$F12,IF($D12="Per jaar",IF(12=$W12,$C12,0),IF($D12="Per half jaar",IF(MOD(12-$W12,6)=0,$C12,0),IF($D12="Per kwartaal",IF(MOD(12-$W12,3)=0,$C12,0),$F12)))))) | W12: =IF($E12="",1,IFERROR(MATCH($E12,Lijsten!$K$6:$K$17,0),1)) -> 1
F13: =IF($C13="","",IF($D13="Per jaar",$C13/12,IF($D13="Per kwartaal",$C13/3,IF($D13="Per half jaar",$C13/6,IF($D13="Per week",$C13*52/12,$C13))))) | J13: =IF($C13="","",IF(Dashboard!$C$4="Gemiddeld per maand",$F13,IF(OR($D13="Per maand",$D13="Per week",$D13=""),$F13,IF($D13="Per jaar",IF(Dashboard!$N$2=$W13,$C13,0),IF($D13="Per half jaar",IF(MOD(Dashboard!$N$2-$W13,6)=0,$C13,0),IF($D13="Per kwartaal",IF(MOD(Dashboard!$N$2-$W13,3)=0,$C13,0),$F13)))))) | K13: =IF($C13="","",IF(Dashboard!$C$4="Gemiddeld per maand",$F13,IF(OR($D13="Per maand",$D13="Per week",$D13=""),$F13,IF($D13="Per jaar",IF(1=$W13,$C13,0),IF($D13="Per half jaar",IF(MOD(1-$W13,6)=0,$C13,0),IF($D13="Per kwartaal",IF(MOD(1-$W13,3)=0,$C13,0),$F13)))))) | L13: =IF($C13="","",IF(Dashboard!$C$4="Gemiddeld per maand",$F13,IF(OR($D13="Per maand",$D13="Per week",$D13=""),$F13,IF($D13="Per jaar",IF(2=$W13,$C13,0),IF($D13="Per half jaar",IF(MOD(2-$W13,6)=0,$C13,0),IF($D13="Per kwartaal",IF(MOD(2-$W13,3)=0,$C13,0),$F13)))))) | M13: =IF($C13="","",IF(Dashboard!$C$4="Gemiddeld per maand",$F13,IF(OR($D13="Per maand",$D13="Per week",$D13=""),$F13,IF($D13="Per jaar",IF(3=$W13,$C13,0),IF($D13="Per half jaar",IF(MOD(3-$W13,6)=0,$C13,0),IF($D13="Per kwartaal",IF(MOD(3-$W13,3)=0,$C13,0),$F13)))))) | N13: =IF($C13="","",IF(Dashboard!$C$4="Gemiddeld per maand",$F13,IF(OR($D13="Per maand",$D13="Per week",$D13=""),$F13,IF($D13="Per jaar",IF(4=$W13,$C13,0),IF($D13="Per half jaar",IF(MOD(4-$W13,6)=0,$C13,0),IF($D13="Per kwartaal",IF(MOD(4-$W13,3)=0,$C13,0),$F13)))))) | O13: =IF($C13="","",IF(Dashboard!$C$4="Gemiddeld per maand",$F13,IF(OR($D13="Per maand",$D13="Per week",$D13=""),$F13,IF($D13="Per jaar",IF(5=$W13,$C13,0),IF($D13="Per half jaar",IF(MOD(5-$W13,6)=0,$C13,0),IF($D13="Per kwartaal",IF(MOD(5-$W13,3)=0,$C13,0),$F13)))))) | P13: =IF($C13="","",IF(Dashboard!$C$4="Gemiddeld per maand",$F13,IF(OR($D13="Per maand",$D13="Per week",$D13=""),$F13,IF($D13="Per jaar",IF(6=$W13,$C13,0),IF($D13="Per half jaar",IF(MOD(6-$W13,6)=0,$C13,0),IF($D13="Per kwartaal",IF(MOD(6-$W13,3)=0,$C13,0),$F13)))))) | Q13: =IF($C13="","",IF(Dashboard!$C$4="Gemiddeld per maand",$F13,IF(OR($D13="Per maand",$D13="Per week",$D13=""),$F13,IF($D13="Per jaar",IF(7=$W13,$C13,0),IF($D13="Per half jaar",IF(MOD(7-$W13,6)=0,$C13,0),IF($D13="Per kwartaal",IF(MOD(7-$W13,3)=0,$C13,0),$F13)))))) | R13: =IF($C13="","",IF(Dashboard!$C$4="Gemiddeld per maand",$F13,IF(OR($D13="Per maand",$D13="Per week",$D13=""),$F13,IF($D13="Per jaar",IF(8=$W13,$C13,0),IF($D13="Per half jaar",IF(MOD(8-$W13,6)=0,$C13,0),IF($D13="Per kwartaal",IF(MOD(8-$W13,3)=0,$C13,0),$F13)))))) | S13: =IF($C13="","",IF(Dashboard!$C$4="Gemiddeld per maand",$F13,IF(OR($D13="Per maand",$D13="Per week",$D13=""),$F13,IF($D13="Per jaar",IF(9=$W13,$C13,0),IF($D13="Per half jaar",IF(MOD(9-$W13,6)=0,$C13,0),IF($D13="Per kwartaal",IF(MOD(9-$W13,3)=0,$C13,0),$F13)))))) | T13: =IF($C13="","",IF(Dashboard!$C$4="Gemiddeld per maand",$F13,IF(OR($D13="Per maand",$D13="Per week",$D13=""),$F13,IF($D13="Per jaar",IF(10=$W13,$C13,0),IF($D13="Per half jaar",IF(MOD(10-$W13,6)=0,$C13,0),IF($D13="Per kwartaal",IF(MOD(10-$W13,3)=0,$C13,0),$F13)))))) | U13: =IF($C13="","",IF(Dashboard!$C$4="Gemiddeld per maand",$F13,IF(OR($D13="Per maand",$D13="Per week",$D13=""),$F13,IF($D13="Per jaar",IF(11=$W13,$C13,0),IF($D13="Per half jaar",IF(MOD(11-$W13,6)=0,$C13,0),IF($D13="Per kwartaal",IF(MOD(11-$W13,3)=0,$C13,0),$F13)))))) | V13: =IF($C13="","",IF(Dashboard!$C$4="Gemiddeld per maand",$F13,IF(OR($D13="Per maand",$D13="Per week",$D13=""),$F13,IF($D13="Per jaar",IF(12=$W13,$C13,0),IF($D13="Per half jaar",IF(MOD(12-$W13,6)=0,$C13,0),IF($D13="Per kwartaal",IF(MOD(12-$W13,3)=0,$C13,0),$F13)))))) | W13: =IF($E13="",1,IFERROR(MATCH($E13,Lijsten!$K$6:$K$17,0),1)) -> 1
F14: =IF($C14="","",IF($D14="Per jaar",$C14/12,IF($D14="Per kwartaal",$C14/3,IF($D14="Per half jaar",$C14/6,IF($D14="Per week",$C14*52/12,$C14))))) | J14: =IF($C14="","",IF(Dashboard!$C$4="Gemiddeld per maand",$F14,IF(OR($D14="Per maand",$D14="Per week",$D14=""),$F14,IF($D14="Per jaar",IF(Dashboard!$N$2=$W14,$C14,0),IF($D14="Per half jaar",IF(MOD(Dashboard!$N$2-$W14,6)=0,$C14,0),IF($D14="Per kwartaal",IF(MOD(Dashboard!$N$2-$W14,3)=0,$C14,0),$F14)))))) | K14: =IF($C14="","",IF(Dashboard!$C$4="Gemiddeld per maand",$F14,IF(OR($D14="Per maand",$D14="Per week",$D14=""),$F14,IF($D14="Per jaar",IF(1=$W14,$C14,0),IF($D14="Per half jaar",IF(MOD(1-$W14,6)=0,$C14,0),IF($D14="Per kwartaal",IF(MOD(1-$W14,3)=0,$C14,0),$F14)))))) | L14: =IF($C14="","",IF(Dashboard!$C$4="Gemiddeld per maand",$F14,IF(OR($D14="Per maand",$D14="Per week",$D14=""),$F14,IF($D14="Per jaar",IF(2=$W14,$C14,0),IF($D14="Per half jaar",IF(MOD(2-$W14,6)=0,$C14,0),IF($D14="Per kwartaal",IF(MOD(2-$W14,3)=0,$C14,0),$F14)))))) | M14: =IF($C14="","",IF(Dashboard!$C$4="Gemiddeld per maand",$F14,IF(OR($D14="Per maand",$D14="Per week",$D14=""),$F14,IF($D14="Per jaar",IF(3=$W14,$C14,0),IF($D14="Per half jaar",IF(MOD(3-$W14,6)=0,$C14,0),IF($D14="Per kwartaal",IF(MOD(3-$W14,3)=0,$C14,0),$F14)))))) | N14: =IF($C14="","",IF(Dashboard!$C$4="Gemiddeld per maand",$F14,IF(OR($D14="Per maand",$D14="Per week",$D14=""),$F14,IF($D14="Per jaar",IF(4=$W14,$C14,0),IF($D14="Per half jaar",IF(MOD(4-$W14,6)=0,$C14,0),IF($D14="Per kwartaal",IF(MOD(4-$W14,3)=0,$C14,0),$F14)))))) | O14: =IF($C14="","",IF(Dashboard!$C$4="Gemiddeld per maand",$F14,IF(OR($D14="Per maand",$D14="Per week",$D14=""),$F14,IF($D14="Per jaar",IF(5=$W14,$C14,0),IF($D14="Per half jaar",IF(MOD(5-$W14,6)=0,$C14,0),IF($D14="Per kwartaal",IF(MOD(5-$W14,3)=0,$C14,0),$F14)))))) | P14: =IF($C14="","",IF(Dashboard!$C$4="Gemiddeld per maand",$F14,IF(OR($D14="Per maand",$D14="Per week",$D14=""),$F14,IF($D14="Per jaar",IF(6=$W14,$C14,0),IF($D14="Per half jaar",IF(MOD(6-$W14,6)=0,$C14,0),IF($D14="Per kwartaal",IF(MOD(6-$W14,3)=0,$C14,0),$F14)))))) | Q14: =IF($C14="","",IF(Dashboard!$C$4="Gemiddeld per maand",$F14,IF(OR($D14="Per maand",$D14="Per week",$D14=""),$F14,IF($D14="Per jaar",IF(7=$W14,$C14,0),IF($D14="Per half jaar",IF(MOD(7-$W14,6)=0,$C14,0),IF($D14="Per kwartaal",IF(MOD(7-$W14,3)=0,$C14,0),$F14)))))) | R14: =IF($C14="","",IF(Dashboard!$C$4="Gemiddeld per maand",$F14,IF(OR($D14="Per maand",$D14="Per week",$D14=""),$F14,IF($D14="Per jaar",IF(8=$W14,$C14,0),IF($D14="Per half jaar",IF(MOD(8-$W14,6)=0,$C14,0),IF($D14="Per kwartaal",IF(MOD(8-$W14,3)=0,$C14,0),$F14)))))) | S14: =IF($C14="","",IF(Dashboard!$C$4="Gemiddeld per maand",$F14,IF(OR($D14="Per maand",$D14="Per week",$D14=""),$F14,IF($D14="Per jaar",IF(9=$W14,$C14,0),IF($D14="Per half jaar",IF(MOD(9-$W14,6)=0,$C14,0),IF($D14="Per kwartaal",IF(MOD(9-$W14,3)=0,$C14,0),$F14)))))) | T14: =IF($C14="","",IF(Dashboard!$C$4="Gemiddeld per maand",$F14,IF(OR($D14="Per maand",$D14="Per week",$D14=""),$F14,IF($D14="Per jaar",IF(10=$W14,$C14,0),IF($D14="Per half jaar",IF(MOD(10-$W14,6)=0,$C14,0),IF($D14="Per kwartaal",IF(MOD(10-$W14,3)=0,$C14,0),$F14)))))) | U14: =IF($C14="","",IF(Dashboard!$C$4="Gemiddeld per maand",$F14,IF(OR($D14="Per maand",$D14="Per week",$D14=""),$F14,IF($D14="Per jaar",IF(11=$W14,$C14,0),IF($D14="Per half jaar",IF(MOD(11-$W14,6)=0,$C14,0),IF($D14="Per kwartaal",IF(MOD(11-$W14,3)=0,$C14,0),$F14)))))) | V14: =IF($C14="","",IF(Dashboard!$C$4="Gemiddeld per maand",$F14,IF(OR($D14="Per maand",$D14="Per week",$D14=""),$F14,IF($D14="Per jaar",IF(12=$W14,$C14,0),IF($D14="Per half jaar",IF(MOD(12-$W14,6)=0,$C14,0),IF($D14="Per kwartaal",IF(MOD(12-$W14,3)=0,$C14,0),$F14)))))) | W14: =IF($E14="",1,IFERROR(MATCH($E14,Lijsten!$K$6:$K$17,0),1)) -> 1
F15: =IF($C15="","",IF($D15="Per jaar",$C15/12,IF($D15="Per kwartaal",$C15/3,IF($D15="Per half jaar",$C15/6,IF($D15="Per week",$C15*52/12,$C15))))) | J15: =IF($C15="","",IF(Dashboard!$C$4="Gemiddeld per maand",$F15,IF(OR($D15="Per maand",$D15="Per week",$D15=""),$F15,IF($D15="Per jaar",IF(Dashboard!$N$2=$W15,$C15,0),IF($D15="Per half jaar",IF(MOD(Dashboard!$N$2-$W15,6)=0,$C15,0),IF($D15="Per kwartaal",IF(MOD(Dashboard!$N$2-$W15,3)=0,$C15,0),$F15)))))) | K15: =IF($C15="","",IF(Dashboard!$C$4="Gemiddeld per maand",$F15,IF(OR($D15="Per maand",$D15="Per week",$D15=""),$F15,IF($D15="Per jaar",IF(1=$W15,$C15,0),IF($D15="Per half jaar",IF(MOD(1-$W15,6)=0,$C15,0),IF($D15="Per kwartaal",IF(MOD(1-$W15,3)=0,$C15,0),$F15)))))) | L15: =IF($C15="","",IF(Dashboard!$C$4="Gemiddeld per maand",$F15,IF(OR($D15="Per maand",$D15="Per week",$D15=""),$F15,IF($D15="Per jaar",IF(2=$W15,$C15,0),IF($D15="Per half jaar",IF(MOD(2-$W15,6)=0,$C15,0),IF($D15="Per kwartaal",IF(MOD(2-$W15,3)=0,$C15,0),$F15)))))) | M15: =IF($C15="","",IF(Dashboard!$C$4="Gemiddeld per maand",$F15,IF(OR($D15="Per maand",$D15="Per week",$D15=""),$F15,IF($D15="Per jaar",IF(3=$W15,$C15,0),IF($D15="Per half jaar",IF(MOD(3-$W15,6)=0,$C15,0),IF($D15="Per kwartaal",IF(MOD(3-$W15,3)=0,$C15,0),$F15)))))) | N15: =IF($C15="","",IF(Dashboard!$C$4="Gemiddeld per maand",$F15,IF(OR($D15="Per maand",$D15="Per week",$D15=""),$F15,IF($D15="Per jaar",IF(4=$W15,$C15,0),IF($D15="Per half jaar",IF(MOD(4-$W15,6)=0,$C15,0),IF($D15="Per kwartaal",IF(MOD(4-$W15,3)=0,$C15,0),$F15)))))) | O15: =IF($C15="","",IF(Dashboard!$C$4="Gemiddeld per maand",$F15,IF(OR($D15="Per maand",$D15="Per week",$D15=""),$F15,IF($D15="Per jaar",IF(5=$W15,$C15,0),IF($D15="Per half jaar",IF(MOD(5-$W15,6)=0,$C15,0),IF($D15="Per kwartaal",IF(MOD(5-$W15,3)=0,$C15,0),$F15)))))) | P15: =IF($C15="","",IF(Dashboard!$C$4="Gemiddeld per maand",$F15,IF(OR($D15="Per maand",$D15="Per week",$D15=""),$F15,IF($D15="Per jaar",IF(6=$W15,$C15,0),IF($D15="Per half jaar",IF(MOD(6-$W15,6)=0,$C15,0),IF($D15="Per kwartaal",IF(MOD(6-$W15,3)=0,$C15,0),$F15)))))) | Q15: =IF($C15="","",IF(Dashboard!$C$4="Gemiddeld per maand",$F15,IF(OR($D15="Per maand",$D15="Per week",$D15=""),$F15,IF($D15="Per jaar",IF(7=$W15,$C15,0),IF($D15="Per half jaar",IF(MOD(7-$W15,6)=0,$C15,0),IF($D15="Per kwartaal",IF(MOD(7-$W15,3)=0,$C15,0),$F15)))))) | R15: =IF($C15="","",IF(Dashboard!$C$4="Gemiddeld per maand",$F15,IF(OR($D15="Per maand",$D15="Per week",$D15=""),$F15,IF($D15="Per jaar",IF(8=$W15,$C15,0),IF($D15="Per half jaar",IF(MOD(8-$W15,6)=0,$C15,0),IF($D15="Per kwartaal",IF(MOD(8-$W15,3)=0,$C15,0),$F15)))))) | S15: =IF($C15="","",IF(Dashboard!$C$4="Gemiddeld per maand",$F15,IF(OR($D15="Per maand",$D15="Per week",$D15=""),$F15,IF($D15="Per jaar",IF(9=$W15,$C15,0),IF($D15="Per half jaar",IF(MOD(9-$W15,6)=0,$C15,0),IF($D15="Per kwartaal",IF(MOD(9-$W15,3)=0,$C15,0),$F15)))))) | T15: =IF($C15="","",IF(Dashboard!$C$4="Gemiddeld per maand",$F15,IF(OR($D15="Per maand",$D15="Per week",$D15=""),$F15,IF($D15="Per jaar",IF(10=$W15,$C15,0),IF($D15="Per half jaar",IF(MOD(10-$W15,6)=0,$C15,0),IF($D15="Per kwartaal",IF(MOD(10-$W15,3)=0,$C15,0),$F15)))))) | U15: =IF($C15="","",IF(Dashboard!$C$4="Gemiddeld per maand",$F15,IF(OR($D15="Per maand",$D15="Per week",$D15=""),$F15,IF($D15="Per jaar",IF(11=$W15,$C15,0),IF($D15="Per half jaar",IF(MOD(11-$W15,6)=0,$C15,0),IF($D15="Per kwartaal",IF(MOD(11-$W15,3)=0,$C15,0),$F15)))))) | V15: =IF($C15="","",IF(Dashboard!$C$4="Gemiddeld per maand",$F15,IF(OR($D15="Per maand",$D15="Per week",$D15=""),$F15,IF($D15="Per jaar",IF(12=$W15,$C15,0),IF($D15="Per half jaar",IF(MOD(12-$W15,6)=0,$C15,0),IF($D15="Per kwartaal",IF(MOD(12-$W15,3)=0,$C15,0),$F15)))))) | W15: =IF($E15="",1,IFERROR(MATCH($E15,Lijsten!$K$6:$K$17,0),1)) -> 1
F16: =IF($C16="","",IF($D16="Per jaar",$C16/12,IF($D16="Per kwartaal",$C16/3,IF($D16="Per half jaar",$C16/6,IF($D16="Per week",$C16*52/12,$C16))))) | J16: =IF($C16="","",IF(Dashboard!$C$4="Gemiddeld per maand",$F16,IF(OR($D16="Per maand",$D16="Per week",$D16=""),$F16,IF($D16="Per jaar",IF(Dashboard!$N$2=$W16,$C16,0),IF($D16="Per half jaar",IF(MOD(Dashboard!$N$2-$W16,6)=0,$C16,0),IF($D16="Per kwartaal",IF(MOD(Dashboard!$N$2-$W16,3)=0,$C16,0),$F16)))))) | K16: =IF($C16="","",IF(Dashboard!$C$4="Gemiddeld per maand",$F16,IF(OR($D16="Per maand",$D16="Per week",$D16=""),$F16,IF($D16="Per jaar",IF(1=$W16,$C16,0),IF($D16="Per half jaar",IF(MOD(1-$W16,6)=0,$C16,0),IF($D16="Per kwartaal",IF(MOD(1-$W16,3)=0,$C16,0),$F16)))))) | L16: =IF($C16="","",IF(Dashboard!$C$4="Gemiddeld per maand",$F16,IF(OR($D16="Per maand",$D16="Per week",$D16=""),$F16,IF($D16="Per jaar",IF(2=$W16,$C16,0),IF($D16="Per half jaar",IF(MOD(2-$W16,6)=0,$C16,0),IF($D16="Per kwartaal",IF(MOD(2-$W16,3)=0,$C16,0),$F16)))))) | M16: =IF($C16="","",IF(Dashboard!$C$4="Gemiddeld per maand",$F16,IF(OR($D16="Per maand",$D16="Per week",$D16=""),$F16,IF($D16="Per jaar",IF(3=$W16,$C16,0),IF($D16="Per half jaar",IF(MOD(3-$W16,6)=0,$C16,0),IF($D16="Per kwartaal",IF(MOD(3-$W16,3)=0,$C16,0),$F16)))))) | N16: =IF($C16="","",IF(Dashboard!$C$4="Gemiddeld per maand",$F16,IF(OR($D16="Per maand",$D16="Per week",$D16=""),$F16,IF($D16="Per jaar",IF(4=$W16,$C16,0),IF($D16="Per half jaar",IF(MOD(4-$W16,6)=0,$C16,0),IF($D16="Per kwartaal",IF(MOD(4-$W16,3)=0,$C16,0),$F16)))))) | O16: =IF($C16="","",IF(Dashboard!$C$4="Gemiddeld per maand",$F16,IF(OR($D16="Per maand",$D16="Per week",$D16=""),$F16,IF($D16="Per jaar",IF(5=$W16,$C16,0),IF($D16="Per half jaar",IF(MOD(5-$W16,6)=0,$C16,0),IF($D16="Per kwartaal",IF(MOD(5-$W16,3)=0,$C16,0),$F16)))))) | P16: =IF($C16="","",IF(Dashboard!$C$4="Gemiddeld per maand",$F16,IF(OR($D16="Per maand",$D16="Per week",$D16=""),$F16,IF($D16="Per jaar",IF(6=$W16,$C16,0),IF($D16="Per half jaar",IF(MOD(6-$W16,6)=0,$C16,0),IF($D16="Per kwartaal",IF(MOD(6-$W16,3)=0,$C16,0),$F16)))))) | Q16: =IF($C16="","",IF(Dashboard!$C$4="Gemiddeld per maand",$F16,IF(OR($D16="Per maand",$D16="Per week",$D16=""),$F16,IF($D16="Per jaar",IF(7=$W16,$C16,0),IF($D16="Per half jaar",IF(MOD(7-$W16,6)=0,$C16,0),IF($D16="Per kwartaal",IF(MOD(7-$W16,3)=0,$C16,0),$F16)))))) | R16: =IF($C16="","",IF(Dashboard!$C$4="Gemiddeld per maand",$F16,IF(OR($D16="Per maand",$D16="Per week",$D16=""),$F16,IF($D16="Per jaar",IF(8=$W16,$C16,0),IF($D16="Per half jaar",IF(MOD(8-$W16,6)=0,$C16,0),IF($D16="Per kwartaal",IF(MOD(8-$W16,3)=0,$C16,0),$F16)))))) | S16: =IF($C16="","",IF(Dashboard!$C$4="Gemiddeld per maand",$F16,IF(OR($D16="Per maand",$D16="Per week",$D16=""),$F16,IF($D16="Per jaar",IF(9=$W16,$C16,0),IF($D16="Per half jaar",IF(MOD(9-$W16,6)=0,$C16,0),IF($D16="Per kwartaal",IF(MOD(9-$W16,3)=0,$C16,0),$F16)))))) | T16: =IF($C16="","",IF(Dashboard!$C$4="Gemiddeld per maand",$F16,IF(OR($D16="Per maand",$D16="Per week",$D16=""),$F16,IF($D16="Per jaar",IF(10=$W16,$C16,0),IF($D16="Per half jaar",IF(MOD(10-$W16,6)=0,$C16,0),IF($D16="Per kwartaal",IF(MOD(10-$W16,3)=0,$C16,0),$F16)))))) | U16: =IF($C16="","",IF(Dashboard!$C$4="Gemiddeld per maand",$F16,IF(OR($D16="Per maand",$D16="Per week",$D16=""),$F16,IF($D16="Per jaar",IF(11=$W16,$C16,0),IF($D16="Per half jaar",IF(MOD(11-$W16,6)=0,$C16,0),IF($D16="Per kwartaal",IF(MOD(11-$W16,3)=0,$C16,0),$F16)))))) | V16: =IF($C16="","",IF(Dashboard!$C$4="Gemiddeld per maand",$F16,IF(OR($D16="Per maand",$D16="Per week",$D16=""),$F16,IF($D16="Per jaar",IF(12=$W16,$C16,0),IF($D16="Per half jaar",IF(MOD(12-$W16,6)=0,$C16,0),IF($D16="Per kwartaal",IF(MOD(12-$W16,3)=0,$C16,0),$F16)))))) | W16: =IF($E16="",1,IFERROR(MATCH($E16,Lijsten!$K$6:$K$17,0),1)) -> 1
F17: =IF($C17="","",IF($D17="Per jaar",$C17/12,IF($D17="Per kwartaal",$C17/3,IF($D17="Per half jaar",$C17/6,IF($D17="Per week",$C17*52/12,$C17))))) | J17: =IF($C17="","",IF(Dashboard!$C$4="Gemiddeld per maand",$F17,IF(OR($D17="Per maand",$D17="Per week",$D17=""),$F17,IF($D17="Per jaar",IF(Dashboard!$N$2=$W17,$C17,0),IF($D17="Per half jaar",IF(MOD(Dashboard!$N$2-$W17,6)=0,$C17,0),IF($D17="Per kwartaal",IF(MOD(Dashboard!$N$2-$W17,3)=0,$C17,0),$F17)))))) | K17: =IF($C17="","",IF(Dashboard!$C$4="Gemiddeld per maand",$F17,IF(OR($D17="Per maand",$D17="Per week",$D17=""),$F17,IF($D17="Per jaar",IF(1=$W17,$C17,0),IF($D17="Per half jaar",IF(MOD(1-$W17,6)=0,$C17,0),IF($D17="Per kwartaal",IF(MOD(1-$W17,3)=0,$C17,0),$F17)))))) | L17: =IF($C17="","",IF(Dashboard!$C$4="Gemiddeld per maand",$F17,IF(OR($D17="Per maand",$D17="Per week",$D17=""),$F17,IF($D17="Per jaar",IF(2=$W17,$C17,0),IF($D17="Per half jaar",IF(MOD(2-$W17,6)=0,$C17,0),IF($D17="Per kwartaal",IF(MOD(2-$W17,3)=0,$C17,0),$F17)))))) | M17: =IF($C17="","",IF(Dashboard!$C$4="Gemiddeld per maand",$F17,IF(OR($D17="Per maand",$D17="Per week",$D17=""),$F17,IF($D17="Per jaar",IF(3=$W17,$C17,0),IF($D17="Per half jaar",IF(MOD(3-$W17,6)=0,$C17,0),IF($D17="Per kwartaal",IF(MOD(3-$W17,3)=0,$C17,0),$F17)))))) | N17: =IF($C17="","",IF(Dashboard!$C$4="Gemiddeld per maand",$F17,IF(OR($D17="Per maand",$D17="Per week",$D17=""),$F17,IF($D17="Per jaar",IF(4=$W17,$C17,0),IF($D17="Per half jaar",IF(MOD(4-$W17,6)=0,$C17,0),IF($D17="Per kwartaal",IF(MOD(4-$W17,3)=0,$C17,0),$F17)))))) | O17: =IF($C17="","",IF(Dashboard!$C$4="Gemiddeld per maand",$F17,IF(OR($D17="Per maand",$D17="Per week",$D17=""),$F17,IF($D17="Per jaar",IF(5=$W17,$C17,0),IF($D17="Per half jaar",IF(MOD(5-$W17,6)=0,$C17,0),IF($D17="Per kwartaal",IF(MOD(5-$W17,3)=0,$C17,0),$F17)))))) | P17: =IF($C17="","",IF(Dashboard!$C$4="Gemiddeld per maand",$F17,IF(OR($D17="Per maand",$D17="Per week",$D17=""),$F17,IF($D17="Per jaar",IF(6=$W17,$C17,0),IF($D17="Per half jaar",IF(MOD(6-$W17,6)=0,$C17,0),IF($D17="Per kwartaal",IF(MOD(6-$W17,3)=0,$C17,0),$F17)))))) | Q17: =IF($C17="","",IF(Dashboard!$C$4="Gemiddeld per maand",$F17,IF(OR($D17="Per maand",$D17="Per week",$D17=""),$F17,IF($D17="Per jaar",IF(7=$W17,$C17,0),IF($D17="Per half jaar",IF(MOD(7-$W17,6)=0,$C17,0),IF($D17="Per kwartaal",IF(MOD(7-$W17,3)=0,$C17,0),$F17)))))) | R17: =IF($C17="","",IF(Dashboard!$C$4="Gemiddeld per maand",$F17,IF(OR($D17="Per maand",$D17="Per week",$D17=""),$F17,IF($D17="Per jaar",IF(8=$W17,$C17,0),IF($D17="Per half jaar",IF(MOD(8-$W17,6)=0,$C17,0),IF($D17="Per kwartaal",IF(MOD(8-$W17,3)=0,$C17,0),$F17)))))) | S17: =IF($C17="","",IF(Dashboard!$C$4="Gemiddeld per maand",$F17,IF(OR($D17="Per maand",$D17="Per week",$D17=""),$F17,IF($D17="Per jaar",IF(9=$W17,$C17,0),IF($D17="Per half jaar",IF(MOD(9-$W17,6)=0,$C17,0),IF($D17="Per kwartaal",IF(MOD(9-$W17,3)=0,$C17,0),$F17)))))) | T17: =IF($C17="","",IF(Dashboard!$C$4="Gemiddeld per maand",$F17,IF(OR($D17="Per maand",$D17="Per week",$D17=""),$F17,IF($D17="Per jaar",IF(10=$W17,$C17,0),IF($D17="Per half jaar",IF(MOD(10-$W17,6)=0,$C17,0),IF($D17="Per kwartaal",IF(MOD(10-$W17,3)=0,$C17,0),$F17)))))) | U17: =IF($C17="","",IF(Dashboard!$C$4="Gemiddeld per maand",$F17,IF(OR($D17="Per maand",$D17="Per week",$D17=""),$F17,IF($D17="Per jaar",IF(11=$W17,$C17,0),IF($D17="Per half jaar",IF(MOD(11-$W17,6)=0,$C17,0),IF($D17="Per kwartaal",IF(MOD(11-$W17,3)=0,$C17,0),$F17)))))) | V17: =IF($C17="","",IF(Dashboard!$C$4="Gemiddeld per maand",$F17,IF(OR($D17="Per maand",$D17="Per week",$D17=""),$F17,IF($D17="Per jaar",IF(12=$W17,$C17,0),IF($D17="Per half jaar",IF(MOD(12-$W17,6)=0,$C17,0),IF($D17="Per kwartaal",IF(MOD(12-$W17,3)=0,$C17,0),$F17)))))) | W17: =IF($E17="",1,IFERROR(MATCH($E17,Lijsten!$K$6:$K$17,0),1)) -> 1
F18: =IF($C18="","",IF($D18="Per jaar",$C18/12,IF($D18="Per kwartaal",$C18/3,IF($D18="Per half jaar",$C18/6,IF($D18="Per week",$C18*52/12,$C18))))) | J18: =IF($C18="","",IF(Dashboard!$C$4="Gemiddeld per maand",$F18,IF(OR($D18="Per maand",$D18="Per week",$D18=""),$F18,IF($D18="Per jaar",IF(Dashboard!$N$2=$W18,$C18,0),IF($D18="Per half jaar",IF(MOD(Dashboard!$N$2-$W18,6)=0,$C18,0),IF($D18="Per kwartaal",IF(MOD(Dashboard!$N$2-$W18,3)=0,$C18,0),$F18)))))) | K18: =IF($C18="","",IF(Dashboard!$C$4="Gemiddeld per maand",$F18,IF(OR($D18="Per maand",$D18="Per week",$D18=""),$F18,IF($D18="Per jaar",IF(1=$W18,$C18,0),IF($D18="Per half jaar",IF(MOD(1-$W18,6)=0,$C18,0),IF($D18="Per kwartaal",IF(MOD(1-$W18,3)=0,$C18,0),$F18)))))) | L18: =IF($C18="","",IF(Dashboard!$C$4="Gemiddeld per maand",$F18,IF(OR($D18="Per maand",$D18="Per week",$D18=""),$F18,IF($D18="Per jaar",IF(2=$W18,$C18,0),IF($D18="Per half jaar",IF(MOD(2-$W18,6)=0,$C18,0),IF($D18="Per kwartaal",IF(MOD(2-$W18,3)=0,$C18,0),$F18)))))) | M18: =IF($C18="","",IF(Dashboard!$C$4="Gemiddeld per maand",$F18,IF(OR($D18="Per maand",$D18="Per week",$D18=""),$F18,IF($D18="Per jaar",IF(3=$W18,$C18,0),IF($D18="Per half jaar",IF(MOD(3-$W18,6)=0,$C18,0),IF($D18="Per kwartaal",IF(MOD(3-$W18,3)=0,$C18,0),$F18)))))) | N18: =IF($C18="","",IF(Dashboard!$C$4="Gemiddeld per maand",$F18,IF(OR($D18="Per maand",$D18="Per week",$D18=""),$F18,IF($D18="Per jaar",IF(4=$W18,$C18,0),IF($D18="Per half jaar",IF(MOD(4-$W18,6)=0,$C18,0),IF($D18="Per kwartaal",IF(MOD(4-$W18,3)=0,$C18,0),$F18)))))) | O18: =IF($C18="","",IF(Dashboard!$C$4="Gemiddeld per maand",$F18,IF(OR($D18="Per maand",$D18="Per week",$D18=""),$F18,IF($D18="Per jaar",IF(5=$W18,$C18,0),IF($D18="Per half jaar",IF(MOD(5-$W18,6)=0,$C18,0),IF($D18="Per kwartaal",IF(MOD(5-$W18,3)=0,$C18,0),$F18)))))) | P18: =IF($C18="","",IF(Dashboard!$C$4="Gemiddeld per maand",$F18,IF(OR($D18="Per maand",$D18="Per week",$D18=""),$F18,IF($D18="Per jaar",IF(6=$W18,$C18,0),IF($D18="Per half jaar",IF(MOD(6-$W18,6)=0,$C18,0),IF($D18="Per kwartaal",IF(MOD(6-$W18,3)=0,$C18,0),$F18)))))) | Q18: =IF($C18="","",IF(Dashboard!$C$4="Gemiddeld per maand",$F18,IF(OR($D18="Per maand",$D18="Per week",$D18=""),$F18,IF($D18="Per jaar",IF(7=$W18,$C18,0),IF($D18="Per half jaar",IF(MOD(7-$W18,6)=0,$C18,0),IF($D18="Per kwartaal",IF(MOD(7-$W18,3)=0,$C18,0),$F18)))))) | R18: =IF($C18="","",IF(Dashboard!$C$4="Gemiddeld per maand",$F18,IF(OR($D18="Per maand",$D18="Per week",$D18=""),$F18,IF($D18="Per jaar",IF(8=$W18,$C18,0),IF($D18="Per half jaar",IF(MOD(8-$W18,6)=0,$C18,0),IF($D18="Per kwartaal",IF(MOD(8-$W18,3)=0,$C18,0),$F18)))))) | S18: =IF($C18="","",IF(Dashboard!$C$4="Gemiddeld per maand",$F18,IF(OR($D18="Per maand",$D18="Per week",$D18=""),$F18,IF($D18="Per jaar",IF(9=$W18,$C18,0),IF($D18="Per half jaar",IF(MOD(9-$W18,6)=0,$C18,0),IF($D18="Per kwartaal",IF(MOD(9-$W18,3)=0,$C18,0),$F18)))))) | T18: =IF($C18="","",IF(Dashboard!$C$4="Gemiddeld per maand",$F18,IF(OR($D18="Per maand",$D18="Per week",$D18=""),$F18,IF($D18="Per jaar",IF(10=$W18,$C18,0),IF($D18="Per half jaar",IF(MOD(10-$W18,6)=0,$C18,0),IF($D18="Per kwartaal",IF(MOD(10-$W18,3)=0,$C18,0),$F18)))))) | U18: =IF($C18="","",IF(Dashboard!$C$4="Gemiddeld per maand",$F18,IF(OR($D18="Per maand",$D18="Per week",$D18=""),$F18,IF($D18="Per jaar",IF(11=$W18,$C18,0),IF($D18="Per half jaar",IF(MOD(11-$W18,6)=0,$C18,0),IF($D18="Per kwartaal",IF(MOD(11-$W18,3)=0,$C18,0),$F18)))))) | V18: =IF($C18="","",IF(Dashboard!$C$4="Gemiddeld per maand",$F18,IF(OR($D18="Per maand",$D18="Per week",$D18=""),$F18,IF($D18="Per jaar",IF(12=$W18,$C18,0),IF($D18="Per half jaar",IF(MOD(12-$W18,6)=0,$C18,0),IF($D18="Per kwartaal",IF(MOD(12-$W18,3)=0,$C18,0),$F18)))))) | W18: =IF($E18="",1,IFERROR(MATCH($E18,Lijsten!$K$6:$K$17,0),1)) -> 1
F19: =IF($C19="","",IF($D19="Per jaar",$C19/12,IF($D19="Per kwartaal",$C19/3,IF($D19="Per half jaar",$C19/6,IF($D19="Per week",$C19*52/12,$C19))))) | J19: =IF($C19="","",IF(Dashboard!$C$4="Gemiddeld per maand",$F19,IF(OR($D19="Per maand",$D19="Per week",$D19=""),$F19,IF($D19="Per jaar",IF(Dashboard!$N$2=$W19,$C19,0),IF($D19="Per half jaar",IF(MOD(Dashboard!$N$2-$W19,6)=0,$C19,0),IF($D19="Per kwartaal",IF(MOD(Dashboard!$N$2-$W19,3)=0,$C19,0),$F19)))))) | K19: =IF($C19="","",IF(Dashboard!$C$4="Gemiddeld per maand",$F19,IF(OR($D19="Per maand",$D19="Per week",$D19=""),$F19,IF($D19="Per jaar",IF(1=$W19,$C19,0),IF($D19="Per half jaar",IF(MOD(1-$W19,6)=0,$C19,0),IF($D19="Per kwartaal",IF(MOD(1-$W19,3)=0,$C19,0),$F19)))))) | L19: =IF($C19="","",IF(Dashboard!$C$4="Gemiddeld per maand",$F19,IF(OR($D19="Per maand",$D19="Per week",$D19=""),$F19,IF($D19="Per jaar",IF(2=$W19,$C19,0),IF($D19="Per half jaar",IF(MOD(2-$W19,6)=0,$C19,0),IF($D19="Per kwartaal",IF(MOD(2-$W19,3)=0,$C19,0),$F19)))))) | M19: =IF($C19="","",IF(Dashboard!$C$4="Gemiddeld per maand",$F19,IF(OR($D19="Per maand",$D19="Per week",$D19=""),$F19,IF($D19="Per jaar",IF(3=$W19,$C19,0),IF($D19="Per half jaar",IF(MOD(3-$W19,6)=0,$C19,0),IF($D19="Per kwartaal",IF(MOD(3-$W19,3)=0,$C19,0),$F19)))))) | N19: =IF($C19="","",IF(Dashboard!$C$4="Gemiddeld per maand",$F19,IF(OR($D19="Per maand",$D19="Per week",$D19=""),$F19,IF($D19="Per jaar",IF(4=$W19,$C19,0),IF($D19="Per half jaar",IF(MOD(4-$W19,6)=0,$C19,0),IF($D19="Per kwartaal",IF(MOD(4-$W19,3)=0,$C19,0),$F19)))))) | O19: =IF($C19="","",IF(Dashboard!$C$4="Gemiddeld per maand",$F19,IF(OR($D19="Per maand",$D19="Per week",$D19=""),$F19,IF($D19="Per jaar",IF(5=$W19,$C19,0),IF($D19="Per half jaar",IF(MOD(5-$W19,6)=0,$C19,0),IF($D19="Per kwartaal",IF(MOD(5-$W19,3)=0,$C19,0),$F19)))))) | P19: =IF($C19="","",IF(Dashboard!$C$4="Gemiddeld per maand",$F19,IF(OR($D19="Per maand",$D19="Per week",$D19=""),$F19,IF($D19="Per jaar",IF(6=$W19,$C19,0),IF($D19="Per half jaar",IF(MOD(6-$W19,6)=0,$C19,0),IF($D19="Per kwartaal",IF(MOD(6-$W19,3)=0,$C19,0),$F19)))))) | Q19: =IF($C19="","",IF(Dashboard!$C$4="Gemiddeld per maand",$F19,IF(OR($D19="Per maand",$D19="Per week",$D19=""),$F19,IF($D19="Per jaar",IF(7=$W19,$C19,0),IF($D19="Per half jaar",IF(MOD(7-$W19,6)=0,$C19,0),IF($D19="Per kwartaal",IF(MOD(7-$W19,3)=0,$C19,0),$F19)))))) | R19: =IF($C19="","",IF(Dashboard!$C$4="Gemiddeld per maand",$F19,IF(OR($D19="Per maand",$D19="Per week",$D19=""),$F19,IF($D19="Per jaar",IF(8=$W19,$C19,0),IF($D19="Per half jaar",IF(MOD(8-$W19,6)=0,$C19,0),IF($D19="Per kwartaal",IF(MOD(8-$W19,3)=0,$C19,0),$F19)))))) | S19: =IF($C19="","",IF(Dashboard!$C$4="Gemiddeld per maand",$F19,IF(OR($D19="Per maand",$D19="Per week",$D19=""),$F19,IF($D19="Per jaar",IF(9=$W19,$C19,0),IF($D19="Per half jaar",IF(MOD(9-$W19,6)=0,$C19,0),IF($D19="Per kwartaal",IF(MOD(9-$W19,3)=0,$C19,0),$F19)))))) | T19: =IF($C19="","",IF(Dashboard!$C$4="Gemiddeld per maand",$F19,IF(OR($D19="Per maand",$D19="Per week",$D19=""),$F19,IF($D19="Per jaar",IF(10=$W19,$C19,0),IF($D19="Per half jaar",IF(MOD(10-$W19,6)=0,$C19,0),IF($D19="Per kwartaal",IF(MOD(10-$W19,3)=0,$C19,0),$F19)))))) | U19: =IF($C19="","",IF(Dashboard!$C$4="Gemiddeld per maand",$F19,IF(OR($D19="Per maand",$D19="Per week",$D19=""),$F19,IF($D19="Per jaar",IF(11=$W19,$C19,0),IF($D19="Per half jaar",IF(MOD(11-$W19,6)=0,$C19,0),IF($D19="Per kwartaal",IF(MOD(11-$W19,3)=0,$C19,0),$F19)))))) | V19: =IF($C19="","",IF(Dashboard!$C$4="Gemiddeld per maand",$F19,IF(OR($D19="Per maand",$D19="Per week",$D19=""),$F19,IF($D19="Per jaar",IF(12=$W19,$C19,0),IF($D19="Per half jaar",IF(MOD(12-$W19,6)=0,$C19,0),IF($D19="Per kwartaal",IF(MOD(12-$W19,3)=0,$C19,0),$F19)))))) | W19: =IF($E19="",1,IFERROR(MATCH($E19,Lijsten!$K$6:$K$17,0),1)) -> 1
F20: =IF($C20="","",IF($D20="Per jaar",$C20/12,IF($D20="Per kwartaal",$C20/3,IF($D20="Per half jaar",$C20/6,IF($D20="Per week",$C20*52/12,$C20))))) | J20: =IF($C20="","",IF(Dashboard!$C$4="Gemiddeld per maand",$F20,IF(OR($D20="Per maand",$D20="Per week",$D20=""),$F20,IF($D20="Per jaar",IF(Dashboard!$N$2=$W20,$C20,0),IF($D20="Per half jaar",IF(MOD(Dashboard!$N$2-$W20,6)=0,$C20,0),IF($D20="Per kwartaal",IF(MOD(Dashboard!$N$2-$W20,3)=0,$C20,0),$F20)))))) | K20: =IF($C20="","",IF(Dashboard!$C$4="Gemiddeld per maand",$F20,IF(OR($D20="Per maand",$D20="Per week",$D20=""),$F20,IF($D20="Per jaar",IF(1=$W20,$C20,0),IF($D20="Per half jaar",IF(MOD(1-$W20,6)=0,$C20,0),IF($D20="Per kwartaal",IF(MOD(1-$W20,3)=0,$C20,0),$F20)))))) | L20: =IF($C20="","",IF(Dashboard!$C$4="Gemiddeld per maand",$F20,IF(OR($D20="Per maand",$D20="Per week",$D20=""),$F20,IF($D20="Per jaar",IF(2=$W20,$C20,0),IF($D20="Per half jaar",IF(MOD(2-$W20,6)=0,$C20,0),IF($D20="Per kwartaal",IF(MOD(2-$W20,3)=0,$C20,0),$F20)))))) | M20: =IF($C20="","",IF(Dashboard!$C$4="Gemiddeld per maand",$F20,IF(OR($D20="Per maand",$D20="Per week",$D20=""),$F20,IF($D20="Per jaar",IF(3=$W20,$C20,0),IF($D20="Per half jaar",IF(MOD(3-$W20,6)=0,$C20,0),IF($D20="Per kwartaal",IF(MOD(3-$W20,3)=0,$C20,0),$F20)))))) | N20: =IF($C20="","",IF(Dashboard!$C$4="Gemiddeld per maand",$F20,IF(OR($D20="Per maand",$D20="Per week",$D20=""),$F20,IF($D20="Per jaar",IF(4=$W20,$C20,0),IF($D20="Per half jaar",IF(MOD(4-$W20,6)=0,$C20,0),IF($D20="Per kwartaal",IF(MOD(4-$W20,3)=0,$C20,0),$F20)))))) | O20: =IF($C20="","",IF(Dashboard!$C$4="Gemiddeld per maand",$F20,IF(OR($D20="Per maand",$D20="Per week",$D20=""),$F20,IF($D20="Per jaar",IF(5=$W20,$C20,0),IF($D20="Per half jaar",IF(MOD(5-$W20,6)=0,$C20,0),IF($D20="Per kwartaal",IF(MOD(5-$W20,3)=0,$C20,0),$F20)))))) | P20: =IF($C20="","",IF(Dashboard!$C$4="Gemiddeld per maand",$F20,IF(OR($D20="Per maand",$D20="Per week",$D20=""),$F20,IF($D20="Per jaar",IF(6=$W20,$C20,0),IF($D20="Per half jaar",IF(MOD(6-$W20,6)=0,$C20,0),IF($D20="Per kwartaal",IF(MOD(6-$W20,3)=0,$C20,0),$F20)))))) | Q20: =IF($C20="","",IF(Dashboard!$C$4="Gemiddeld per maand",$F20,IF(OR($D20="Per maand",$D20="Per week",$D20=""),$F20,IF($D20="Per jaar",IF(7=$W20,$C20,0),IF($D20="Per half jaar",IF(MOD(7-$W20,6)=0,$C20,0),IF($D20="Per kwartaal",IF(MOD(7-$W20,3)=0,$C20,0),$F20)))))) | R20: =IF($C20="","",IF(Dashboard!$C$4="Gemiddeld per maand",$F20,IF(OR($D20="Per maand",$D20="Per week",$D20=""),$F20,IF($D20="Per jaar",IF(8=$W20,$C20,0),IF($D20="Per half jaar",IF(MOD(8-$W20,6)=0,$C20,0),IF($D20="Per kwartaal",IF(MOD(8-$W20,3)=0,$C20,0),$F20)))))) | S20: =IF($C20="","",IF(Dashboard!$C$4="Gemiddeld per maand",$F20,IF(OR($D20="Per maand",$D20="Per week",$D20=""),$F20,IF($D20="Per jaar",IF(9=$W20,$C20,0),IF($D20="Per half jaar",IF(MOD(9-$W20,6)=0,$C20,0),IF($D20="Per kwartaal",IF(MOD(9-$W20,3)=0,$C20,0),$F20)))))) | T20: =IF($C20="","",IF(Dashboard!$C$4="Gemiddeld per maand",$F20,IF(OR($D20="Per maand",$D20="Per week",$D20=""),$F20,IF($D20="Per jaar",IF(10=$W20,$C20,0),IF($D20="Per half jaar",IF(MOD(10-$W20,6)=0,$C20,0),IF($D20="Per kwartaal",IF(MOD(10-$W20,3)=0,$C20,0),$F20)))))) | U20: =IF($C20="","",IF(Dashboard!$C$4="Gemiddeld per maand",$F20,IF(OR($D20="Per maand",$D20="Per week",$D20=""),$F20,IF($D20="Per jaar",IF(11=$W20,$C20,0),IF($D20="Per half jaar",IF(MOD(11-$W20,6)=0,$C20,0),IF($D20="Per kwartaal",IF(MOD(11-$W20,3)=0,$C20,0),$F20)))))) | V20: =IF($C20="","",IF(Dashboard!$C$4="Gemiddeld per maand",$F20,IF(OR($D20="Per maand",$D20="Per week",$D20=""),$F20,IF($D20="Per jaar",IF(12=$W20,$C20,0),IF($D20="Per half jaar",IF(MOD(12-$W20,6)=0,$C20,0),IF($D20="Per kwartaal",IF(MOD(12-$W20,3)=0,$C20,0),$F20)))))) | W20: =IF($E20="",1,IFERROR(MATCH($E20,Lijsten!$K$6:$K$17,0),1)) -> 1
... F37: =IF($C37="","",IF($D37="Per jaar",$C37/12,IF($D37="Per kwartaal",$C37/3,IF($D37="Per half jaar",$C37/6,IF($D37="Per week",$C37*52/12,$C37))))) | J37: =IF($C37="","",IF(Dashboard!$C$4="Gemiddeld per maand",$F37,IF(OR($D37="Per maand",$D37="Per week",$D37=""),$F37,IF($D37="Per jaar",IF(Dashboard!$N$2=$W37,$C37,0),IF($D37="Per half jaar",IF(MOD(Dashboard!$N$2-$W37,6)=0,$C37,0),IF($D37="Per kwartaal",IF(MOD(Dashboard!$N$2-$W37,3)=0,$C37,0),$F37)))))) | K37: =IF($C37="","",IF(Dashboard!$C$4="Gemiddeld per maand",$F37,IF(OR($D37="Per maand",$D37="Per week",$D37=""),$F37,IF($D37="Per jaar",IF(1=$W37,$C37,0),IF($D37="Per half jaar",IF(MOD(1-$W37,6)=0,$C37,0),IF($D37="Per kwartaal",IF(MOD(1-$W37,3)=0,$C37,0),$F37)))))) | L37: =IF($C37="","",IF(Dashboard!$C$4="Gemiddeld per maand",$F37,IF(OR($D37="Per maand",$D37="Per week",$D37=""),$F37,IF($D37="Per jaar",IF(2=$W37,$C37,0),IF($D37="Per half jaar",IF(MOD(2-$W37,6)=0,$C37,0),IF($D37="Per kwartaal",IF(MOD(2-$W37,3)=0,$C37,0),$F37)))))) | M37: =IF($C37="","",IF(Dashboard!$C$4="Gemiddeld per maand",$F37,IF(OR($D37="Per maand",$D37="Per week",$D37=""),$F37,IF($D37="Per jaar",IF(3=$W37,$C37,0),IF($D37="Per half jaar",IF(MOD(3-$W37,6)=0,$C37,0),IF($D37="Per kwartaal",IF(MOD(3-$W37,3)=0,$C37,0),$F37)))))) | N37: =IF($C37="","",IF(Dashboard!$C$4="Gemiddeld per maand",$F37,IF(OR($D37="Per maand",$D37="Per week",$D37=""),$F37,IF($D37="Per jaar",IF(4=$W37,$C37,0),IF($D37="Per half jaar",IF(MOD(4-$W37,6)=0,$C37,0),IF($D37="Per kwartaal",IF(MOD(4-$W37,3)=0,$C37,0),$F37)))))) | O37: =IF($C37="","",IF(Dashboard!$C$4="Gemiddeld per maand",$F37,IF(OR($D37="Per maand",$D37="Per week",$D37=""),$F37,IF($D37="Per jaar",IF(5=$W37,$C37,0),IF($D37="Per half jaar",IF(MOD(5-$W37,6)=0,$C37,0),IF($D37="Per kwartaal",IF(MOD(5-$W37,3)=0,$C37,0),$F37)))))) | P37: =IF($C37="","",IF(Dashboard!$C$4="Gemiddeld per maand",$F37,IF(OR($D37="Per maand",$D37="Per week",$D37=""),$F37,IF($D37="Per jaar",IF(6=$W37,$C37,0),IF($D37="Per half jaar",IF(MOD(6-$W37,6)=0,$C37,0),IF($D37="Per kwartaal",IF(MOD(6-$W37,3)=0,$C37,0),$F37)))))) | Q37: =IF($C37="","",IF(Dashboard!$C$4="Gemiddeld per maand",$F37,IF(OR($D37="Per maand",$D37="Per week",$D37=""),$F37,IF($D37="Per jaar",IF(7=$W37,$C37,0),IF($D37="Per half jaar",IF(MOD(7-$W37,6)=0,$C37,0),IF($D37="Per kwartaal",IF(MOD(7-$W37,3)=0,$C37,0),$F37)))))) | R37: =IF($C37="","",IF(Dashboard!$C$4="Gemiddeld per maand",$F37,IF(OR($D37="Per maand",$D37="Per week",$D37=""),$F37,IF($D37="Per jaar",IF(8=$W37,$C37,0),IF($D37="Per half jaar",IF(MOD(8-$W37,6)=0,$C37,0),IF($D37="Per kwartaal",IF(MOD(8-$W37,3)=0,$C37,0),$F37)))))) | S37: =IF($C37="","",IF(Dashboard!$C$4="Gemiddeld per maand",$F37,IF(OR($D37="Per maand",$D37="Per week",$D37=""),$F37,IF($D37="Per jaar",IF(9=$W37,$C37,0),IF($D37="Per half jaar",IF(MOD(9-$W37,6)=0,$C37,0),IF($D37="Per kwartaal",IF(MOD(9-$W37,3)=0,$C37,0),$F37)))))) | T37: =IF($C37="","",IF(Dashboard!$C$4="Gemiddeld per maand",$F37,IF(OR($D37="Per maand",$D37="Per week",$D37=""),$F37,IF($D37="Per jaar",IF(10=$W37,$C37,0),IF($D37="Per half jaar",IF(MOD(10-$W37,6)=0,$C37,0),IF($D37="Per kwartaal",IF(MOD(10-$W37,3)=0,$C37,0),$F37)))))) | U37: =IF($C37="","",IF(Dashboard!$C$4="Gemiddeld per maand",$F37,IF(OR($D37="Per maand",$D37="Per week",$D37=""),$F37,IF($D37="Per jaar",IF(11=$W37,$C37,0),IF($D37="Per half jaar",IF(MOD(11-$W37,6)=0,$C37,0),IF($D37="Per kwartaal",IF(MOD(11-$W37,3)=0,$C37,0),$F37)))))) | V37: =IF($C37="","",IF(Dashboard!$C$4="Gemiddeld per maand",$F37,IF(OR($D37="Per maand",$D37="Per week",$D37=""),$F37,IF($D37="Per jaar",IF(12=$W37,$C37,0),IF($D37="Per half jaar",IF(MOD(12-$W37,6)=0,$C37,0),IF($D37="Per kwartaal",IF(MOD(12-$W37,3)=0,$C37,0),$F37)))))) | W37: =IF($E37="",1,IFERROR(MATCH($E37,Lijsten!$K$6:$K$17,0),1)) -> 1

Sheet Schulden
A1: SCHULDEN | E1: ⌂ Menu | F1: Dashboard ▸
A2: Openstaande schulden met hun maandtermijn. De termijnen tellen automatisch mee als vaste last — zet ze dus NIET ook bij Vaste lasten.
A3: Vul saldo, rente en maandtermijn in; looptijd en einddatum rekent het bestand zelf uit.
A5: Totale schuld | C5: =SUMIFS($C$8:$C$37,$G$8:$G$37,"Ja") -> 15000 | D5: Maandlast | E5: =SUMIFS($E$8:$E$37,$G$8:$G$37,"Ja") -> 190 | F5: Schuldenvrij rond | H5: =IFERROR(IF(MAX($I$8:$I$37)=0,"",MAX($I$8:$I$37)),"") -> 48907
A7: Schuldeiser | B7: Waarvoor | C7: Openstaand saldo | D7: Rente % p/j | E7: Maandtermijn | F7: Categorie | G7: Actief | H7: Maanden te gaan | I7: Verwacht klaar | J7: Prioriteit | K7: Notitie
A8: DUO | B8: Studieschuld | C8: 15000 | D8: 2.5 | E8: 190 | F8: Schulden & aflossingen | G8: Ja | H8: =IF(OR($C8="",$E8="",$E8=0),"",IFERROR(ROUNDUP(NPER(IF($D8="",0,$D8/100/12),-$E8,$C8),0),"termijn te laag")) -> 87 | I8: =IF(OR($H8="",ISTEXT($H8)),"",EDATE(TODAY(),$H8)) -> 48907 | J8: =IF($C8="","",RANK(IF($D8="",0,$D8),$D$8:$D$37,0)) -> 1 | K8: VOORBEELDREGEL — vervang door je eigen schuld
H9: =IF(OR($C9="",$E9="",$E9=0),"",IFERROR(ROUNDUP(NPER(IF($D9="",0,$D9/100/12),-$E9,$C9),0),"termijn te laag")) | I9: =IF(OR($H9="",ISTEXT($H9)),"",EDATE(TODAY(),$H9)) | J9: =IF($C9="","",RANK(IF($D9="",0,$D9),$D$8:$D$37,0))
H10: =IF(OR($C10="",$E10="",$E10=0),"",IFERROR(ROUNDUP(NPER(IF($D10="",0,$D10/100/12),-$E10,$C10),0),"termijn te laag")) | I10: =IF(OR($H10="",ISTEXT($H10)),"",EDATE(TODAY(),$H10)) | J10: =IF($C10="","",RANK(IF($D10="",0,$D10),$D$8:$D$37,0))
H11: =IF(OR($C11="",$E11="",$E11=0),"",IFERROR(ROUNDUP(NPER(IF($D11="",0,$D11/100/12),-$E11,$C11),0),"termijn te laag")) | I11: =IF(OR($H11="",ISTEXT($H11)),"",EDATE(TODAY(),$H11)) | J11: =IF($C11="","",RANK(IF($D11="",0,$D11),$D$8:$D$37,0))
H12: =IF(OR($C12="",$E12="",$E12=0),"",IFERROR(ROUNDUP(NPER(IF($D12="",0,$D12/100/12),-$E12,$C12),0),"termijn te laag")) | I12: =IF(OR($H12="",ISTEXT($H12)),"",EDATE(TODAY(),$H12)) | J12: =IF($C12="","",RANK(IF($D12="",0,$D12),$D$8:$D$37,0))
H13: =IF(OR($C13="",$E13="",$E13=0),"",IFERROR(ROUNDUP(NPER(IF($D13="",0,$D13/100/12),-$E13,$C13),0),"termijn te laag")) | I13: =IF(OR($H13="",ISTEXT($H13)),"",EDATE(TODAY(),$H13)) | J13: =IF($C13="","",RANK(IF($D13="",0,$D13),$D$8:$D$37,0))
H14: =IF(OR($C14="",$E14="",$E14=0),"",IFERROR(ROUNDUP(NPER(IF($D14="",0,$D14/100/12),-$E14,$C14),0),"termijn te laag")) | I14: =IF(OR($H14="",ISTEXT($H14)),"",EDATE(TODAY(),$H14)) | J14: =IF($C14="","",RANK(IF($D14="",0,$D14),$D$8:$D$37,0))
H15: =IF(OR($C15="",$E15="",$E15=0),"",IFERROR(ROUNDUP(NPER(IF($D15="",0,$D15/100/12),-$E15,$C15),0),"termijn te laag")) | I15: =IF(OR($H15="",ISTEXT($H15)),"",EDATE(TODAY(),$H15)) | J15: =IF($C15="","",RANK(IF($D15="",0,$D15),$D$8:$D$37,0))
H16: =IF(OR($C16="",$E16="",$E16=0),"",IFERROR(ROUNDUP(NPER(IF($D16="",0,$D16/100/12),-$E16,$C16),0),"termijn te laag")) | I16: =IF(OR($H16="",ISTEXT($H16)),"",EDATE(TODAY(),$H16)) | J16: =IF($C16="","",RANK(IF($D16="",0,$D16),$D$8:$D$37,0))
H17: =IF(OR($C17="",$E17="",$E17=0),"",IFERROR(ROUNDUP(NPER(IF($D17="",0,$D17/100/12),-$E17,$C17),0),"termijn te laag")) | I17: =IF(OR($H17="",ISTEXT($H17)),"",EDATE(TODAY(),$H17)) | J17: =IF($C17="","",RANK(IF($D17="",0,$D17),$D$8:$D$37,0))
H18: =IF(OR($C18="",$E18="",$E18=0),"",IFERROR(ROUNDUP(NPER(IF($D18="",0,$D18/100/12),-$E18,$C18),0),"termijn te laag")) | I18: =IF(OR($H18="",ISTEXT($H18)),"",EDATE(TODAY(),$H18)) | J18: =IF($C18="","",RANK(IF($D18="",0,$D18),$D$8:$D$37,0))
H19: =IF(OR($C19="",$E19="",$E19=0),"",IFERROR(ROUNDUP(NPER(IF($D19="",0,$D19/100/12),-$E19,$C19),0),"termijn te laag")) | I19: =IF(OR($H19="",ISTEXT($H19)),"",EDATE(TODAY(),$H19)) | J19: =IF($C19="","",RANK(IF($D19="",0,$D19),$D$8:$D$37,0))
H20: =IF(OR($C20="",$E20="",$E20=0),"",IFERROR(ROUNDUP(NPER(IF($D20="",0,$D20/100/12),-$E20,$C20),0),"termijn te laag")) | I20: =IF(OR($H20="",ISTEXT($H20)),"",EDATE(TODAY(),$H20)) | J20: =IF($C20="","",RANK(IF($D20="",0,$D20),$D$8:$D$37,0))
... H37: =IF(OR($C37="",$E37="",$E37=0),"",IFERROR(ROUNDUP(NPER(IF($D37="",0,$D37/100/12),-$E37,$C37),0),"termijn te laag")) | I37: =IF(OR($H37="",ISTEXT($H37)),"",EDATE(TODAY(),$H37)) | J37: =IF($C37="","",RANK(IF($D37="",0,$D37),$D$8:$D$37,0))
A39: Prioriteit 1 = hoogste rente. Los die eerst extra af; dat kost je het minste geld (lawinemethode).
A40: Wil je liever snel resultaat zien? Los dan de kleinste schuld eerst af (sneeuwbalmethode).

Sheet Transacties
A1: TRANSACTIES | E1: ⌂ Menu | F1: Dashboard ▸
A2: Alleen wat wisselt per maand: boodschappen, tanken, uit eten, losse inkomsten. Vaste posten staan al op hun eigen tabblad.
A3: Het type (uitgave of inkomst) volgt automatisch uit de categorie die je kiest.
A7: Datum | B7: Categorie | C7: Omschrijving | D7: Bedrag | E7: Type (auto) | F7: Betaalmethode | G7: Notitie | H7: Maandsleutel
A8: 46237 | B8: Boodschappen & eten | C8: Supermarkt weekboodschappen | D8: 62.3 | E8: =IF($B8="","",IF(COUNTIF(Lijsten!$A$6:$A$12,$B8)>0,"Inkomst","Uitgave")) -> Uitgave | F8: Bankpas | G8: VOORBEELDREGEL — overschrijf of verwijder | H8: =IF($A8="","",YEAR($A8)*100+MONTH($A8)) -> 202608
E9: =IF($B9="","",IF(COUNTIF(Lijsten!$A$6:$A$12,$B9)>0,"Inkomst","Uitgave")) | H9: =IF($A9="","",YEAR($A9)*100+MONTH($A9))
E10: =IF($B10="","",IF(COUNTIF(Lijsten!$A$6:$A$12,$B10)>0,"Inkomst","Uitgave")) | H10: =IF($A10="","",YEAR($A10)*100+MONTH($A10))
E11: =IF($B11="","",IF(COUNTIF(Lijsten!$A$6:$A$12,$B11)>0,"Inkomst","Uitgave")) | H11: =IF($A11="","",YEAR($A11)*100+MONTH($A11))
E12: =IF($B12="","",IF(COUNTIF(Lijsten!$A$6:$A$12,$B12)>0,"Inkomst","Uitgave")) | H12: =IF($A12="","",YEAR($A12)*100+MONTH($A12))
E13: =IF($B13="","",IF(COUNTIF(Lijsten!$A$6:$A$12,$B13)>0,"Inkomst","Uitgave")) | H13: =IF($A13="","",YEAR($A13)*100+MONTH($A13))
E14: =IF($B14="","",IF(COUNTIF(Lijsten!$A$6:$A$12,$B14)>0,"Inkomst","Uitgave")) | H14: =IF($A14="","",YEAR($A14)*100+MONTH($A14))
E15: =IF($B15="","",IF(COUNTIF(Lijsten!$A$6:$A$12,$B15)>0,"Inkomst","Uitgave")) | H15: =IF($A15="","",YEAR($A15)*100+MONTH($A15))
E16: =IF($B16="","",IF(COUNTIF(Lijsten!$A$6:$A$12,$B16)>0,"Inkomst","Uitgave")) | H16: =IF($A16="","",YEAR($A16)*100+MONTH($A16))
E17: =IF($B17="","",IF(COUNTIF(Lijsten!$A$6:$A$12,$B17)>0,"Inkomst","Uitgave")) | H17: =IF($A17="","",YEAR($A17)*100+MONTH($A17))
E18: =IF($B18="","",IF(COUNTIF(Lijsten!$A$6:$A$12,$B18)>0,"Inkomst","Uitgave")) | H18: =IF($A18="","",YEAR($A18)*100+MONTH($A18))
E19: =IF($B19="","",IF(COUNTIF(Lijsten!$A$6:$A$12,$B19)>0,"Inkomst","Uitgave")) | H19: =IF($A19="","",YEAR($A19)*100+MONTH($A19))
E20: =IF($B20="","",IF(COUNTIF(Lijsten!$A$6:$A$12,$B20)>0,"Inkomst","Uitgave")) | H20: =IF($A20="","",YEAR($A20)*100+MONTH($A20))
... E507: =IF($B507="","",IF(COUNTIF(Lijsten!$A$6:$A$12,$B507)>0,"Inkomst","Uitgave")) | H507: =IF($A507="","",YEAR($A507)*100+MONTH($A507))

Sheet Jaaroverzicht
B2: JAAROVERZICHT | D2: ⌂ Menu | E2: Dashboard ▸
B3: Volgt het jaar dat je op het Dashboard kiest.
B5: Jaar | C5: =Dashboard!$E$5 -> 2026
B7: Maand | C7: Inkomsten | D7: Uitgaven | E7: Saldo | F7: Cumulatief saldo
B8: =Lijsten!$K$6 -> januari | C8: =SUMIFS('Vaste inkomsten'!$K$8:$K$37,'Vaste inkomsten'!$H$8:$H$37,"Ja")+SUMIFS(Transacties!$D$8:$D$507,Transacties!$H$8:$H$507,$G8,Transacties!$E$8:$E$507,"Inkomst") -> 2800 | D8: =SUMIFS('Vaste lasten'!$K$8:$K$207,'Vaste lasten'!$H$8:$H$207,"Ja")+SUMIFS(Schulden!$E$8:$E$37,Schulden!$G$8:$G$37,"Ja")+SUMIFS(Transacties!$D$8:$D$507,Transacties!$H$8:$H$507,$G8)-SUMIFS(Transacties!$D$8:$D$507,Transacties!$H$8:$H$507,$G8,Transacties!$E$8:$E$507,"Inkomst") -> 1140 | E8: =$C8-$D8 -> 1660 | F8: =$E8 -> 1660 | G8: =$C$5*100+1 -> 202601
B9: =Lijsten!$K$7 -> februari | C9: =SUMIFS('Vaste inkomsten'!$L$8:$L$37,'Vaste inkomsten'!$H$8:$H$37,"Ja")+SUMIFS(Transacties!$D$8:$D$507,Transacties!$H$8:$H$507,$G9,Transacties!$E$8:$E$507,"Inkomst") -> 2800 | D9: =SUMIFS('Vaste lasten'!$L$8:$L$207,'Vaste lasten'!$H$8:$H$207,"Ja")+SUMIFS(Schulden!$E$8:$E$37,Schulden!$G$8:$G$37,"Ja")+SUMIFS(Transacties!$D$8:$D$507,Transacties!$H$8:$H$507,$G9)-SUMIFS(Transacties!$D$8:$D$507,Transacties!$H$8:$H$507,$G9,Transacties!$E$8:$E$507,"Inkomst") -> 1140 | E9: =$C9-$D9 -> 1660 | F9: =$F8+$E9 -> 3320 | G9: =$C$5*100+2 -> 202602
B10: =Lijsten!$K$8 -> maart | C10: =SUMIFS('Vaste inkomsten'!$M$8:$M$37,'Vaste inkomsten'!$H$8:$H$37,"Ja")+SUMIFS(Transacties!$D$8:$D$507,Transacties!$H$8:$H$507,$G10,Transacties!$E$8:$E$507,"Inkomst") -> 2800 | D10: =SUMIFS('Vaste lasten'!$M$8:$M$207,'Vaste lasten'!$H$8:$H$207,"Ja")+SUMIFS(Schulden!$E$8:$E$37,Schulden!$G$8:$G$37,"Ja")+SUMIFS(Transacties!$D$8:$D$507,Transacties!$H$8:$H$507,$G10)-SUMIFS(Transacties!$D$8:$D$507,Transacties!$H$8:$H$507,$G10,Transacties!$E$8:$E$507,"Inkomst") -> 1140 | E10: =$C10-$D10 -> 1660 | F10: =$F9+$E10 -> 4980 | G10: =$C$5*100+3 -> 202603
B11: =Lijsten!$K$9 -> april | C11: =SUMIFS('Vaste inkomsten'!$N$8:$N$37,'Vaste inkomsten'!$H$8:$H$37,"Ja")+SUMIFS(Transacties!$D$8:$D$507,Transacties!$H$8:$H$507,$G11,Transacties!$E$8:$E$507,"Inkomst") -> 2800 | D11: =SUMIFS('Vaste lasten'!$N$8:$N$207,'Vaste lasten'!$H$8:$H$207,"Ja")+SUMIFS(Schulden!$E$8:$E$37,Schulden!$G$8:$G$37,"Ja")+SUMIFS(Transacties!$D$8:$D$507,Transacties!$H$8:$H$507,$G11)-SUMIFS(Transacties!$D$8:$D$507,Transacties!$H$8:$H$507,$G11,Transacties!$E$8:$E$507,"Inkomst") -> 1140 | E11: =$C11-$D11 -> 1660 | F11: =$F10+$E11 -> 6640 | G11: =$C$5*100+4 -> 202604
B12: =Lijsten!$K$10 -> mei | C12: =SUMIFS('Vaste inkomsten'!$O$8:$O$37,'Vaste inkomsten'!$H$8:$H$37,"Ja")+SUMIFS(Transacties!$D$8:$D$507,Transacties!$H$8:$H$507,$G12,Transacties!$E$8:$E$507,"Inkomst") -> 2800 | D12: =SUMIFS('Vaste lasten'!$O$8:$O$207,'Vaste lasten'!$H$8:$H$207,"Ja")+SUMIFS(Schulden!$E$8:$E$37,Schulden!$G$8:$G$37,"Ja")+SUMIFS(Transacties!$D$8:$D$507,Transacties!$H$8:$H$507,$G12)-SUMIFS(Transacties!$D$8:$D$507,Transacties!$H$8:$H$507,$G12,Transacties!$E$8:$E$507,"Inkomst") -> 1140 | E12: =$C12-$D12 -> 1660 | F12: =$F11+$E12 -> 8300 | G12: =$C$5*100+5 -> 202605
B13: =Lijsten!$K$11 -> juni | C13: =SUMIFS('Vaste inkomsten'!$P$8:$P$37,'Vaste inkomsten'!$H$8:$H$37,"Ja")+SUMIFS(Transacties!$D$8:$D$507,Transacties!$H$8:$H$507,$G13,Transacties!$E$8:$E$507,"Inkomst") -> 2800 | D13: =SUMIFS('Vaste lasten'!$P$8:$P$207,'Vaste lasten'!$H$8:$H$207,"Ja")+SUMIFS(Schulden!$E$8:$E$37,Schulden!$G$8:$G$37,"Ja")+SUMIFS(Transacties!$D$8:$D$507,Transacties!$H$8:$H$507,$G13)-SUMIFS(Transacties!$D$8:$D$507,Transacties!$H$8:$H$507,$G13,Transacties!$E$8:$E$507,"Inkomst") -> 1140 | E13: =$C13-$D13 -> 1660 | F13: =$F12+$E13 -> 9960 | G13: =$C$5*100+6 -> 202606
B14: =Lijsten!$K$12 -> juli | C14: =SUMIFS('Vaste inkomsten'!$Q$8:$Q$37,'Vaste inkomsten'!$H$8:$H$37,"Ja")+SUMIFS(Transacties!$D$8:$D$507,Transacties!$H$8:$H$507,$G14,Transacties!$E$8:$E$507,"Inkomst") -> 2800 | D14: =SUMIFS('Vaste lasten'!$Q$8:$Q$207,'Vaste lasten'!$H$8:$H$207,"Ja")+SUMIFS(Schulden!$E$8:$E$37,Schulden!$G$8:$G$37,"Ja")+SUMIFS(Transacties!$D$8:$D$507,Transacties!$H$8:$H$507,$G14)-SUMIFS(Transacties!$D$8:$D$507,Transacties!$H$8:$H$507,$G14,Transacties!$E$8:$E$507,"Inkomst") -> 1140 | E14: =$C14-$D14 -> 1660 | F14: =$F13+$E14 -> 11620 | G14: =$C$5*100+7 -> 202607
B15: =Lijsten!$K$13 -> augustus | C15: =SUMIFS('Vaste inkomsten'!$R$8:$R$37,'Vaste inkomsten'!$H$8:$H$37,"Ja")+SUMIFS(Transacties!$D$8:$D$507,Transacties!$H$8:$H$507,$G15,Transacties!$E$8:$E$507,"Inkomst") -> 2800 | D15: =SUMIFS('Vaste lasten'!$R$8:$R$207,'Vaste lasten'!$H$8:$H$207,"Ja")+SUMIFS(Schulden!$E$8:$E$37,Schulden!$G$8:$G$37,"Ja")+SUMIFS(Transacties!$D$8:$D$507,Transacties!$H$8:$H$507,$G15)-SUMIFS(Transacties!$D$8:$D$507,Transacties!$H$8:$H$507,$G15,Transacties!$E$8:$E$507,"Inkomst") -> 1202.3 | E15: =$C15-$D15 -> 1597.7 | F15: =$F14+$E15 -> 13217.7 | G15: =$C$5*100+8 -> 202608
B16: =Lijsten!$K$14 -> september | C16: =SUMIFS('Vaste inkomsten'!$S$8:$S$37,'Vaste inkomsten'!$H$8:$H$37,"Ja")+SUMIFS(Transacties!$D$8:$D$507,Transacties!$H$8:$H$507,$G16,Transacties!$E$8:$E$507,"Inkomst") -> 2800 | D16: =SUMIFS('Vaste lasten'!$S$8:$S$207,'Vaste lasten'!$H$8:$H$207,"Ja")+SUMIFS(Schulden!$E$8:$E$37,Schulden!$G$8:$G$37,"Ja")+SUMIFS(Transacties!$D$8:$D$507,Transacties!$H$8:$H$507,$G16)-SUMIFS(Transacties!$D$8:$D$507,Transacties!$H$8:$H$507,$G16,Transacties!$E$8:$E$507,"Inkomst") -> 1140 | E16: =$C16-$D16 -> 1660 | F16: =$F15+$E16 -> 14877.7 | G16: =$C$5*100+9 -> 202609
B17: =Lijsten!$K$15 -> oktober | C17: =SUMIFS('Vaste inkomsten'!$T$8:$T$37,'Vaste inkomsten'!$H$8:$H$37,"Ja")+SUMIFS(Transacties!$D$8:$D$507,Transacties!$H$8:$H$507,$G17,Transacties!$E$8:$E$507,"Inkomst") -> 2800 | D17: =SUMIFS('Vaste lasten'!$T$8:$T$207,'Vaste lasten'!$H$8:$H$207,"Ja")+SUMIFS(Schulden!$E$8:$E$37,Schulden!$G$8:$G$37,"Ja")+SUMIFS(Transacties!$D$8:$D$507,Transacties!$H$8:$H$507,$G17)-SUMIFS(Transacties!$D$8:$D$507,Transacties!$H$8:$H$507,$G17,Transacties!$E$8:$E$507,"Inkomst") -> 1140 | E17: =$C17-$D17 -> 1660 | F17: =$F16+$E17 -> 16537.7 | G17: =$C$5*100+10 -> 202610
B18: =Lijsten!$K$16 -> november | C18: =SUMIFS('Vaste inkomsten'!$U$8:$U$37,'Vaste inkomsten'!$H$8:$H$37,"Ja")+SUMIFS(Transacties!$D$8:$D$507,Transacties!$H$8:$H$507,$G18,Transacties!$E$8:$E$507,"Inkomst") -> 2800 | D18: =SUMIFS('Vaste lasten'!$U$8:$U$207,'Vaste lasten'!$H$8:$H$207,"Ja")+SUMIFS(Schulden!$E$8:$E$37,Schulden!$G$8:$G$37,"Ja")+SUMIFS(Transacties!$D$8:$D$507,Transacties!$H$8:$H$507,$G18)-SUMIFS(Transacties!$D$8:$D$507,Transacties!$H$8:$H$507,$G18,Transacties!$E$8:$E$507,"Inkomst") -> 1140 | E18: =$C18-$D18 -> 1660 | F18: =$F17+$E18 -> 18197.7 | G18: =$C$5*100+11 -> 202611
B19: =Lijsten!$K$17 -> december | C19: =SUMIFS('Vaste inkomsten'!$V$8:$V$37,'Vaste inkomsten'!$H$8:$H$37,"Ja")+SUMIFS(Transacties!$D$8:$D$507,Transacties!$H$8:$H$507,$G19,Transacties!$E$8:$E$507,"Inkomst") -> 2800 | D19: =SUMIFS('Vaste lasten'!$V$8:$V$207,'Vaste lasten'!$H$8:$H$207,"Ja")+SUMIFS(Schulden!$E$8:$E$37,Schulden!$G$8:$G$37,"Ja")+SUMIFS(Transacties!$D$8:$D$507,Transacties!$H$8:$H$507,$G19)-SUMIFS(Transacties!$D$8:$D$507,Transacties!$H$8:$H$507,$G19,Transacties!$E$8:$E$507,"Inkomst") -> 1140 | E19: =$C19-$D19 -> 1660 | F19: =$F18+$E19 -> 19857.7 | G19: =$C$5*100+12 -> 202612
B20: Totaal jaar | C20: =SUM(C8:C19) -> 33600 | D20: =SUM(D8:D19) -> 13742.3 | E20: =SUM(E8:E19) -> 19857.7
B22: Staat het Dashboard op 'Werkelijke betaalmaand'? Dan zie je hier de echte pieken van jaar- en kwartaalrekeningen.

Sheet Lijsten
A1: LIJSTEN | C1: ⌂ Menu | E1: Dashboard ▸
A2: Alleen keuzelijsten — geen bedragen. Wat je hier toevoegt verschijnt in de dropdowns op de andere tabbladen.
A3: Vul lege regels aan met je eigen categorieën, bedrijven of schuldeisers.
A5: Categorie — inkomsten | C5: Categorie — uitgaven | E5: Bedrijven / leveranciers | G5: Schuldeisers | I5: Betaalmethode | K5: Maanden | M5: Frequentie | O5: Alle categorieën (auto)
A6: Salaris | C6: Wonen | E6: Woningcorporatie | G6: DUO | I6: Bankpas | K6: januari | M6: Per maand | O6: =IF($A6="","",$A6) -> Salaris
A7: Vakantiegeld | C7: Nutsvoorzieningen | E7: Energieleverancier | G7: Bank | I7: Contant | K7: februari | M7: Per week | O7: =IF($A7="","",$A7) -> Vakantiegeld
A8: Bonus / extra werk | C8: Telefoon & internet | E8: Waterbedrijf | G8: Creditcardmaatschappij | I8: Creditcard | K8: maart | M8: Per kwartaal | O8: =IF($A8="","",$A8) -> Bonus / extra werk
A9: Toeslagen | C9: Technologie & software | E9: Internetprovider | I9: Automatische incasso | K9: april | M9: Per half jaar | O9: =IF($A9="","",$A9) -> Toeslagen
A10: Overig inkomen | C10: Verzekeringen | E10: Telefoonprovider | I10: Overboeking | K10: mei | M10: Per jaar | O10: =IF($A10="","",$A10) -> Overig inkomen
C11: Auto & vervoer | E11: Zorgverzekeraar | I11: Tikkie | K11: juni | O11: =IF($A11="","",$A11)
C12: Belastingen | E12: Autoverzekeraar | I12: Online | K12: juli | O12: =IF($A12="","",$A12)
C13: Boodschappen & eten | E13: Belastingdienst | I13: Anders | K13: augustus | O13: =IF($C6="","",$C6) -> Wonen
C14: Uit eten & horeca | E14: Gemeente | K14: september | O14: =IF($C7="","",$C7) -> Nutsvoorzieningen
C15: Gezondheid & zorg | E15: Waterschap | K15: oktober | O15: =IF($C8="","",$C8) -> Telefoon & internet
C16: Persoonlijke verzorging | E16: Streamingdienst | K16: november | O16: =IF($C9="","",$C9) -> Technologie & software
C17: Kleding | E17: Sportschool | K17: december | O17: =IF($C10="","",$C10) -> Verzekeringen
C18: Huishouden | O18: =IF($C11="","",$C11) -> Auto & vervoer
C19: Abonnementen & media | O19: =IF($C12="","",$C12) -> Belastingen
C20: Sport & fitness | O20: =IF($C13="","",$C13) -> Boodschappen & eten
C21: Vrije tijd & uitjes | O21: =IF($C14="","",$C14) -> Uit eten & horeca
C22: Vakantie & reizen | O22: =IF($C15="","",$C15) -> Gezondheid & zorg
C23: Studie & ontwikkeling | O23: =IF($C16="","",$C16) -> Persoonlijke verzorging
C24: Kinderen & alimentatie | O24: =IF($C17="","",$C17) -> Kleding
C25: Giften & goede doelen | O25: =IF($C18="","",$C18) -> Huishouden
C26: Huisdieren | O26: =IF($C19="","",$C19) -> Abonnementen & media
C27: Schulden & aflossingen | O27: =IF($C20="","",$C20) -> Sport & fitness
C28: Sparen & reserveringen | O28: =IF($C21="","",$C21) -> Vrije tijd & uitjes
C29: Zakelijk | O29: =IF($C22="","",$C22) -> Vakantie & reizen
... C31: Overig | O31: =IF($C24="","",$C24) -> Kinderen & alimentatie
O32: =IF($C25="","",$C25) -> Giften & goede doelen
O33: =IF($C26="","",$C26) -> Huisdieren
O34: =IF($C27="","",$C27) -> Schulden & aflossingen
O35: =IF($C28="","",$C28) -> Sparen & reserveringen
O36: =IF($C29="","",$C29) -> Zakelijk
O37: =IF($C30="","",$C30) -> Onvoorzien
A38: Let op: het Dashboard leest de categorielijsten op volgorde. Voeg nieuwe categorieën onderaan een lijst toe, | O38: =IF($C31="","",$C31) -> Overig
A39: anders schuiven de variabele budgetten op het Dashboard mee met de rijen. | O39: =IF($C32="","",$C32)
O40: =IF($C33="","",$C33)
O41: =IF($C34="","",$C34)
O42: =IF($C35="","",$C35)
O44: Niet aanpassen — vult zichzelf.
